Workbook
Name _xlchart.v5.1: #REF!
Name _xlchart.v5.2: #REF!
Name _xlchart.v5.6: #REF!
Name _xlchart.v5.5: #REF!
Name _xlchart.v5.7: #REF!
Name _xlchart.v5.0: #REF!
Name _xlchart.v5.3: #REF!
Name _xlchart.v5.4: #REF!
Name _xlchart.v5.9: #REF!
Name _xlchart.v5.8: #REF!

Sheet SWAP_Connections
A1: state | B1: name | C1: agency | D1: type | E1: notes
A2: Alabama | B2: Paul Johnson | C2: Alabama Department of Conservation and Natural Resources ADCNR | D2: state
A3: Alabama | B3: Kevin Anson | C3: Alabama Department of Conservation and Natural Resources ADCNR | D3: state
A4: Alabama | B4: Eric Soehren | C4: Alabama Department of Conservation and Natural Resources ADCNR | D4: state
A5: Alabama | B5: Jo Lewis | C5: Alabama Department of Conservation and Natural Resources ADCNR | D5: state
A6: Alabama | B6: Courtney Norman | C6: Alabama Department of Conservation and Natural Resources ADCNR | D6: state
A7: Alabama | B7: Ashley Peters | C7: Alabama Department of Conservation and Natural Resources ADCNR | D7: state
A8: Alabama | B8: Forrest Bailey | C8: Alabama Department of Conservation and Natural Resources ADCNR | D8: state
A9: Alabama | B9: Chuck Sykes | C9: Alabama Department of Conservation and Natural Resources ADCNR | D9: state
A10: Alabama | B10: Jim Schrenkel | C10: Alabama Department of Conservation and Natural Resources ADCNR | D10: state
A11: Alabama | B11: Casey Norris | C11: Alabama Department of Conservation and Natural Resources ADCNR | D11: state
A12: Alabama | B12: Nick Nichols | C12: Alabama Department of Conservation and Natural Resources ADCNR | D12: state
A13: Alabama | B13: Stan Cook | C13: Alabama Department of Conservation and Natural Resources ADCNR | D13: state
... A207: Alaska | B207: Kathy Lepley | C207: Galaxy Graphics | D207: business
A208: Alaska | C208: Alaska Natural Heritage Program UAA | D208: school
A209: Alaska | C209: Audubon Alaska | D209: ngo-nongame
A210: Alaska | C210: Juneau Audubon | D210: ngo-nongame
A211: Alaska | C211: US Fish and Wildlife Service USFWS | D211: federal
A212: Alaska | C212: Pacific Coast Joint Venture | D212: partnership
A213: Alaska | C213: US Geological Survey USGS | D213: federal
A214: Alaska | C214: National Park Service | D214: federal
A215: Alaska | C215: Alaska Fish Habitat Partnerships | D215: partnership
A216: Alaska | C216: American Fisheries Society Alaska Chapter | D216: ngo-consumptive
A217: Alaska | C217: University of Alaska Fairbanks | D217: school
A218: Alaska | C218: Boreal Partners in Flight | D218: partnership
A219: Alaska | C219: Alaska Raptor Group | D219: partnership
... A222: Alaska | C222: Association of Fish and Wildlife Agencies | D222: ngo-consumptive
A223: Arizona | B223: Joyce Francis | C223: Arizona Game and Fish Department AZGFD | D223: state
A224: Arizona | B224: Charles Hofer | C224: Arizona Game and Fish Department AZGFD | D224: state
A225: Arizona | B225: Matthew King | C225: Arizona Game and Fish Department AZGFD | D225: state
A226: Arizona | B226: Tiffany Finke | C226: Arizona Game and Fish Department AZGFD | D226: state
A227: Arizona | B227: Josh Avey | C227: Arizona Game and Fish Department AZGFD | D227: state
A228: Arizona | B228: Michael Barbour | C228: Arizona Game and Fish Department AZGFD | D228: state
A229: Arizona | B229: Zach Beard | C229: Arizona Game and Fish Department AZGFD | D229: state
A230: Arizona | B230: Erin Butler | C230: Arizona Game and Fish Department AZGFD | D230: state
A231: Arizona | B231: Chris Cantrell | C231: Arizona Game and Fish Department AZGFD | D231: state
A232: Arizona | B232: Julie Carter | C232: Arizona Game and Fish Department AZGFD | D232: state
A233: Arizona | B233: Barbara Cook | C233: Arizona Game and Fish Department AZGFD | D233: state
A234: Arizona | B234: Jom Cooley | C234: Arizona Game and Fish Department AZGFD | D234: state
... A300: Arizona | B300: Tim Howard | C300: Research Foundation for The State University of New York Environmental Science and Forestry SUNY | D300: school
A301: Arizona | C301: Altar Valley Conservation Alliance | D301: ngo-nongame
A302: Arizona | C302: Arizona State University | D302: school
A303: Arizona | C303: ASARCO | D303: business
A304: Arizona | C304: Audubon Arizona | D304: ngo-nongame
A305: Arizona | C305: Be Outdoors Arizona | D305: ngo-nongame
A306: Arizona | C306: Big Sandy NRCD | D306: state
A307: Arizona | C307: Borderlands Restoration Network | D307: ngo-nongame
A308: Arizona | C308: US Bureau of Land Management | D308: federal
A309: Arizona | C309: City of Flagstaff | D309: local
A310: Arizona | C310: City of Peoria | D310: local
A311: Arizona | C311: Federal Highway Administration | D311: federal
A312: Arizona | C312: Fort Huachuca | D312: federal
... A340: Arizona | C340: Yuma Crossing National Heritage Area | D340: federal
A341: Arkansas | B341: Allison Fowler | C341: Arkansas Game and Fish Commission | D341: state
A342: Arkansas | B342: Jane Anderson | C342: Arkansas Game and Fish Commission | D342: state
A343: Arkansas | B343: Ricky Chastain | C343: Arkansas Game and Fish Commission | D343: state
A344: Arkansas | B344: Brad Carner | C344: Arkansas Game and Fish Commission | D344: state
A345: Arkansas | B345: Chris Racey | C345: Arkansas Game and Fish Commission | D345: state
A346: Arkansas | B346: Melvin Tobin | C346: US Fish and Wildlife Service USFWS | D346: federal
A347: Arkansas | B347: Scott Simon | C347: The Nature Conservancy | D347: ngo-nongame
A348: Arkansas | B348: Chris Colclasure | C348: The Arkansas Natural Heritage Commission | D348: state
A349: Arkansas | B349: AJ Riggs | C349: Arkansas Game and Fish Commission | D349: state
A350: Arkansas | B350: Eric Brinkman | C350: Arkansas Game and Fish Commission | D350: state
A351: Arkansas | B351: Chris Davidson | C351: US Fish and Wildlife Service USFWS | D351: federal
A352: Arkansas | B352: Dan Schiemna | C352: Audubon Arkansas | D352: ngo-nongame
... A682: California | B682: Eric Wilkins | C682: California Department of Fish and Wildlife | D682: state
A683: Colorado | E683: Page 406 lists number of representatives from types of agencies
A684: Colorado | C684: Adams County Parks Department | D684: local
A685: Colorado | C685: Rio Grande Headwaters Land Trust | D685: ngo-nongame
A686: Colorado | C686: River Otter Alliance | D686: ngo-nongame
A687: Colorado | C687: Roaring Fork Conservancy | D687: ngo-nongame
A688: Colorado | C688: Rocky Mountain Bighorn Society | D688: ngo-nongame
A689: Colorado | C689: Rocky Mountain Bird Observatory | D689: ngo-nongame
A690: Colorado | C690: Rocky Mountain Climate Organization | D690: ngo-nongame
A691: Colorado | C691: Rocky Mountain Elk Foundation | D691: ngo-consumptive
A692: Colorado | C692: Rocky Mountain Recreation Initiative | D692: ngo-consumptive
A693: Colorado | C693: Rocky Mountain Wild | D693: ngo-nongame
A694: Colorado | C694: Roe Ecological Services | D694: business
A695: Colorado | C695: San Isabel Land Protection Trust | D695: ngo-nongame
... A837: Colorado | C837: Quiet Use Coalition | D837: ngo-nongame
A838: Connecticut | E838: Chapter 8 lists participation from types of audience
A839: Connecticut | C839: Connecticut National Guard Armory | D839: state
A840: Connecticut | C840: US Army Aviation Support, Bradley International Airport | D840: federal
A841: Connecticut | C841: US Coast Guard | D841: federal
A842: Connecticut | C842: US Naval Submarine Base | D842: federal
A843: Connecticut | C843: Connecticut Animal Control Division | D843: state
A844: Connecticut | C844: Connecticut Shellfish and Aquaculture Program | D844: state
A845: Connecticut | C845: Connecticut Conservation Advisory Council | D845: state
A846: Connecticut | C846: Connecticut Fisheries Advisory Council | D846: state
A847: Connecticut | C847: Connecticut Soil and Water Conservation Districts | D847: state
A848: Connecticut | C848: The Connecticut Open Space Initiative | D848: state
A849: Connecticut | C849: Mashantucket Pequot Tribal Nation | D849: indigenous
A850: Connecticut | C850: Mohegan Tribal Nation | D850: indigenous
... A866: Connecticut | C866: Green Valley Institute (UConn and UMass partnership) | D866: school
A867: Connecticut | C867: Hartford Sportsmen Club
A868: Connecticut | C868: Maritime Aquarium at Norwalk | D868: ngo-nongame
A869: Connecticut | C869: Mystic Aquarium | D869: ngo-nongame
A870: Connecticut | C870: National Wildlife Federation | D870: ngo-nongame
A871: Connecticut | C871: Rivers Alliance Connecticut | D871: ngo-consumptive
A872: Connecticut | C872: The Jonah Center for Earth and Art | D872: ngo-nongame
...

Sheet All Agencies by State
A1: Alabama | B1: Alaska | C1: Arizona | D1: Arkansas | E1: California | F1: Colorado | G1: Connecticut | H1: Delaware | I1: Florida | J1: Georgia | K1: Hawaii | L1: Idaho | M1: Illinois | N1: Indiana | O1: Iowa | P1: Kansas | Q1: Kentucky | R1: Louisiana | S1: Maine | T1: Maryland | U1: Massachusetts | V1: Michigan | W1: Minnesota | X1: Mississippi | Y1: Missouri | Z1: Montana | AA1: Nebraska | AB1: Nevada | AC1: New Hampshire | AD1: New Jersey | AE1: New Mexico | AF1: North Carolina | AG1: North Dakota | AH1: Oklahoma | AI1: Oregon | AJ1: Pennsylvania | AK1: Rhode Island | AL1: South Carolina | AM1: South Dakota | AN1: Tennessee | AO1: Texas | AP1: Utah | AQ1: Vermont | AR1: Virginia | AS1: Washington | AT1: West Virginia | AU1: Wisconsin | AV1: Wyoming
A2: Alabama Clean Water Partnership | B2: Action Plan Coordinators from Idaho and Washington | C2: Altar Valley Conservation Alliance | D2: Arkansas Department of Environmental Quality | E2: Ascent Environmental, Inc | F2: Adams County Parks Department | G2: Appalachian Trail Conservancy | H2: Alexander Environmental Consulting | I2: American Museum of Natural History | J2: Abraham Baldwin Agricultural College | K2: Bishop Museum | L2: Boise State University, Intermountain Bird Observatory | M2: Association of Illinois Soil and Water Conservation Districts | N2: Ducks Unlimited | O2: American Fisheries Society | P2: Audubon Society | Q2: Asbury University | R2: Acadiana Park Nature Station | S2: Acadia National Park | T2: American Bird Conservancy | U2: Cape Cod Cranberry Growers Association | V2: Adrian College | W2: Audubon Minnesota | X2: 25x25 Alliance | Y2: American Bird Conservancy | Z2: American Wildlands | AA2: Audubon Society of Omaha | AB2: Arizona Game and Fish Department AZGFD | AC2: Antioch University New England | AD2: Atlantic City Electric | AE2: Arizona Game and Fish Department AZGFD | AF2: Appalachian State University | AG2: North Dakota Game and Fish Department | AH2: Cameron University | AI2: American Bird Conservancy | AJ2: American Fisheries Society | AK2: American Fisheries Society | AL2: Agriculture Canada | AM2: Badlands National Park | AN2: Arnold Air Force Base | AO2: Texas Parks and Wildlife Department | AP2: Bureau of Land Management | AQ2: Audubon Vermont | AR2: Accomack/Northampton Planning District Commission | AS2: Audubon Washington | AT2: Alabama Department of Conservation and Natural Resources ADCNR | AU2: All Things Wild Consulting | AV2: Association of Conservation Districts
A3: Alabama Cooperative Wildlife Unit | B3: Alaska Department of Fish and Game | C3: Arizona Game and Fish Department AZGFD | D3: Arkansas Game and Fish Commission | E3: Blue Earth Consultants | F3: Adams State College | G3: Aquarion Water Company | H3: Delaware Department of Agriculture | I3: Florida Department of Agriculture and Consumer Services | J3: Alabama Aquatic Biodiversity Center | K3: Hawaii Department of Land and Natural Resources | L3: College of Idaho | M3: Bird Conservation Network | N3: Duke Energy | O3: Buena Vista University | P3: Central Plains Society of Mammalogists | Q3: Austin Peay State University | R3: Audubon Institute | S3: Appalacian Conservation Biology | T3: Ann Arundel County Department of Recreation and Parks | U3: Charles River Watershed Association | V3: Alma College | W3: Consultant | X3: Audubon Mississippi | Y3: American Fisheries Society | Z3: Bureau of Land Management | AA3: Audubon Spring Creek Prairie | AB3: Bureau of Land Management | AC3: Appalachian Mountain Club | AD3: Buttonbush Design and Delineation | AE3: Arizona State University | AF3: Auburn University | AH3: Central Hardwoods Joint Venture | AI3: Association of Northwest Steelheaders | AJ3: American Rivers | AK3: American Heritage Rivers | AL3: Alderman Environmental Services | AM3: Black Hills State University | AN3: Austin Peay State University | AO3: University of Texas | AP3: Hawkwatch International | AQ3: Birds of Vermont Museum | AR3: Appalachian Landscape Conservation Cooperative | AS3: Black Hills Audubon | AT3: American University | AU3: Audubon Society | AV3: Audubon Wyoming
A4: Alabama Department of Conservation and Natural Resources ADCNR | B4: Alaska Fish Habitat Partnerships | C4: Arizona State University | D4: Arkansas Highway and Transportation Department | E4: Bureau of Land Management | F4: Audubon Society of Greater Denver | G4: Atlantic Coast Joint Venture | H4: Delaware Department of Natural Resources and Environmental Control | I4: Florida Department of Environmental Protection | J4: Appalachian State University | K4: Hawaii Institute of Marine Biology | L4: Defenders of Wildlife | M4: Boone County Conservation District | N4: Eppley Institute for Parks and Lands | O4: Butterfliz of Iowa | P4: Ducks Unlimited | Q4: Berea College | R4: Barataria-Terrebonne National Estuary | S4: Aroostook Band of MicMac Indians | T4: Audubon Maryland | U4: Conservation Law Foundation | V4: Central Michigan University | W4: Minnesota Department of Natural Resources | X4: Bureau of Land Management | Y4: American Tree Farm System | Z4: Center for Large Landscape Conservation | AA4: Breeding Bird Atlas | AB4: Great Basin Bird Observatory | AC4: Blue Ocean Society | AD4: Cape May National Wildlife Refuge | AE4: Audubon New Mexico | AF4: Audubon North Carolina | AH4: Cherokee Nation | AI4: Association of Oregon Counties | AJ4: American University | AK4: Applied Bio-Systems | AL4: Alligator Adventure | AM4: Bureau of Indian Affairs | AN4: Belmont University | AP4: Hill Air Force Base | AQ4: Consultant | AR4: Appalachian Mountain Joint Venture | AS4: Cascadia Partner Forum | AT4: Appalachian Mountain Joint Venture | AU4: Bad River Band | AV4: BP America
A5: Alabama Department of Environmental Management | B5: Alaska Natural Heritage Program UAA | C5: ASARCO | D5: Arkansas Natural Heritage Commission | E5: California Department of Fish and Wildlife | F5: Audubon Colorado | G5: Atlantic States Marine Fisheries Commission | H5: Delaware Museum of Natural History | I5: Florida Fish and Wildlife Conservation Commission | J5: Atlanta Audubon Society | K5: Hawaii Invasive Species Council | L5: Foundations of Success | M5: Byron Forest Preserve District | N5: Indiana Department of Environmental Management | O5: Consultant | P5: Environmental Division Fort Riley | Q5: Big South Fork National River and Recreation Area | R5: Bird Study Group | S5: Atlantic Salmon Federation | T5: Bowie State University | U5: Environmental League of Massachusetts | V5: Clinton River Watershed Council | W5: Minnesota Dragonfly Society | X5: Delta Wildlife | Y5: Animal and Plant Health Inspection Service | Z5: Defenders of Wildlife | AA5: Central College Iowa | AB5: Kearns and West | AC5: Connecticut Department of Energy and Environmental Protection | AD5: Conserve Wildlife Foundation of New Jersey | AE5: Bat Conservation International | AF5: Belize Foundation for Research and Environmental Education | AH5: East Central Oklahoma University | AI5: Audubon Society of Portland | AJ5: Atlas of Pennsylvania Butterflies | AK5: Atlantic Coast Fish Habitat Partnership Committee | AL5: Auburn University | AM5: Bureau of Land Management | AN5: Clinch-Powell Resource Conservation and Development Council | AP5: National Park Service | AQ5: Cougar Rewilding Foundation, Northeast Wolf Coalition | AR5: Chesapeake Bay Conservancy | AS5: EcoAdapt | AT5: Brooks Bird Club | AU5: Beaver Creek Nature Center | AV5: British Petroleum
A6: Alabama Department of Transportation | B6: Alaska Raptor Group | C6: Association of Environmental Professionals | D6: Arkansas State University | E6: California Department of Forestry and Fire Protection | F6: Back Country Hunters | G6: Audubon Connecticut | H6: Delaware Nature Society | I6: Florida Forest Service | J6: Atlanta Botanical Garden | K6: Hawaii Watershed Partnerships | L6: Gonzales-Stoller Surveillance, LLC | M6: Carroll County Soil and Water Conservation District | N6: Indiana Department of Natural Resources | O6: Drake University | P6: Fort Hays State University | Q6: Bluegrass Woodland | R6: Centenary Colllege of Louisiana | S6: Baxter State Park | T6: Calvert County Natural Resources Division | U6: Massachusetts Audubon | V6: Detroit Zoo | W6: Minnesota Odonata Survey Project | X6: Ducks Unlimited | Y6: Audubon Society of Missouri | Z6: Intermountain Joint Venture | AA6: Central Platte Natural Resources District | AB6: NatureServe | AC6: Consultant | AD6: D&R Greenway Land Trust | AE6: Big Picture Conservation | AF6: Catawba Land Conservancy | AH6: Emporia State University | AI6: Bureau of Indian Affairs | AJ6: Audubon Pennsylvania | AK6: Atlantic States-Rural Waters Association, Rose Island Lighthouse Foundation | AL6: Avian Research and conservation Institute | AM6: Bureau of Reclamation | AN6: Conservation Fisheries Inc | AP6: Natural Resources Conservation Service NRCS | AQ6: First Vermont Bird Atlas | AR6: Crater Planning District Commission | AS6: North Pacific Landscape Conservation Cooperative | AT6: Canaan Valley Institute | AU6: Carroll University | AV6: Bureau of Land Management
A7: Alabama Forestry Commission | B7: Alaska Shorebird Group | C7: Audubon Arizona | D7: Arkansas Tech University | E7: California Invasive Plant Council | F7: Betty Ford Alpine Gardens | G7: Beardsley Zoological Gardens | H7: Delaware State University | I7: Florida Forestry Association | J7: Auburn University | K7: HT Harvey and Associates | L7: Great Basin Landscape Conservation Cooperative | M7: Champaign County Forest Preserve District | N7: Indiana Department of Transportation | O7: Ducks Unlimited | P7: Friends of Kaw, Kansas Riverkeeper | Q7: Clarks River National Wildlife Refuge | R7: Center of Excellence COE | S7: Biodiversity Research Institute | T7: Coastal Resources Inc | U7: Massachusetts Division of Fisheries and Wildlife | V7: Ducks Unlimited | W7: Minnesota Ornithologists Union | X7: Grand Bay National Estuarine Research Reserve | Y7: Central Hardwoods Joint Venture | Z7: Montana Audubon | AA7: Chadron State College | AB7: Nevada Department of Wildlife | AC7: CrossCurrent Communications | AD7: Edwin B Forsythe National Wildlife Refuge | AE7: Black Hills State University | AF7: Clean Water Management Trust Fund | AH7: Fort Sill Military Reservation | AI7: City of Salem | AJ7: Audubon Society of Western Pennsylvania | AK7: Audubon Society | AL7: Cape Romain Bird Observatory | AM7: Cheyenne River Sioux Tribe | AN7: Cumberland Region Tomorrow | AP7: Round River Conservation Studies | AQ7: Green Mountain College | AR7: Eastern Brook Trout Joint Venture | AS7: Northwest Climate Science Center | AT7: Carnegie Museum of Natural History | AU7: Chadron State University | AV7: Carbon County Weed and Pest Medicine Bow Conservation District
A8: Alabama Geological Survey | B8: American Fisheries Society Alaska Chapter | C8: Audubon Southwest | D8: Audubon Arkansas | E8: California Native Plant Society | F8: BIO-Logic, Inc | G8: Connecticut Agricultural Experiment Station | H8: Lenape Tribe | I8: Florida Natural Areas Inventory | J8: Augusta Chronicle | K8: National Park Service | L8: Greater Yellowstone Coalition | M8: Chicago Academy of Sciences | N8: Indiana Farm Bureau | O8: E Resources Group | P8: Grassland Heritage Foundation | Q8: Copperhead Consulting | R8: Gulf Coast Joint Venture | S8: Brunswick-Topsham Land Trust | T8: Cornell University, eBird | U8: Massachusetts Rivers Alliance | V8: Eastern Michigan University | W8: Minnesota Zoo | X8: Gulf Coast Joint Venture | Y8: Conservation Federation of Missouri | Z8: Montana Fish, Wildlife and Parks | AA8: Concordia University | AB8: Nevada Division of Forestry | AC8: Ecosystem Management Consultants | AD8: ENSAC Endangered and Nongame Species Advisory Committee | AE8: Consultant | AF8: Clemson University | AH8: Gulf Coastal Prairies Landscape Conservation Cooperative | AI8: Clackamas Soil and Water Conservation District | AJ8: Bucknell University | AK8: Audubon Society of Rhode Island | AL8: Central Florida University | AM8: Crow Creek Sioux Tribe | AN8: Cumberland University | AP8: The Nature Conservancy | AQ8: Lake Champlain Basin Program | AR8: George Washington National Forest | AS8: Pacific Coast Joint Venture | AT8: Coalition of West Virginia Land Trusts | AU8: Chicago Field Museum | AV8: City of Cheyenne
A9: Alabama Power Company | B9: Association of Fish and Wildlife Agencies | C9: Be Outdoors Arizona | D9: Beaver Water District | E9: Catalina Conservancy | F9: Black Canyon Regional Land Trust | G9: Connecticut Animal Control Division | H9: Sarver Ecological | I9: Florida Power and Light Company | J9: Avian Research and conservation Institute | K9: Pacific Islands Climate Change Cooperative | L9: Idaho Cattle Association | M9: Chicago Wilderness | N9: Indiana Forest and Woodland Owners Association | O9: EarthTech | P9: Kansas Alliance for Wetlands and Streams | Q9: Cumberlands University | R9: Kentucky Department of Fish and Wildlife Resources | S9: Casco Bay Estuary Partnership | T9: Delmarva Low Impact Tourism Experiences | U9: Massachusetts Water Resources Authority | V9: Fisheries and Oceans Canada | W9: Ornithologist | X9: Gulf Coastal Plains and Ozarks Landscape Conservation Cooperative | Y9: Ducks Unlimited | Z9: Montana Natural Heritage Program | AA9: Congressmen Tom Osborne Office | AB9: Nevada Division of Natural Heritage | AC9: Great Bay National Estuarine Research Reserve | AD9: Great Egg Harbor Watershed Association | AE9: Furman University | AF9: Conservation Trust for North Carolina | AH9: Natural Resources Conservation Service NRCS | AI9: Coalition of Oregon Land Trusts | AJ9: Butterflies and Moths of North America | AK9: Block Island Bird Banding Station | AL9: Charleston Turtle and Tortoise Society | AM9: Ecosystem Management Research Institute | AN9: East Tennessee State University | AP9: US Army Dugway Proving Ground | AQ9: National Wildlife Federation | AR9: George Washington Planning District Commission | AS9: US Fish and Wildlife Service USFWS | AT9: Columbus Zoo | AU9: Consultant | AV9: Consultant
A10: Alabama Water Watch Auburn University | B10: Audubon Alaska | C10: Big Sandy NRCD | D10: Consultant | E10: Center for Collaborative Policy - California State University, Sacramento | F10: Boulder County | G10: Connecticut Audubon | H10: Terwilliger Consulting | I10: Florida Southern College | J10: A-Z Animals | K10: The Nature Conservancy | L10: Idaho Department of Fish and Game | M10: Clifftop Alliance | N10: Indiana Land Protection Allinace | O10: Harrison County Conservation Board | P10: Kansas Applied Remote Sensing Program | Q10: Daniel Boone National Forest | R10: Louisiana Asset Management Pool | S10: Coastal Mountains Land Trust | T10: Environmental Regulations Consultant Inc | U10: Massachusetts Water Works Association | V10: Friends of the Rouge | W10: Science Museum of Minnesota | X10: Gulf Restoration Network | Y10: Forest and Woodland Association of Missouri | Z10: National Park Service | AA10: DeSoto National Wildlife Refuge | AB10: New York Natural Heritage Program | AC10: High Branch Conservation Services | AD10: Great Swamp National Wildlife Refuge | AE10: National Park Service | AF10: Davidson College | AH10: Northeastern Oklahoma State University | AI10: Confederated Tribes of Coos, Lower Umpqua, and Suislaw Indians | AJ10: California University of Pennsylvania | AK10: Brook Trout Forever | AL10: Clemson University | AM10: Flandreau Santee Sioux Tribe | AN10: Fort Campbell Military Installation | AP10: US Fish and Wildlife Service USFWS | AQ10: North Branch Nature Center | AR10: Hampton Roads Planning District Commission | AS10: US Forest Service USFS | AT10: George Washington National Forest | AU10: Driftless Land Stewards | AV10: Defenders of Wildlife
A11: Alabama Wildlife Federation | B11: Boreal Partners in Flight | C11: Borderlands Restoration Network | D11: Henderson State University | E11: Central Valley Joint Venture | F11: Boulder County Audubon | G11: Connecticut College | H11: University of Delaware | I11: Florida Wildlife Legacy Initiative | J11: Captain Planet Foundation | K11: University of Hawaii | L11: Idaho Department of Lands | M11: Conservation Technologies | N11: Indiana State Department of Agriculture | O11: Hawkeye Flyfishing Association | P11: Kansas Biological Survey | Q11: Eastern Kentucky University | R11: Louisiana Department of Enviromental Quality | S11: Conservation Law Foundation | T11: FrogWatch USA | U11: The Nature Conservancy | V11: Golden-winged Warbler Conservation Initiative | W11: The Nature Conservancy | X11: Land Trust Alliance | Y11: Gulf Coastal Plains and Ozarks Landscape Conservation Cooperative | Z11: National Wildlife Federation | AA11: Ducks Unlimited | AB11: Pyramid Lake Paiute Tribe | AC11: Loon Preservation Committee | AD11: Monmouth Conservation Foundation | AE11: Natural Heritage New Mexico | AF11: Duke (Progress) Energy | AH11: Oaks and Prairies Joint Venture | AI11: Confederated Tribes of Siletz Indians of Oregon | AJ11: Carnegie Museum of Natural History | AK11: Brown University | AL11: Coastal Carolina University | AM11: Jewel Cave National Park | AN11: Freed Hardeman University | AP11: US Forest Service USFS | AQ11: Northwoods Stewardship Center | AR11: Middle Peninsula Planning District Commission | AS11: Washington Department of Fish and Wildlife | AT11: Marshall University | AU11: Ducks Unlimited | AV11: Encana
A12: Auburn University | B12: Galaxy Graphics | C12: Bureau of Land Management | D12: Lower Mississippi Valley Joint Venture | E12: Conservation Biology Institute | F12: Boulder County Nature Association | G12: Connecticut Conservation Advisory Council | H12: US Fish and Wildlife Service USFWS | I12: University of Florida | J12: CCR Environmental Consulting | K12: US Fish and Wildlife Service USFWS | L12: Idaho Governor's Office of Species Conservaiton | M12: Ducks Unlimited | N12: Indiana Wildlife Federation | O12: Ida County Conservation Board | P12: Kansas Cooperative Fish and Wildlife Research Unit | Q12: Fort Knox | R12: Louisiana Department of Wildlife and Fisheries | S12: Cornell University | T12: Frostburg State University | U12: Unnamed environmental law expert | V12: Grand Traverse Band of Ottawa and Chippewa Indians | W12: The Wildlife Society | X12: Land Trust for the Mississippi Coastal Plain | Y12: L-A-D Foundation | Z12: Natural Resources Conservation Service NRCS | AA12: Educator | AB12: The Nature Conservancy | AC12: Maine Department of Inland Fisheries and Wildlife | AD12: Monmouth County Audubon Society | AE12: New Mexico Audubon | AF12: Freshwater Mollusk Conservation Society | AH12: Oklahoma Conservation Commission | AI12: Confederated Tribes of the Grand Ronde | AJ12: Chesapeake Bay Foundation | AK12: Caputo and Wick LTD | AL12: Coastal Georgia Community College | AM12: Lower Brule Sioux Tribe | AN12: Gulf Coastal Plains and Ozarks Landscape Conservation Cooperative | AP12: Utah Department of Natural Resources | AQ12: Norwich University | AR12: National Park Service | AS12: Washington Department of Natural Resources | AT12: Monongahela National Forest | AU12: Forest County Potawatomi | AV12: E-Quant Consulting
A13: Birmingham-Southern College | B13: Juneau Audubon | C13: City of Flagstaff | D13: Mitigation Surveying Services, LLC | E13: Defenders of Wildlife | F13: Boulder County Parks & Open Space | G13: Connecticut Department of Agriculture | H13: US Geological Survey USGS | I13: US Fish and Wildlife Service USFWS | J13: Chattahoochee/Oconee National Forest | K13: US Geological Survey USGS | L13: Idaho State Department of Agriculture | M13: Forest Preserve District of Cook County | N13: Natural Resources Conservation Service NRCS | O13: Iowa Audubon | P13: Kansas Department of Health and Environment | Q13: Illinois Natural History Survey | R13: Louisiana Fauna Project | S13: Defenders of Wildlife | T13: Garrett College | U13: Unnamed expert in sustainable business | V13: Grand Traverse Regional Land Conservancy | W13: Three Rivers Parks District | X13: Louisiana Department of Wildlife and Fisheries | Y13: Mark Twain National Forest | Z13: The Nature Conservancy | AA13: Farmers Union | AB13: US Fish and Wildlife Service USFWS | AC13: Massachusetts Natural Heritage and Endangered Species Program | AD13: Monmouth County Park System | AE13: New Mexico Department of Game and Fish | AF13: Georgia College | AH13: Oklahoma Department of Environmental Quality | AI13: Confederated Tribes of the Umatilla Indian Reservation | AJ13: Clyde Peelings Reptiland | AK13: Coastal Resources Management Council | AL13: College of Charleston | AM13: National Park Service | AN13: K Gregg Consulting | AP13: Utah Division of Wildlife Resources | AQ13: Sain Michaels College | AR13: Natural Resources Conservation Service NRCS | AS13: Wildlife Diversity Advisory Council | AT13: National Audubon Society | AU13: Fort McCoy | AV13: Fremont County Weed and Pest
A14: Conservation Southeast | B14: National Park Service | C14: City of Peoria | D14: National Park Service | E14: Delta Conservancy | F14: Bureau of Land Management | G14: Connecticut Department of Economic and Community Development | I14: US Geological Survey USGS | J14: Clayton State University | K14: US National Oceanic and Atmospheric Administration NOAA | L14: Idaho State University | M14: Forest Preserve District of Dupage County | N14: Pheasants Forever | O14: Iowa Coop Unit | P14: Kansas Department of Wildlife and Parks | Q14: Kentucky Department of Fish and Wildlife Resources | R14: Louisiana State University | S14: Downeast Lakes Land Trust | T14: Interstate Commission on the Potomac River Basin | U14: Unnamed municipal public works managers | V14: Gratiot Conservation District | W14: University of Minnesota | X14: Lower Mississippi Valley Joint Venture | Y14: Missouri Association of Soil and Water Conservation Districts | Z14: The Wilderness Society | AA14: Fontenelle Nature Association | AB14: US Forest Service USFS | AC14: National Oceanic and Atmospheric Administration NOAA | AD14: Monmouth University | AE14: New Mexico Environment Department | AF14: Georgia Museum of Natural History | AH14: Oklahoma Department of Transportation | AI14: Confederated Tribes of Warm Springs | AJ14: College of Charleston | AK14: Consultant | AL14: Colorado State University | AM14: Natural Resources Conservation Service NRCS | AN14: Knoxville Zoological Gardens | AP14: Utah Farm Bureau Federation | AQ14: Terwilliger Consulting | AR14: North Atlantic Landscape Conservation Cooperative | AT14: Natural Resources Conservation Service NRCS | AU14: Gathering Waters | AV14: Invenergy LLC
A15: Coosa Riverkeeper | B15: Pacific Coast Joint Venture | C15: Creative Resource Strategies | D15: Northwest Arkansas Land Trust | E15: Eremico | F15: Bureau of Reclamation | G15: Connecticut Department of Energy and Environmental Protection | I15: ZooTampa | J15: Clemson University | L15: Latah Soil and Water Conservation District | M15: Forest Preserves of Winnebago County | N15: Purdue University | O15: Iowa Cooperative Fish and Wildlife Research Unit | P15: Kansas Forest Service | Q15: Kentucky Division of Water | R15: Louisiana Tech | S15: Downeast Salmon Federation | T15: Maryland Biodiversity Project | U15: Unnamed private engineering firms | V15: Herpetological Resource and Management | W15: US Army Corps of Engineers | X15: Mississippi Band of Choctaw Indians | Y15: Missouri Audubon | Z15: US Fish and Wildlife Service USFWS | AA15: Grassland Foundation | AB15: US Geological Survey USGS | AC15: Natural Resources Conservation Service NRCS | AD15: Morris County Park Commission | AE15: New Mexico Museum of Natural History and Science | AF15: Midwest Biodiversity Institute | AH15: Oklahoma Department of Wildlife Conservation | AI15: Consultant | AJ15: College of New Jersey | AK15: Environmental Protection Agency | AL15: Columbia University | AM15: Nebraska Game and Parks Commission | AN15: Lee University | AP15: Utah State University | AQ15: The Nature Conservancy | AR15: North Virginia Regional Commission | AT15: NatureServe | AU15: Great Lakes Indian Fish and Wildlife Commission | AV15: LS Power
A16: Nongame Conference Amphibian and Reptile Committee | B16: University of Alaska Fairbanks | C16: Federal Highway Administration | D16: Southern Arkansas University | E16: Foundations of Success | F16: City of Boulder Open Space and Mountain Parks | G16: Connecticut Department of Transportation | J16: Columbus State University | L16: National Park Service | M16: Heartlands Conservancy | N16: The Nature Conservancy | O16: Iowa Department of Natural Resources | P16: Kansas Forest Service, Kansas State University | Q16: Kentucky Herpetological Society | R16: Loyola University | S16: Ducks Unlimited | T16: Maryland Bird Conservation Initiative | U16: Unnamed regional planning agencies | V16: Huron River Watershed Council | W16: US Fish and Wildlife Service USFWS | X16: Mississippi Bat Working Group | Y16: Missouri Bird Conservation Initiative | Z16: US Forest Service USFS | AA16: Lincoln Public Schools | AB16: Walker River Paiute Tribe | AC16: New Boston Air Force Base | AD16: National Oceanic and Atmospheric Administration NOAA | AE16: New Mexico State Land Office | AF16: Nash Community College | AH16: Oklahoma Master Naturalists Program | AI16: Defenders of Wildlife | AJ16: Delaware River Basin Commission | AK16: Johnson and Wales University | AL16: Consultant | AM16: Northern Great Plains Joint Venture | AN16: Lincoln Memorial University | AP16: Utah Wildlife in Need | AQ16: University of Vermont | AR16: Northern Neck Planning District Commission | AT16: Northeast Partners in Amphibian and Reptile Conservation | AU16: Milwaukee County Zoo | AV16: National Park Service
A17: Nongame Conference Bird Committee | B17: US Fish and Wildlife Service USFWS | C17: Fort Huachuca | D17: The Arkansas Natural Heritage Commission | E17: National Park Service | F17: City of Fort Collins | G17: Connecticut Fisheries Advisory Council | J17: Conservation Fisheries | L17: Natural Resources Conservation Service NRCS | M17: Huff and Huff | N17: TrendyMinds | O17: Iowa Department of Transportation | P17: Kansas Grazing Lands Coalition | Q17: Kentucky Herpetological Society, Louisville Zoo | R17: McNeese State University | S17: Endangered Species Coalition | T17: Maryland Coastal Bays Program | U17: US Geological Survey USGS | V17: Huron-Clinton Metroparks | W17: Warner Nature Center | X17: Mississippi Chapter of The Wildlife Society | Y17: Missouri Botanical Garden | Z17: Wildlife Conservation Society | AA17: Missouri Department of Conservation | AB17: Xerces Society | AC17: New Hampshire Audubon | AD17: National Park Service | AE17: New Mexico State Parks | AF17: National Bobwhite Conservation Initiative | AH17: Oklahoma Native Plant Society | AI17: Greenbelt Land Trust | AJ17: Delaware Valley College | AK17: Land Management Services | AL17: Culture and Heritage Museums | AM17: Northern Prairies Land Trust | AN17: Middle Tennessee State University | AP17: Wild Utah Project | AQ17: US Fish and Wildlife Service USFWS | AR17: Richmond Regional Planning District Commission | AT17: Northeast State Fish and Wildlife Technical Committee | AU17: Milwaukee Public Museum | AV17: Natural Resources Conservation Service NRCS
A18: Nongame Conference Crayfish Committee | B18: US Geological Survey USGS | C18: Friends of Northern Arizona Forests | D18: The Nature Conservancy | E18: Point Blue Conservation Science | F18: City of Loveland | G18: Connecticut Forest and Park Association | J18: Consultant | L18: Nez Perce Soil and Water Conservation District | M18: Illinois Audubon Society | N18: US Fish and Wildlife Service USFWS | O18: Iowa Environmental Council | P18: Kansas Native Plant Society | Q18: Kentucky Native Plant Society | R18: Mississippi State University | S18: Forest Society of Maine | T18: Maryland Department of Natural Resources | V18: Jackson County Conservation District | X18: Mississippi Department of Environmental Quality | Y18: Missouri Caves and Karst Conservancy | AA18: National Park Service | AC18: New Hampshire Department of Environmental Services | AD18: Natural Resources Conservation Service NRCS | AE18: New Mexico State University | AF18: National Oceanic and Atmospheric Administration NOAA | AH18: Oklahoma Natural Heritage Inventory | AI18: Institute for Applied Ecology | AJ18: Dickinson College | AK18: Lloyd Center for Environmental Studies | AL18: Davidson College | AM18: Northern State University | AN18: Midwest Biodiversity Institute | AQ18: Vermont Agency of Transportation | AR18: South Atlantic Landscape Conservation Cooperative | AT18: Oglebay Institute | AU18: Minnesota Department of Natural Resources | AV18: Peabody Energy
A19: Nongame Conference Fishes Committee | C19: Grand Canyon University | D19: University of Arkansas | E19: San Francisco Bay Joint Venture | F19: Clear Creek Land Conservancy | G19: Connecticut Land Conservation Council | J19: Cumberland Island Museum | L19: Nez Perce Tribe | M19: Illinois Chapter of Sierra Club | N19: US Forest Service USFS | O19: Iowa Farm Bureau Federation | P19: Kansas Natural Resource Council | Q19: Kentucky Nature Preserves | R19: National Marine Fisheries Service | S19: GrowSmart Maine | T19: Maryland Department of the Environment | V19: John Ball Zoo | X19: Mississippi Department of Marine Resources | Y19: Missouri Community Forestry Council | AA19: Natural Resources Conservation Service NRCS | AC19: New Hampshire Department of Resources and Economic Development | AD19: New Jersey Audubon Society | AE19: Northern Arizona University | AF19: National Park Service | AH19: Oklahoma Ornithological Society | AI19: Institute for Natural Resources | AJ19: Drexel University | AK19: Mason and Associates | AL19: Edisto Island Serpentarium | AM19: Oglala Sioux Parks and Recreation Authority | AN19: Nashville Metropolitan Planning Organization | AQ19: Vermont Center for Ecostudies | AR19: Southeast Atlantic Slope Mollusk Group | AT19: Oglebay Zoo | AU19: Natural Resources Conservation Service NRCS | AV19: Petroleum Association of Wyoming
A20: Nongame Conference Mammal Committee | C20: Hopi Tribe | D20: University of Arkansas-Little Rock | E20: Sitka Technology | F20: Colorado Beekeepers | G20: Connecticut National Guard Armory | J20: Dalton State College | L20: Northwest Nazarene University | M20: Illinois Chapter of the American Fisheries Society | O20: Iowa Farmers Union | P20: Kansas Ornithological Society | Q20: Kentucky Ornithological Society | R20: National Oceanic and Atmospheric Administration NOAA | S20: Gulf of Maine Research Institute | T20: Maryland Entomological Society | V20: Kalamazoo Nature Center | X20: Mississippi Department of Wildlife, Fisheries and Parks | Y20: Missouri Conservation Heritage Foundation | AA20: Nebraska Alliance for Conservation and Environment Education | AC20: New Hampshire Fish and Game | AD20: New Jersey Conservation Foundation | AE20: Prescott College | AF20: Natural Resources Conservation Service NRCS | AH20: Oklahoma Scenic Rivers Commission | AI20: Intertwine Alliance | AJ20: Duquesne University | AK20: Napatree Conservancy | AL20: Erskine College | AM20: Oglala Sioux Tribe | AN20: Nashville Zoo | AQ20: Vermont Department of Environmental Conservation | AR20: The Nature Conservancy | AT20: Ohio River Islands National Wildlife Refuge | AU20: Northland College | AV20: Rio Tinto Energy of America
A21: Nongame Conference Mussels and Snails Committee | C21: Maricopa County | D21: University of Arkansas-Monticello | E21: The Nature Conservancy | F21: Colorado Cattlemen's Agricultural Land Trust | G21: Connecticut Office of Policy and Management | J21: Dinkins Biological Consulting | L21: Owyhee County | M21: Illinois Department of Agriculture | O21: Iowa Natural Heritage Foundation | P21: Kansas State University | Q21: Kentucky Reptile Zoo | R21: National Park Service | S21: Houlton Band of Maliseet Indians | T21: Maryland Herpetological Society | V21: Kirtlands Warbler Alliance | X21: Mississippi Development Authority | Y21: Missouri Department of Agriculture | AA21: Nebraska Association of Resources Districts | AC21: New Hampshire Natural Heritage | AD21: New Jersey Department of Environmental Protection | AE21: Sierra Club | AF21: North Carolina Department of Agriculture and Consumer Services | AH21: Oklahoma State University | AI21: Klamath Bird Observatory | AJ21: East Stroudsburg University | AK21: Narragansett Bay Estuary Program | AL21: Francis Marion University | AM21: Prairie Pothole Joint Venture | AN21: National Park Service | AQ21: Vermont Fish and Wildlife Department | AR21: US Department of Defense DOD | AT21: The Conservation Fund's Freshwater Institute | AU21: Ozaukee County | AV21: Rocky Mountain Elk Foundation
A22: North River Watershed, University of Alabama | C22: Matrix Design Group | D22: University of Central Arkansas | E22: Trout Unlimited | F22: Colorado Coalition of Land Trusts | G22: Connecticut Ornithological Association | J22: Ecological Solutions | L22: Potlatch Forest Holdings, Inc. | M22: Illinois Department of Natural Resources | O22: Iowa Natural Resources Commission | P22: Kansas Walleye Association | Q22: Kentucky State University | R22: Nicholls State University | S22: Island Institute | T22: Maryland Ornithological Society | V22: Little Traverse Bay Bands of Odawa Indians | X22: Mississippi Forestry Commission | Y22: Missouri Department of Conservation | AA22: Nebraska Audubon | AC22: Northeast Climate Science Center | AD22: New Jersey Department of Transportation | AE22: Texas Tech University | AF22: North Carolina Department of Environment and Natural Resources | AH22: Olsson Environmental | AI22: League of Oregon Cities | AJ22: Eastern Pennsylvania Coalition of Abandonded Mine Reclamation | AK22: Narragansett Bay National Estuarine Research Reserve | AL22: Furman University | AM22: Rosebud Sioux Tribe | AN22: National Wildlife Federation | AQ22: Vermont Forest Parks and Recreation Department | AR22: US Fish and Wildlife Service USFWS | AT22: The Nature Conservancy | AU22: Red Cliff Band of Lake Superior Chippewas | AV22: Rocky Mountain Power
A23: Poarch Creek Tribe | C23: McDowell Sonoran Preserve | D23: US Army Corps of Engineers | E23: UC Berkeley | F23: Colorado College | G23: Connecticut Professional Timber Producers | J23: Eco-Tech Consultants | L23: POWER Engineers, Inc | M23: Illinois Department of Transportation | O23: Iowa NatureMapping | P23: Kansas Wildlife Federation | Q23: Mammoth Cave National Park | R23: Northwestern State University of Louisiana | S23: Lakes Environmental Association | T23: Mid-Atlantic Invertebrate Field Studies | V23: MIARNG | X23: Mississippi Sandhill Crane National Wildlife Refuge | Y23: Missouri Department of Natural Resources | AA23: Nebraska Bird Partnership | AC23: Shoals Marine Lab | AD23: New Jersey Endangered and Nongame Species Advisory Committee | AE23: Turner Biological | AF23: North Carolina Department of Parks and Recreation | AH23: Ouachita National Forest | AI23: Lewis and Clark College | AJ23: French and Pickering Creeks Conservation Trust | AK23: Narragansett Bay Research Reserve | AL23: Georgia Department of Natural Resources GADNR | AM23: Sisseton-Wahpeton Oyate | AN23: Natural Resources Conservation Service NRCS | AQ23: Vermont Herp Atlas | AR23: US Forest Service USFS | AT23: The World Conservation Union | AU23: Rivers Alliance | AV23: Ruckelshaus Institute of Environment and Natural Resources
A24: Tennessee Valley Authority | C24: National Park Service | D24: US Fish and Wildlife Service USFWS | E24: UC Davis | F24: Colorado Counties Inc. | G24: Connecticut River Gateway Commission | J24: Edwards-Pitman | L24: Shoshone-Bannock Tribes | M24: Illinois Endangered Species Protection Board | O24: Iowa Odonata Society | P24: Konza Prairie Biological Station | Q24: Morehead State University | R24: Southeastern Bat Conservation Network | S24: Main Discovery Museum | T24: National Aquarium in Baltimore | V24: Michigan Association of Conservation Districts | X24: Mississippi Soil and Water Conservation Commission | Y24: Missouri Department of Transportation | AA24: Nebraska Cattlemen | AC24: Society for the Protection of New Hampshire Forests | AD24: New Jersey Fish and Game Council | AE24: University of Arizona | AF24: North Carolina Department of Transportation | AH24: Peoria Nation | AI24: National Oceanic and Atmospheric Administration NOAA | AJ24: Gettysburg College | AK24: Narragansett Chapter of Trout Unlimited | AL24: Greenville Zoo | AM24: South Dakota Department of Agriculture | AN24: Open Space Institute | AQ24: Vermont Land Trust | AR24: Virginia Audubon Society | AT24: Thomas Jefferson National Forest | AU24: Shedd Aquarium | AV24: Sheridan County
A25: Terwilliger Consulting | C25: Navajo Nation Department of Fish and Wildlife | D25: US Forest Service USFS | E25: UC Riverside | F25: Colorado Department of Agriculture | G25: Connecticut River Salmon Association | J25: Enduring Conservation Outcomes | L25: Sitka Technology Group | M25: Illinois Environmental Protection Agency | O25: Iowa Ornithologist Union | P25: Mid-American All-Indian Center | Q25: Murray State University | R25: Southeastern Louisiana University | S25: Maine Aquaculture Association | T25: National Oceanic and Atmospheric Administration NOAA | V25: Michigan Audubon | X25: Mississippi State University | Y25: Missouri Farm Bureau | AA25: Nebraska Corn Board | AC25: St Anselm College | AD25: New Jersey Pinelands Commission | AE25: University of New Mexico | AF25: North Carolina Division of Parks and Recreation | AH25: Rogers State University | AI25: Natural Resources Conservation Service NRCS | AJ25: Hawk Mountain Sanctuary | AK25: Narragansett Indian Tribe | AL25: Indiana University | AM25: South Dakota Department of Environment and Natural Resources | AN25: Shortleaf Pine Initiative | AQ25: Vermont Natural Resources Council | AR25: Virginia Department of Conservation and Recreation | AT25: University of Alabama | AU25: Snapping Linton Ecology | AV25: Sonoran Institute
A26: The Longleaf Alliance | C26: Northern Arizona University | D26: US Geological Survey USGS | E26: US Fish and Wildlife Service USFWS | F26: Colorado Department of Natural Resources | G26: Connecticut River Watershed Association | J26: Flint Riverquarium | L26: Stimson Lumber Company | M26: Illinois Farm Bureau | O26: Iowa Pork Producers Association | P26: National Wild Turkey Federation | Q26: Northern Kentucky University | R26: Texas State University | S26: Maine Army National Guard | T26: Natural History Society of Maryland | V26: Michigan Department of Environmental Quality | X26: Mississippi Wildlife Federation | Y26: Missouri Forest Products Association | AA26: Nebraska Department of Agriculture | AC26: St Paul's School, Northeast Ecological Services | AD26: New Jersey Shellfish Council | AE26: US Army Corps of Engineers | AF26: North Carolina Division of Water Quality | AH26: Sam Noble Oklahoma Museum of Natural History | AI26: Network of Oregon Watershed Councils | AJ26: Indiana University of Pennsylvania | AK26: National Oceanic and Atmospheric Administration NOAA | AL26: Iowa State University | AM26: South Dakota Department of Transportation | AN26: Southeast Aquatic Resources Partnership | AR26: Virginia Department of Environmental Quality | AT26: US Fish and Wildlife Service USFWS | AU26: Southeastern Wisconsin Regional Planning Commission | AV26: The Nature Conservancy
A27: The Nature Conservancy | C27: Phoenix Zoo | E27: US Forest Service USFS | F27: Colorado Department of Transportation | G27: Connecticut Shellfish and Aquaculture Program | J27: Florida Fish and Wildlife Conservation Commission | L27: Teton Regional Land Trust | M27: Illinois Federation for Outdoor Resources | O27: Iowa Prairie Network | P27: Natural Resources Conservation Service NRCS | Q27: Society of Kentucky Lepidopterists | R27: Texas Tech University | S27: Maine Association of Conservation Commissions | T27: Patuxent River Naval Air Station | V27: Michigan Department of Natural Resources | X27: National Park Service | Y27: Missouri Landscape and Nursery Association | AA27: Nebraska Department of Education | AC27: The Nature Conservancy | AD27: New Jersey State Forestry Service | AE27: US Bureau of Land Management | AF27: North Carolina Division of Water Resources | AH27: Smith Environmental Research and Consulting | AI27: Oregon Association of Conservation Districts | AJ27: Interactive Environmental Programs | AK27: National Park Service | AL27: Kentucky Department of Natural Resources | AM27: South Dakota Department of Tribal Relations | AN27: Southeast Missouri State University | AR27: Virginia Department of Forestry | AT27: US Forest Service USFS | AU27: Southern Connecticut State University | AV27: Trout Unlimited
A28: Trutta Consulting | C28: Pima County | E28: US Navy | F28: Colorado Field Ornithologists | G28: Connecticut Soil and Water Conservation Districts | J28: Florida Natural Areas Inventory | L28: The Nature Conservancy | M28: Illinois Forestry Development Council | O28: Iowa Rehabilitators Association | P28: Pheasants Forever and Quail Forever | Q28: Stantec | R28: The Nature Conservancy | S28: Maine Association of Planners | T28: Randolph-Macon College | V28: Michigan Department of Transportation | X28: National Wild Turkey Federation | Y28: Missouri Native Plant Society | AA28: Nebraska Environmental Trust | AC28: University of Massachusetts | AD28: Oysters Crabs and Soft Crabs | AE28: US Bureau of Reclamation | AF28: North Carolina Forest Service | AH28: Southeastern Oklahoma State University | AI28: Oregon Biodiversity Information Center | AJ28: Juniata Valley Audubon | AK28: National Wildlife Federation | AL28: Lander College | AM28: South Dakota Game, Fish and Parks | AN28: Southern Environmental Law Center | AR28: Virginia Department of Game and Inland Fisheries | AT28: Virginia Department of Game and Inland Fisheries | AU28: St Marys University | AV28: University of Wyoming
A29: University of Alabama (student) | C29: Pinal County | F29: Colorado Hawking Club | G29: Connecticut Waterfowlers Association | J29: Fort Gordon Army Base | L29: Trout Unlimited | M29: Illinois Green Industry Association | O29: Iowa State University | P29: Pittsburg State University | Q29: The Nature Conservancy | R29: Thibodaux Live Supply | S29: Maine Association of Wetland Scientists | T29: Salisbury University | V29: Michigan Environmental Council | X29: National Wildlife Federation | Y29: Missouri Park and Recreation Association | AA29: Nebraska Farm Bureau | AC29: University of New Hampshire | AD29: Pinelands Preservation Alliance | AE29: US Fish and Wildlife Service USFWS | AF29: North Carolina Museum of Natural History | AH29: Southwestern Oklahoma State University | AI29: Oregon Cattlemens Association | AJ29: Lehigh University | AK29: Natural Resources Conservation Service NRCS | AL29: Macon State College | AM29: South Dakota Governors Office | AN29: Tennessee Aquarium | AR29: Virginia Institute of Marine Science | AT29: West Liberty University | AU29: Stantec | AV29: UR Energy
A30: US Army Corps of Engineers | C30: Quail Forever Phesants Forever | F30: Colorado Headwaters Land Trust | G30: Ducks Unlimited | J30: Georgia 4H | L30: Trumpeter Swan Society | M30: Illinois Nature Preserves Commission | O30: Iowa Trappers Association | P30: Playa Lakes Joint Venture | Q30: Touchstone Energy | R30: Towson University | S30: Maine Audubon Society | T30: Sierra Club | V30: Michigan Natural Features Inventory | X30: National Wildlife Refuge | Y30: Missouri Parks Association | AA30: Nebraska Forest Service | AC30: University of Vermont | AD30: PSEG Services Corporation | AE30: US Forest Service USFS | AF30: North Carolina Museum of Natural Sciences | AH30: Sutton Avian Research Center | AI30: Oregon Chapter of American Fisheries Society | AJ30: Lock Haven University | AK30: New England Fishery Management Council | AL30: Nash Community College | AM30: South Dakota Office of School and Public Lands | AN30: Tennessee Clean Water Network | AR30: Virginia Marine Resources Commission | AT30: West Virginia Conservation Agency | AU30: Stockbridge-Munsee Community | AV30: US Department of Agriculture
A31: US Fish and Wildlife Service USFWS | C31: Research Foundation for The State University of New York Environmental Science and Forestry SUNY | F31: Colorado Mountain Club | G31: Farmington River Watershed Association | J31: Georgia Aquarium | L31: University of Idaho | M31: Illinois Pollution Control Board | O31: Iowa Tree Farm Committee | P31: Sierra Club | Q31: University of Kentucky | R31: Tulane University | S31: Maine Birding Trail | T31: Smithsonian | V31: Michigan Nature Association | X31: Natural Resource Enterprises | Y31: Missouri Prairie Foundation | AA31: Nebraska Game and Parks Commission | AC31: US Fish and Wildlife Service USFWS | AD31: Rowan University | AE31: Western New Mexico University | AF31: North Carolina Natural Heritage Program | AH31: The Nature Conservancy | AI31: Oregon Chapter of The Wildlife Society | AJ31: Messiah College | AK31: New England Interstate Water Pollution Control Commission | AL31: National Oceanic and Atmospheric Administration NOAA | AM31: South Dakota State University | AN31: Tennessee Department of Environment and Conservation | AR31: Virginia Society of Ornithology | AT31: West Virginia Cooperative Fish and Wildlife Research Unit | AU31: The Nature Conservancy | AV31: US Fish and Wildlife Service USFWS
A32: US Forest Service USFS | C32: Salt River Pima Maricopa Indian Community | F32: Colorado Native Plant Society | G32: Federal Aviation Administration FAA | J32: Georgia Botanical Society | L32: US Army Corps of Engineers | M32: Jo Daviess Conservation Foundation | O32: Iowa Wildlife Center | P32: Stantec | Q32: US Fish and Wildlife Service USFWS | R32: University New Orleans | S32: Maine Bowhunters Association | T32: Susquehannock Wildlife Society | V32: Michigan State University | X32: Natural Resources Conservation Service NRCS | Y32: Missouri Resource Assessment Partnership | AA32: Nebraska Land Trust | AC32: US Forest Service USFS | AD32: Rutgers University | AE32: White Sands Missile Range | AF32: North Carolina State University | AH32: The Samuel Roberts Noble Foundation | AI32: Oregon Department of Agriculture | AJ32: Mid-Atlantic Center for Herpetology and Conservation | AK32: New England Plant Conservation Program | AL32: North American Native Fishes Association | AM32: Standing Rock Sioux Tribe | AN32: Tennessee Ornithological Society | AR32: Virginia Tech | AT32: West Virginia Council Trout Unlimited | AU32: The Prairie Enthusiasts | AV32: US Forest Service USFS
A33: US Geological Survey USGS | C33: Sierra Club Arizona | F33: Colorado Natural Areas Program | G33: Green Valley Institute (UConn and UMass partnership) | J33: Georgia College and State University | L33: US Bureau of Land Management | M33: Jo Daviess County Soil and Water Conservation District | O33: Iowa Woodland Owners Association | P33: Sternberg Museum of Natural History | Q33: US Forest Service USFS | R33: University of Louisiana | S33: Maine Chamber of Commerce | T33: The Nature Conservancy | V33: Michigan Technological University | X33: Office of Senator Thad Cochran | Y33: Missouri Stream Team Watershed Coalition | AA33: Nebraska Ornithologists Union | AC33: Vermont Center for Ecostudies | AD33: South Jersey Resource Conservation and Development | AF33: North Carolina Wildlife Federation | AH33: Tinker Air Force Base | AI33: Oregon Department of Energy | AJ33: Millersville University | AK33: Pheasants Forever | AL33: North Carolina Division of Marine Fisheries | AM33: University of South Dakota | AN33: Tennessee Parks and Greenways Foundation | AR33: Xerces Society | AT33: West Virginia Department of Environmental Protection | AU33: TRC Environmental | AV33: Water Management Coordinator
C34: The Nature Conservancy | F34: Colorado Natural Heritage Program | G34: Hartford Armory | J34: Georgia Conservancy | L34: US Bureau of Reclamation | M34: Lake County Forest Preserve District | O34: Linn County Conservation Board | P34: The Nature Conservancy | Q34: Western Kentucky University | R34: University of New Orleans | S34: Maine Chapter of the Sierra Club | T34: Towson University | V34: Michigan United Conservation Clubs | X34: Partnership for Gulf Coast Land Conservation | Y34: Missouri Tree Farm Committee | AA34: Nebraska Prairie Partners | AC34: Wells National Estuarine Research Reserve | AD34: Stockton University | AF34: North Carolina Wildlife Resources Commission | AH34: University of Central Oklahoma | AI34: Oregon Department of Environmental Quality | AJ34: Moravian College | AK34: Providence Water | AL34: North Carolina Museum of Natural History | AM34: US Army Corps of Engineers | AN34: Tennessee Technological University | AT34: West Virginia Department of Natural Resources | AU34: Trout Unlimited | AV34: Wildlife Conservation Society
C35: Tuscon Audubon Society | F35: Colorado Openlands | G35: Hartford Sportsmen Club | J35: Georgia Department of Education | L35: US Department of Agriculture | M35: Lincoln Park Zoo | O35: Loess Hills Alliance | P35: US Army Corps of Engineers | R35: US Department of Agriculture | S35: Maine Chapter of the Wildlife Society | T35: University of Delaware | V35: National Audubon Society | X35: Pascagoula River Audubon Center | Y35: National Park Service | AA35: Nebraska Wildlife Federation | AD35: Supawna Meadows National Wildlife Refuge | AF35: Ohio Department of Natural Resources | AH35: University of Oklahoma | AI35: Oregon Department of Fish and Wildlife | AJ35: National Aviary | AK35: Rhode Island Association of Wetland Scientists | AL35: North Carolina Museum of Natural Sciences | AM35: US Fish and Wildlife Service USFWS | AN35: Tennessee Valley Authority | AT35: West Virginia Division of Forestry | AU35: University of Connecticut | AV35: Wildlife Heritage Foundation of Wyoming
C36: University of Arizona | F36: Colorado Outfitters Association | G36: Maritime Aquarium at Norwalk | J36: Georgia Department of Natural Resources GADNR | L36: US Department of Energy | M36: Little River Research and Design | O36: Loess Hills Audubon | P36: US Department of Agriculture | R36: US Fish and Wildlife Service USFWS | S36: Maine Coast Heritage Trust | T36: University of Maryland | V36: National Wild Turkey Federation | X36: Southern Company | Y36: National Wild Turkey Federation | AA36: Nebraska Wildlife Society | AD36: The Nature Conservancy | AF36: Piedmont Land Conservancy | AH36: University of Science and Arts of Oklahoma | AI36: Oregon Department of Forestry | AJ36: National Park Service | AK36: Rhode Island College | AL36: North Carolina State University | AM36: US Forest Service USFS | AN36: Tennessee Wildlife Federation | AT36: West Virginia Division of Highways | AU36: University of Minnesota | AV36: Wyoming Bureau of Land Management
C37: US Air Force Luke Air Force Base | F37: Colorado Pesticide Network | G37: Mashantucket Pequot Tribal Nation | J37: Georgia Department of Transportation | L37: US Fish and Wildlife Service USFWS | M37: Living Lands and Waters | O37: MacBride Raptor Center | P37: US Fish and Wildlife Service USFWS | R37: US Forest Service USFS | S37: Maine Coastal Program | T37: US Department of Agriculture | V37: National Wildlife Federation | X37: The Nature Conservancy | Y37: Natural Resources Conservation Service NRCS | AA37: Northern Prairies Land Trust | AD37: The Wetlands Institute | AF37: Smith College | AH37: University of Tulsa | AI37: Oregon Department of Land Conservation and Development | AJ37: Natural History Museum, Tom Ridge Environmental Center | AK37: Rhode Island Department of Environmental Management | AL37: North Carolina Wildlife Resources Commission | AM37: US Geological Survey USGS | AN37: Tennessee Wildlife Resources Agency | AT37: West Virginia Entomological Society | AU37: University of Wisconsin | AV37: Wyoming Department of Agriculture
C38: US Army Yuma Proving Ground | F38: Colorado Sportsmen's Roundtable | G38: Mid-Atlantic Fishery Management Council | J38: Georgia Environmental Finance Authority | L38: US Forest Service USFS | M38: Loyola University | O38: Morningside College | P38: Westar Energy Company | R38: US Geological Survey USGS | S38: Maine Cooperative Fish and Wildlife Research Unit | T38: US Department of Energy | V38: Organization for Bat Conservation | X38: The Trust for Public Land | Y38: Ozark Regional Land Trust | AA38: Omaha Henry Doorly Zoo | AD38: Unaffiliated private consultants | AF38: Tennessee Valley Authority | AH38: US Fish and Wildlife Service USFWS | AI38: Oregon Department of State Lands | AJ38: Natural Resources Conservation Service NRCS | AK38: Rhode Island Ducks Unlimited | AL38: Piedmont College | AM38: Wind Cave National Park | AN38: The Land Trust for Tennessee | AT38: West Virginia Land Trust | AU38: US Department of Agriculture | AV38: Wyoming Game and Fish Department
C39: US Bureau of Reclamation | F39: Colorado Springs Utilities | G39: Mohegan Tribal Nation | J39: Georgia Forestry Association | L39: US Geological Survey USGS | M39: Max McGraw Wildlife Foundation | O39: National Park Service | P39: Wichita Audubon Society | S39: Maine Department of Agriculture, Conservation and Forestry | T39: US Fish and Wildlife Service USFWS | V39: Pheasants Forever | X39: University of Mississippi | Y39: Pheasants Forever | AA39: Pheasants Forever | AD39: US Department of Defense DOD | AF39: Texas A&M University | AI39: Oregon Department of Transportation | AJ39: NatureServe | AK39: Rhode Island Forest Conservators Organization | AL39: Purdue University | AN39: The Nature Conservancy | AT39: West Virginia Master Naturalist Program | AU39: US Fish and Wildlife Service USFWS | AV39: Wyoming Governors Office
C40: US Department of Agriculture USDA Wildlife Services | F40: Colorado State Forest Service | G40: Mystic Aquarium | J40: Georgia Forestry Commission | M40: McHenry County Conservation District | O40: National Wild Turkey Federation | S40: Maine Department of Environmental Protection | T40: US Geological Survey USGS | V40: Pierce Cedar Creek Institute | X40: University of Southern Mississippi | Y40: Prairies Forever | AA40: Ponca Tribe of Nebraska | AD40: US Fish and Wildlife Service USFWS | AF40: The Catena Group | AI40: Oregon Farm Bureau | AJ40: North Carolina Museum of Natural Sciences | AK40: Rhode Island Geographic Information System | AL40: Randolf Rattlesnake Refuge and Research Center | AN40: Trout Unlimited | AT40: West Virginia Outdoor Heritage Conservation Fund | AU40: US Forest Service USFS | AV40: Wyoming Land Trust
C41: US Fish and Wildlife Service USFWS | F41: Colorado State Land Board | G41: National Marine Fisheries Service | J41: Georgia Highland College | M41: National Wild Turkey Federation | O41: Natural Resources Conservation Service NRCS | S41: Maine Department of Inland Fisheries and Wildlife | T41: Washington College | V41: Ruffed Grouse Society | X41: US Army Corps of Engineers | Y41: Quail and Upland Wildlife Federation | AA41: Prairie Loft Center for Outdoor and Agricultural Learning | AD41: Wallkill River National Wildlife Refuge | AF41: The Nature Conservancy | AI41: Oregon Fish and Wildlife Commission | AJ41: Penn State University | AK41: Rhode Island Marine Fisheries Council | AL41: Riverbanks Zoo | AN41: University of Illinois | AT41: West Virginia Partners in Flight | AU41: Wisconsin Botanical Club | AV41: Wyoming Mining Association
C42: US Forest Service USFS | F42: Colorado State University | G42: National Oceanic and Atmospheric Administration NOAA | J42: Georgia Museum of Natural History | M42: Natural Land Institute | O42: Pheasants Forever | S42: Maine Department of Marine Resources | V42: Sierra Club | X42: US Department of Agriculture | Y42: Quail Forever | AA42: Prairie Plains Resource Institute | AD42: Western Hemisphere Shorebird Reserve Network | AF42: The Xerces Society | AI42: Oregon Forest Industries Council | AJ42: Pennsylvania Association of Conservation Districts | AK42: Rhode Island National Wildlife Refuge Complex | AL42: Roark's Reptile Safari | AN42: University of Tennessee | AT42: West Virginia University | AU42: Wisconsin Conservation Congress | AV42: Wyoming Natural Diversity Database
C43: US Marine Corps Yuma Air Station | F43: Colorado Trout Unlimited | G43: National Park Service | J43: Georgia Ornitological Society, Warner Robins Air Force Base | M43: Natural Resources Conservation Service NRCS | O43: Prairie Edge Sustainable Forestry Cooperative | S43: Maine Department of Transportation | V43: The Nature Conservancy | X43: US Fish and Wildlife Service USFWS | Y43: Soil and Water Conservation Society | AA43: Professional Bird Guide | AF43: Unique Places Land Conservation, Restoration and Management | AI43: Oregon Habitat Joint Ventures | AJ43: Pennsylvania Biological Survey | AK43: Rhode Island Natural History Survey | AL43: Savannah River Ecology Laboratory | AN43: University of the South | AU43: Wisconsin County Forest Association | AV43: Wyoming Nongame Bird and Mammal Program
C44: Westland Resources | F44: Colorado Wildlife Federation | G44: National Wildlife Federation | J44: Georgia Plant Conservation Alliance, State Botanical Garden of Georgia | M44: Northeast Illinois Invasive Plant Partnership | O44: Representative Boswell Staff | S44: Maine Farm Bureau | V44: University of Michigan | X44: US Forest Service USFS | Y44: Southeast Association of Fish and Wildlife Agencies | AA44: Rainwater Basin Joint Venture | AF44: University of Georgia | AI44: Oregon Hunters Association | AJ44: Pennsylvania Department of Conservation and Natural Resources | AK44: Rhode Island Resource Conservation and Development Area council | AL44: Smithosonian | AN44: US Army Corps of Engineers | AU44: Wisconsin Department of Natural Resources | AV44: Wyoming Office of State Lands and Investments
C45: White Mountain Apache Tribe | F45: Colorado Wildlife Heritage Foundation | G45: Natural Resources Conservation Service NRCS | J45: Georgia Power Company | M45: Openlands | O45: Ruffed Grouse Society | S45: Maine Farmland Trust | V45: US Fish and Wildlife Service USFWS | X45: US Geological Survey USGS | Y45: The Nature Conservancy | AA45: Rocky Mountain Bird Observatory | AF45: University of North Carolina | AI45: Oregon Invasive Species Council | AJ45: Pennsylvania Department of Environmental Protection | AK45: Rhode Island Tree Farm | AL45: South Carolina Amphibians and Reptiles Webmaster | AN45: US Fish and Wildlife Service USFWS | AU45: Wisconsin Department of Transportation | AV45: Wyoming Oil and Gas Conservation Commission
C46: Willow Creek Environmental | F46: Community Mediation Concepts | G46: New England Fishery Management Council | J46: Georgia Sea Turtle Center | M46: Park Lands Foundation | O46: Safari Club International | S46: Maine Forest Products Council | V46: US Forest Service USFS | X46: Western Carolina University | Y46: The Wildlife Society | AA46: Rowe Sanctuary | AF46: US Fish and Wildlife Service USFWS | AI46: Oregon Small Woodlands Association | AJ46: Pennsylvania Department of Military and Veterans Affairs | AK46: Roger Williams Park Museum of Natural History | AL46: South Carolina Aquarium | AN46: US Forest Service USFS | AU46: Wisconsin Lakes | AV46: Wyoming Outdoor Council
C47: Yuma Crossing National Heritage Area | F47: Conservation Colorado | G47: Rivers Alliance Connecticut | J47: Georgia Southern University | M47: Pheasants Forever and Quail Forever | O47: Sierra Club | S47: Maine Lakes Society | V47: US Geological Survey USGS | X47: Weyerhaeuser | Y47: University of Central Missouri | AA47: Sandhills Task Force | AF47: US Forest Service USFS | AI47: Oregon State University | AJ47: Pennsylvania Fish and Boat Commission | AK47: Roger Williams Park Zoo | AL47: South Carolina Cooperative Fish and Wildlife Research Unit | AN47: US Geological Survey USGS | AU47: Wisconsin Lutheran College | AV47: Wyoming Plant Company
F48: Continental Divide Land Trust | G48: St Josephs University | J48: Georgia Southwestern University | M48: Prairie Rivers Network | O48: Simpson College | S48: Maine Maritime Academy | V48: Wildlife Habitat Council | X48: Wild South | Y48: University of Missouri | AA48: Southeast Community College | AF48: US Geological Survey USGS | AI48: Oregon Water Resources Department | AJ48: Pennsylvania Game Commission | AK48: Roger Williams University | AL48: South Carolina Department of Health and Environmental Control | AN48: Walden's Puddle Wildlife Rehabilitation Center | AU48: Wisconsin Natural Heritage Conservation | AV48: Wyoming State Engineers Office
F49: Crested Butte Land Trust | G49: The Connecticut Open Space Initiative | J49: Georgia Wildlife Federation | M49: Quail Unlimited | O49: Stantec | S49: Maine Natural Areas Program | V49: Wisconsin Entomological Society | X49: Wildlife Mississippi | Y49: US Army Corps of Engineers | AA49: Tern and Plover Conservation Partnership | AF49: Virginia Department of Game and Inland Fisheries | AI49: Oregon Watershed Enhancement Board | AJ49: Pennsylvania Land Trust Association | AK49: Salt Ponds Coalition | AL49: South Carolina Department of Natural Resources | AN49: Wolf River Conservancy | AU49: Wisconsin Natural Resources Foundation | AV49: Wyoming State Forestry Division
F50: Defenders of Wildlife | G50: The Jonah Center for Earth and Art | J50: Geo-Source | M50: River to River Cooperative Weed Management Area | O50: The Nature Conservancy | S50: Maine Professional Guides Association | V50: World Chelonian Trust | Y50: US Department of Agriculture | AA50: The Nature Conservancy | AF50: Wake Forest University | AI50: Oregon Wild | AJ50: Pennsylvania Natural Heritage Program | AK50: Save the Bay | AL50: Spring Island Trust | AU50: Wisconsin Society for Ornithology | AV50: Wyoming State Lands and Investment
F51: Denver Botanic Gardens | G51: The Last Green Valley | J51: Golder Associates | M51: Rockford Park District | O51: The Wildlife Society | S51: Maine Rivers | Y51: US Fish and Wildlife Service USFWS | AA51: University of Nebraska | AF51: Washington State University | AI51: Oregon Wildlife Heritage Foundation | AJ51: Pennsylvania Public Utility Commission | AK51: Terwilliger Consulting | AL51: Tennessee Aquarium | AU51: Wisconsin Wetlands Association | AV51: Wyoming Stock Growers Agricultural Land Trust
F52: Denver Museum of Nature and Science | G52: The Metropolitan District | J52: Gordon State College | M52: Shawnee Resource Conservation and Development | O52: US Army Corps of Engineers | S52: Maine SeaGrant | Y52: US Forest Service USFS | AA52: US Fish and Wildlife Service USFWS | AF52: West Liberty University | AI52: Oregon Wildlife Institute | AJ52: Pennsylvania State University | AK52: The City University of New York | AL52: The Catena Group | AU52: Wisconsin Wildlife Federation | AV52: Wyoming Water Resources Data System
F53: Denver Zoo | G53: The Nature Conservancy | J53: Greg Greer Enterprises | M53: Shedd Aquarium | O53: US Fish and Wildlife Service USFWS | S53: Maine Tourism Association | AA53: US Forest Service USFS | AF53: West Virginia University | AI53: Oregon/Washington Partners in Flight | AJ53: Pluto Ecological Consulting | AK53: The Conservation Agency | AL53: The Citadel | AU53: Xerces Society | AV53: Wyominig County Commissioners Association
F54: Douglas County Open Space | G54: The Ruffed Grouse Society | J54: Habitat for Bats | M54: Southern Illinois University | O54: US Geological Survey USGS | S54: Maine Trappers Association | AF54: Weyerhaeuser | AI54: Oregonians for Food and Shelter | AJ54: Pocono Avian Research Center | AK54: The Nature Conservancy | AL54: The Nature Conservancy
F55: Douglas Land Conservancy | G55: The Trust for Public Land | J55: Indiana University | M55: Southwstern Illinois Metropolitan and Regional Planning Commission | O55: Winnebago County Conservation | S55: Maine's Teaming with Wildlife | AI55: Pacific States Marine Fisheries Commission | AJ55: Project Owlnet | AK55: The Rhode Island Land Trust Council | AL55: University of Colorado
F56: Duane Nelson | G56: Trout Unlimited | J56: International Paper | M56: The Conservation Foundation | O56: Woodland Growers | S56: Manomet Center for Conservation Science | AI56: Portland Metro | AJ56: Purple Martin Conservation Society | AK56: University of Connecticut | AL56: University of Florida
F57: Ducks Unlimited | G57: United Illuminating | J57: Joseph W Jones Ecological Reserch Center | M57: The Field Museum | S57: Mount Agamenticus to the Sea Conservation Initiative | AI57: Portland State University | AJ57: Shippensburg University | AK57: University of Rhode Island | AL57: University of North Carolina
F58: Eagle County Open Space Program | G58: University of Connecticut UConn | J58: Kennesaw State University | M58: The Morton Arboretum | S58: National Oceanic and Atmospheric Administration NOAA | AI58: Rocky Mountain Elk Foundation | AJ58: Stroud Water Research Center | AK58: US Fish and Wildlife Service USFWS | AL58: University of South Carolina
F59: Eagle Valley Land Trust | G59: University of Rhode Island | J59: LaGrange College | M59: The Nature Conservancy | S59: National Wild Turkey Federation | AI59: Sierra Club | AJ59: Susquehanna River Basin Commission | AK59: US Geological Survey USGS | AL59: US Fish and Wildlife Service USFWS
F60: Ecologic, LLC | G60: US Army Aviation Support, Bradley International Airport | J60: Land Trust for the Little Tennessee | M60: The Nature Institute | S60: Natural Resources Conservation Service NRCS | AI60: The Nature Conservancy | AJ60: Susquehanna University | AK60: Wood Pawcatuck Watershed Association | AL60: US Forest Service USFS
F61: ENSR Corporation | G61: US Army Corps of Engineers | J61: Little St Simons Island | M61: The Wildlife Society | S61: Natural Resources Council of Maine | AI61: The Wetlands Conservancy | AJ61: Temple University | AL61: US Geological Survey USGS
F62: Environmental Defense | G62: US Coast Guard | J62: Longleaf Alliance | M62: Trout Unlimited | S62: North Maine Woods | AI62: The Wild Salmon Center | AJ62: The Nature Conservancy | AL62: Wildlife Conservation Society
F63: ERO Resources | G63: US Department of Agriculture USDA | J63: Mississippi State University | M63: University of Illinois | S63: Northern Maine Partner | AI63: Theodore Roosevelt Conservation Fund | AJ63: The Wildlife Society | AL63: Wofford College
F64: Estes Valley Land Trust | G64: US Department of Defense DOD | J64: Natural Resources Conservation Service NRCS | M64: University of Oregon | S64: Orono Land Trust | AI64: Tillamook Estuary Partnership | AJ64: University of Delaware
F65: Fort Collins Audubon Society | G65: US Department of Transportation USDOT | J65: North Alabama University | M65: University of Washington | S65: Passamaquoddy Tribe Indian Township Reservation | AI65: Travel Oregon | AJ65: University of Kentucky
F66: Fort Collins Natural Areas | G66: US Environmental Protection Agency | J66: North American Land Trust | M66: Urbana Park District | S66: Passamaquoddy Tribe Pleasant Point Reservation | AI66: Trout Unlimited | AJ66: University of Pittsburgh
F67: Fort Lewis College | G67: US Fish and Wildlife Service USFWS | J67: North Carolina Heritage Program | M67: US Army Corps of Engineers | S67: Penobscot Nation | AI67: Trust for Public Land | AJ67: University of Scranton
F68: Friends of Colorado Natural Areas | G68: US Forest Service USFS | J68: Okefenokee Natural Wildlife Refuge | M68: US Department of Agriculture | S68: Project Share | AI68: University of Oregon | AJ68: University of Tennessee
F69: Friends of Wolf Creek | G69: US Geological Survey USGS | J69: One Hundred Miles | M69: US Fish and Wildlife Service USFWS | S69: Restore: The North Woods | AI69: University of Washington | AJ69: US Department of Agriculture
F70: Front Range Community College | G70: US Naval Submarine Base | J70: Piedmont College | M70: US Forest Service USFS | S70: Royal River Conservation Trust | AI70: US Bureau of Land Management | AJ70: US Fish and Wildlife Service USFWS
F71: Great Outdoors Colorado | G71: Weir Farm | J71: Plum Creek | S71: Ruffed Grouse Society | AI71: US Fish and Wildlife Service USFWS | AJ71: US Forest Service USFS
F72: Great Plains Landscape Conservation Cooperative | G72: Wesleyan University | J72: Reinhardt College | S72: Senator George Mitchell Center | AI72: US Forest Service USFS | AJ72: US Geological Survey USGS
F73: Gunnison County Wildlife Conservation Coordinator | G73: Yale University | J73: Sapelo Island National Estuarine Research Reserve | S73: Small Woodland Owners Association of Maine | AI73: US Geological Survey USGS | AJ73: West Virginia University
F74: Gunnison Ranchlands Conservation Legacy | J74: Savannah State University | S74: Sportsmens Alliance of Maine | AI74: Waterwatch of Oregon | AJ74: Western Pennsylvania Conservancy
F75: Head First Biological, LLC | J75: Skidaway Institute of Oceanography | S75: Suffolk University | AI75: Weyerhauser | AJ75: Wildlife Specialists LLC
F76: Intermountain West Joint Venture | J76: South Atlantic Landscape Conservation Cooperative | S76: The Nature Conservancy | AI76: Wildlife Conservation Society | AJ76: Wilkes College
F77: Jefferson County Open Space | J77: South Georgia College | S77: Trout Unlimited | AI77: Willamette Partnership | AJ77: Wilkes University
F78: Jews of the Earth | J78: St Catherines Island Foundation, Altamaha Riverkeeper | S78: University of Maine | AI78: Xerces Society | AJ78: WNEP TV and The Pocono Record
F79: La Plata Open Space Conservancy | J79: State Botanical Garden of Georgia | S79: University of New England
F80: Land Trust of the Upper Arkansas | J80: Tall Timbers Research Station | S80: University of Southern Maine
F81: Larimer County Parks and Open Lands | J81: Tennessee Aquarium | S81: US Fish and Wildlife Service USFWS
F82: Legacy Land Trust | J82: Tennessee Natural Heritage Inventory Program | S82: Wells Reserve
F83: Lower Arkansas Valley Water Conservancy District | J83: Tennessee Tech University, North Carolina State University | S83: Wildlife Alliance of Maine
F84: Mesa Land Trust | J84: Tennessee Valley Authority
F85: Montezuma Land Conservancy | J85: The Nature Conservancy
F86: Mountain Area Land Trust | J86: The Orianne Society
F87: National Audubon Society | J87: Turner Foundation
F88: National Center for Genetic Resources Preservation | J88: University of California at Los Angeles, University of Georgia
F89: National Park Service | J89: University of Georgia
F90: National Wildlife Federation | J90: US Department of Defense DOD
F91: Natural Resources Conservation Service | J91: US Fish and Wildlife Service USFWS
F92: Natural Resources Defense Council | J92: US Forest Service USFS
F93: NatureServe | J93: US Geological Survey USGS
F94: North Central Climate Science Center | J94: US Park Service
F95: Orient Land Trust | J95: Valdosta State University
... F99: Pitkin County Open Space and Trails | J99: Zoo Atlanta
F100: Playa Lakes Joint Venture
F101: Prairie Dog Coalition
F102: Prairie Preservation Alliance
F103: Quiet Use Coalition
...

Sheet SGCN Species
A1: State | B1: SGCN (2015) | C1: Total Number of Agencies
A2: Alabama | B2: 366 | C2: =Alabama!G37 -> 26
A3: Alaska | B3: 376 | C3: =Alaska!G25 -> 17
A4: Arizona | B4: 551 | C4: =Arizona!G55 -> 46
A5: Arkansas | B5: 377 | C5: =Arkansas!G30 -> 25
A6: California | B6: 1157 | C6: =California!G32 -> 27
A7: Colorado* | B7: 351 | C7: =Colorado!G159 -> 154
A8: Connecticut* | B8: 566 | C8: =Connecticut!G77 -> 72
A9: Delaware | B9: 692 | C9: =Delaware!G17 -> 12
A10: Florida | B10: 690 | C10: =Florida!G20 -> 14
A11: Georgia | B11: 640 | C11: =Georgia!G103 -> 98
A12: Hawaii | B12: 1323 | C12: =Hawaii!G23 -> 13
A13: Idaho | B13: 205 | C13: =Idaho!G43 -> 38
A14: Illinois | B14: 421 | C14: =Illinois!G74 -> 69
A15: Indiana | B15: 593 | C15: =Indiana!G23 -> 18
A16: Iowa | B16: 405 | C16: =Iowa!G61 -> 55
A17: Kansas | B17: 285 | C17: =Kansas!G43 -> 38
A18: Kentucky | B18: 301 | C18: =Kentucky!G39 -> 33
A19: Louisiana | B19: 694 | C19: =Louisiana!G43 -> 37
A20: Maine | B20: 378 | C20: =Maine!G92 -> 82
A21: Maryland | B21: 610 | C21: =Maryland!G49 -> 40
A22: Massachusetts | B22: 570 | C22: =Massachusetts!G25 -> 11
A23: Michigan | B23: 302 | C23: =Michigan!G59 -> 49
A24: Minnesota | B24: 346 | C24: =Minnesota!G21 -> 16
A25: Mississippi | B25: 308 | C25: =Mississippi!G58 -> 49
A26: Missouri | B26: 678 | C26: =Missouri!G60 -> 51
A27: Montana | B27: 47 | C27: =Montana!G21 -> 16
A28: Nebraska | B28: 773 | C28: =Nebraska!G57 -> 52
A29: Nevada | B29: 256 | C29: =Nevada!G21 -> 16
A30: New Hampshire | B30: 170 | C30: ='New Hampshire'!G38 -> 33
A31: New Jersey | B31: 655 | C31: ='New Jersey'!G51 -> 40
A32: New Mexico | B32: 235 | C32: ='New Mexico'!G36 -> 31
A33: New York | B33: 366
A34: North Carolina | B34: 976 | C34: ='North Carolina'!G62 -> 53
A35: North Dakota* | B35: 115 | C35: ='North Dakota'!G6 -> 1
A36: Ohio* | B36: 405
A37: Oklahoma | B37: 313 | C37: =Oklahoma!G43 -> 37
A38: Oregon | B38: 332 | C38: =Oregon!G86 -> 77
A39: Pennsylvania | B39: 664 | C39: =Pennsylvania!G82 -> 77
A40: Rhode Island | B40: 454 | C40: ='Rhode Island'!G64 -> 59
A41: South Carolina | B41: 839 | C41: ='South Carolina'!G67 -> 62
A42: South Dakota | B42: 101 | C42: ='South Dakota'!G46 -> 37
A43: Tennessee | B43: 1483 | C43: =Tennessee!G53 -> 48
A44: Texas* | B44: 1307 | C44: =Texas!G8 -> 2
A45: Utah | B45: 169 | C45: =Utah!G21 -> 16
A46: Vermont | B46: 1000 | C46: =Vermont!G29 -> 24
A47: Virginia | B47: 883 | C47: =Virginia!G41 -> 32
A48: Washington | B48: 268 | C48: =Washington!G21 -> 12
A49: West Virginia | B49: 1143 | C49: ='West Virginia'!G51 -> 41
A50: Wisconsin | B50: 417 | C50: =Wisconsin!G57 -> 52
A51: Wyoming | B51: 180 | C51: =Wyoming!G57 -> 52

Sheet Alabama
A1: state | B1: name | C1: agency | D1: type
A2: Alabama | B2: Paul Johnson | C2: Alabama Department of Conservation and Natural Resources ADCNR | D2: state
A3: Alabama | B3: Kevin Anson | C3: Alabama Department of Conservation and Natural Resources ADCNR | D3: state
A4: Alabama | B4: Eric Soehren | C4: Alabama Department of Conservation and Natural Resources ADCNR | D4: state
A5: Alabama | B5: Jo Lewis | C5: Alabama Department of Conservation and Natural Resources ADCNR | D5: state
A6: Alabama | B6: Courtney Norman | C6: Alabama Department of Conservation and Natural Resources ADCNR | D6: state
A7: Alabama | B7: Ashley Peters | C7: Alabama Department of Conservation and Natural Resources ADCNR | D7: state
A8: Alabama | B8: Forrest Bailey | C8: Alabama Department of Conservation and Natural Resources ADCNR | D8: state
A9: Alabama | B9: Chuck Sykes | C9: Alabama Department of Conservation and Natural Resources ADCNR | D9: state
A10: Alabama | B10: Jim Schrenkel | C10: Alabama Department of Conservation and Natural Resources ADCNR | D10: state
A11: Alabama | B11: Casey Norris | C11: Alabama Department of Conservation and Natural Resources ADCNR | D11: state
A12: Alabama | B12: Nick Nichols | C12: Alabama Department of Conservation and Natural Resources ADCNR | D12: state
... A36: Alabama | B36: Richard Klinger | C36: Alabama Department of Transportation | D36: state
A37: Alabama | B37: Dan Jackson | C37: Alabama Forestry Commission | D37: state | F37: Total Number of Agencies (excluding committees) | G37: =COUNTA(F3:F16, F23:F34) -> 26
A38: Alabama | B38: Hank McKinley | C38: Alabama Forestry Commission | D38: state
A39: Alabama | B39: Jim Jeter | C39: Alabama Forestry Commission | D39: state
A40: Alabama | B40: Otis French | C40: Alabama Forestry Commission | D40: state
A41: Alabama | B41: Jason Dockery | C41: Alabama Forestry Commission | D41: state
A42: Alabama | B42: Ryan Prince | C42: Alabama Forestry Commission | D42: state
A43: Alabama | B43: Pat O'Neil | C43: Alabama Geological Survey | D43: state
A44: Alabama | B44: Stuart McGregor | C44: Alabama Geological Survey | D44: state
A45: Alabama | B45: Anne Wynn | C45: Alabama Geological Survey | D45: state
A46: Alabama | B46: Jason Carlee | C46: Alabama Power Company | D46: utility
A47: Alabama | B47: Steve Krotzer | C47: Alabama Power Company | D47: utility
A48: Alabama | B48: Eric Reutebuch | C48: Alabama Water Watch Auburn University | D48: school
A49: Alabama | B49: Rebecca Bearden | C49: Alabama Wildlife Federation | D49: ngo-nongame
... A177: Alabama | B177: Mark Bailey | C177: Conservation Southeast | D177: business

Sheet Alaska
A1: state | B1: name | C1: agency | D1: type
A2: Alaska | B2: Mark Kirchhoff | C2: Alaska Department of Fish and Game | D2: state
A3: Alaska | B3: Tim Viavant | C3: Alaska Department of Fish and Game | D3: state
A4: Alaska | B4: Chris Krenz | C4: Alaska Department of Fish and Game | D4: state
A5: Alaska | B5: David Tessler | C5: Alaska Department of Fish and Game | D5: state
A6: Alaska | B6: Travis Booms | C6: Alaska Department of Fish and Game | D6: state | F6: Names/Number of People Not Given:
A7: Alaska | B7: Julie Hagelin | C7: Alaska Department of Fish and Game | D7: state
A8: Alaska | B8: Karen Blejwas | C8: Alaska Department of Fish and Game | D8: state
A9: Alaska | B9: kelly Nesvacil | C9: Alaska Department of Fish and Game | D9: state
A10: Alaska | B10: Grey Pendleton | C10: Alaska Department of Fish and Game | D10: state
A11: Alaska | B11: Michael Kohan | C11: Alaska Department of Fish and Game | D11: state
A12: Alaska | B12: Chris Barger | C12: Alaska Department of Fish and Game | D12: state
A13: Alaska | B13: Dan Rosenberg | C13: Alaska Department of Fish and Game | D13: state
A14: Alaska | B14: Mike Petrula | C14: Alaska Department of Fish and Game | D14: state
A15: Alaska | B15: Jason Schamber | C15: Alaska Department of Fish and Game | D15: state
A16: Alaska | B16: Bob Small | C16: Alaska Department of Fish and Game | D16: state
A17: Alaska | B17: Michael Rehberg | C17: Alaska Department of Fish and Game | D17: state
A18: Alaska | B18: Lauri Jemison | C18: Alaska Department of Fish and Game | D18: state
... A24: Alaska | B24: Lisa Evans | C24: Alaska Department of Fish and Game | D24: state
A25: Alaska | B25: Maria Gladziszewski | C25: Alaska Department of Fish and Game | D25: state | F25: Total Number of Agencies | G25: =counta(F3:F4, F8:F22) -> 17
A26: Alaska | B26: Forrest Bowers | C26: Alaska Department of Fish and Game | D26: state
A27: Alaska | B27: Nicole Kimbal | C27: Alaska Department of Fish and Game | D27: state
A28: Alaska | B28: Patti Harper | C28: Alaska Department of Fish and Game | D28: state
A29: Alaska | B29: Celia Rozen | C29: Alaska Department of Fish and Game | D29: state
A30: Alaska | B30: Amy Carroll | C30: Alaska Department of Fish and Game | D30: state
A31: Alaska | B31: Kathy Lepley | C31: Galaxy Graphics | D31: business
A32: state | B32: name | C32: agency | D32: type
A33: Alaska | C33: Alaska Natural Heritage Program UAA | D33: school
A34: Alaska | C34: Audubon Alaska | D34: ngo-nongame
A35: Alaska | C35: Juneau Audubon | D35: ngo-nongame
A36: Alaska | C36: US Fish and Wildlife Service USFWS | D36: federal
A37: Alaska | C37: Pacific Coast Joint Venture | D37: partnership
A38: Alaska | C38: US Geological Survey USGS | D38: federal
A39: Alaska | C39: National Park Service | D39: federal
A40: Alaska | C40: Alaska Fish Habitat Partnerships | D40: partnership
A41: Alaska | C41: American Fisheries Society Alaska Chapter | D41: ngo-consumptive
A42: Alaska | C42: University of Alaska Fairbanks | D42: school
A43: Alaska | C43: Boreal Partners in Flight | D43: partnership
A44: Alaska | C44: Alaska Raptor Group | D44: partnership
... A47: Alaska | C47: Association of Fish and Wildlife Agencies | D47: ngo-consumptive

Sheet Arizona
A1: state | B1: name | C1: agency | D1: type
A2: Arizona | B2: Joyce Francis | C2: Arizona Game and Fish Department AZGFD | D2: state
A3: Arizona | B3: Charles Hofer | C3: Arizona Game and Fish Department AZGFD | D3: state
A4: Arizona | B4: Matthew King | C4: Arizona Game and Fish Department AZGFD | D4: state
A5: Arizona | B5: Tiffany Finke | C5: Arizona Game and Fish Department AZGFD | D5: state
A6: Arizona | B6: Josh Avey | C6: Arizona Game and Fish Department AZGFD | D6: state
A7: Arizona | B7: Michael Barbour | C7: Arizona Game and Fish Department AZGFD | D7: state
A8: Arizona | B8: Zach Beard | C8: Arizona Game and Fish Department AZGFD | D8: state
A9: Arizona | B9: Erin Butler | C9: Arizona Game and Fish Department AZGFD | D9: state
A10: Arizona | B10: Chris Cantrell | C10: Arizona Game and Fish Department AZGFD | D10: state
A11: Arizona | B11: Julie Carter | C11: Arizona Game and Fish Department AZGFD | D11: state | F11: Names/Number of People Not Given:
A12: Arizona | B12: Barbara Cook | C12: Arizona Game and Fish Department AZGFD | D12: state
A13: Arizona | B13: Jom Cooley | C13: Arizona Game and Fish Department AZGFD | D13: state
A14: Arizona | B14: Troy Corman | C14: Arizona Game and Fish Department AZGFD | D14: state
A15: Arizona | B15: Marianne Cox | C15: Arizona Game and Fish Department AZGFD | D15: state
A16: Arizona | B16: Clay Crowder | C16: Arizona Game and Fish Department AZGFD | D16: state
A17: Arizona | B17: Mark Dahlberg | C17: Arizona Game and Fish Department AZGFD | D17: state
A18: Arizona | B18: Mike Demlong | C18: Arizona Game and Fish Department AZGFD | D18: state
A19: Arizona | B19: Locana de Souza | C19: Arizona Game and Fish Department AZGFD | D19: state
A20: Arizona | B20: Dave Dorum | C20: Arizona Game and Fish Department AZGFD | D20: state
A21: Arizona | B21: James Driscoll | C21: Arizona Game and Fish Department AZGFD | D21: state
A22: Arizona | B22: Russ Engel | C22: Arizona Game and Fish Department AZGFD | D22: state
A23: Arizona | B23: Karen Franco | C23: Arizona Game and Fish Department AZGFD | D23: state
... A54: Arizona | B54: Johnathan O'Dell | C54: Arizona Game and Fish Department AZGFD | D54: state
A55: Arizona | B55: Audrey Owens | C55: Arizona Game and Fish Department AZGFD | D55: state | F55: Total Number of Agencies | G55: =counta(F3:F8, F13:F52) -> 46
A56: Arizona | B56: Elaine Pittman | C56: Arizona Game and Fish Department AZGFD | D56: state
A57: Arizona | B57: Damian Rawroot | C57: The Nature Conservancy | D57: ngo-nongame
A58: Arizona | B58: Heidi Rayment | C58: Arizona Game and Fish Department AZGFD | D58: state
A59: Arizona | B59: Anthony Robinson | C59: Arizona Game and Fish Department AZGFD | D59: state
A60: Arizona | B60: Esther Rubin | C60: Arizona Game and Fish Department AZGFD | D60: state
A61: Arizona | B61: Mason Ryan | C61: Arizona Game and Fish Department AZGFD | D61: state
A62: Arizona | B62: Tim Snow | C62: Arizona Game and Fish Department AZGFD | D62: state
A63: Arizona | B63: Jeff Sorensen | C63: Arizona Game and Fish Department AZGFD | D63: state
A64: Arizona | B64: Scott Sprague | C64: Arizona Game and Fish Department AZGFD | D64: state
A65: Arizona | B65: Tice Supplee | C65: Audubon Southwest | D65: ngo-nongame
A66: Arizona | B66: Kristin Terpening | C66: Arizona Game and Fish Department AZGFD | D66: state
A67: Arizona | B67: Luke Thompson | C67: Arizona Game and Fish Department AZGFD | D67: state
... A80: state | B80: name | C80: agency | D80: type
A81: Arizona | C81: Altar Valley Conservation Alliance | D81: ngo-nongame
A82: Arizona | C82: Arizona State University | D82: school
A83: Arizona | C83: ASARCO | D83: business
A84: Arizona | C84: Audubon Arizona | D84: ngo-nongame
A85: Arizona | C85: Be Outdoors Arizona | D85: ngo-nongame
A86: Arizona | C86: Big Sandy NRCD | D86: state
A87: Arizona | C87: Borderlands Restoration Network | D87: ngo-nongame
A88: Arizona | C88: US Bureau of Land Management | D88: federal
A89: Arizona | C89: City of Flagstaff | D89: local
A90: Arizona | C90: City of Peoria | D90: local
A91: Arizona | C91: Federal Highway Administration | D91: federal
A92: Arizona | C92: Fort Huachuca | D92: federal
... A120: Arizona | C120: Yuma Crossing National Heritage Area | D120: federal

Sheet Arkansas
A1: state | B1: name | C1: agency | D1: type
A2: Arkansas | B2: Allison Fowler | C2: Arkansas Game and Fish Commission | D2: state
A3: Arkansas | B3: Jane Anderson | C3: Arkansas Game and Fish Commission | D3: state
A4: Arkansas | B4: Ricky Chastain | C4: Arkansas Game and Fish Commission | D4: state
A5: Arkansas | B5: Brad Carner | C5: Arkansas Game and Fish Commission | D5: state
A6: Arkansas | B6: Chris Racey | C6: Arkansas Game and Fish Commission | D6: state
A7: Arkansas | B7: Melvin Tobin | C7: US Fish and Wildlife Service USFWS | D7: federal
A8: Arkansas | B8: Scott Simon | C8: The Nature Conservancy | D8: ngo-nongame
A9: Arkansas | B9: Chris Colclasure | C9: The Arkansas Natural Heritage Commission | D9: state
A10: Arkansas | B10: AJ Riggs | C10: Arkansas Game and Fish Commission | D10: state
A11: Arkansas | B11: Eric Brinkman | C11: Arkansas Game and Fish Commission | D11: state
A12: Arkansas | B12: Chris Davidson | C12: US Fish and Wildlife Service USFWS | D12: federal
... A29: Arkansas | B29: Don White | C29: University of Arkansas-Monticello | D29: school
A30: Arkansas | B30: Karen Rowe | C30: Arkansas Game and Fish Commission | D30: state | F30: Total Number of Agencies | G30: =counta(F3:F27) -> 25
A31: Arkansas | B31: Leif Anderson | C31: US Forest Service USFS | D31: federal
A32: Arkansas | B32: Dick Baxter | C32: Arkansas Game and Fish Commission | D32: state
A33: Arkansas | B33: Than Boves | C33: Arkansas State University | D33: school
A34: Arkansas | B34: Michael Budd | C34: US Fish and Wildlife Service USFWS | D34: federal
A35: Arkansas | B35: Garrick Dugger | C35: Arkansas Game and Fish Commission | D35: state
A36: Arkansas | B36: Steve Duzan | C36: US Forest Service USFS | D36: federal
A37: Arkansas | B37: Steven Fowler | C37: Arkansas Game and Fish Commission | D37: state
A38: Arkansas | B38: David Graves | C38: Arkansas Game and Fish Commission | D38: state
A39: Arkansas | B39: Bubba Groves | C39: Arkansas Game and Fish Commission | D39: state
A40: Arkansas | B40: Brad Hufhines | C40: Beaver Water District | D40: local
A41: Arkansas | B41: Clifton Jackson | C41: Arkansas Game and Fish Commission | D41: state
A42: Arkansas | B42: Chris kellner | C42: Arkansas Tech University | D42: school
... A130: Arkansas | B130: Mitch Wine | C130: US Fish and Wildlife Service USFWS | D130: federal

Sheet California
A1: state | B1: name | C1: agency | D1: type
A2: California | B2: Armand Gonzales | C2: California Department of Fish and Wildlife | D2: state
A3: California | B3: Junko Hoshi | C3: California Department of Fish and Wildlife | D3: state
A4: California | B4: Whitney Albright | C4: California Department of Fish and Wildlife | D4: state
A5: California | B5: Diane Mastalir | C5: California Department of Fish and Wildlife | D5: state
A6: California | B6: Kurt Malchow | C6: California Department of Fish and Wildlife | D6: state
A7: California | B7: Kevin Shaffer | C7: California Department of Fish and Wildlife | D7: state
A8: California | B8: Todd Keeler-Wolf | C8: California Department of Fish and Wildlife | D8: state
A9: California | B9: Melanie Gogol-Prokurat | C9: California Department of Fish and Wildlife | D9: state
A10: California | B10: Vicki Frey | C10: California Department of Fish and Wildlife | D10: state
A11: California | B11: Julia Gonzales | C11: California Department of Fish and Wildlife | D11: state
A12: California | B12: Curtis Alling | C12: Ascent Environmental, Inc | D12: business
... A31: California | B31: Judy Boshoven | C31: Foundations of Success | D31: ngo-nongame
A32: California | B32: Cheryl Margoluis | C32: Foundations of Success | D32: ngo-nongame | F32: Total Number of Agencies | G32: =counta(F3:F29) -> 27
A33: California | B33: Jodie Monaghan | C33: Center for Collaborative Policy - California State University, Sacramento | D33: school
A34: California | B34: Heidi Hill Drum | C34: Center for Collaborative Policy - California State University, Sacramento | D34: school
A35: California | B35: Doug Johnson | C35: California Invasive Plant Council | D35: ngo-nongame
A36: California | B36: Elizabeth Brusati | C36: California Invasive Plant Council | D36: ngo-nongame
A37: California | B37: John Knapp | C37: The Nature Conservancy | D37: ngo-nongame
A38: California | B38: John Randall | C38: The Nature Conservancy | D38: ngo-nongame
A39: California | B39: Dick Cameron | C39: The Nature Conservancy | D39: ngo-nongame
A40: California | B40: Chuck Bonham | C40: California Department of Fish and Wildlife | D40: state
A41: California | B41: Kevin Hunting | C41: California Department of Fish and Wildlife | D41: state
A42: California | B42: Tom Cullen | C42: California Department of Fish and Wildlife | D42: state
A43: California | B43: Sonke Mastrup | C43: California Department of Fish and Wildlife | D43: state
A44: California | B44: John Donnelly | C44: California Department of Fish and Wildlife | D44: state
... A214: California | B214: Eric Wilkins | C214: California Department of Fish and Wildlife | D214: state

Sheet Colorado
A1: state | B1: name | C1: agency | D1: type | F1: Names/Number of people not given
A2: Colorado | C2: Adams County Parks Department | D2: local
A3: Colorado | C3: Rio Grande Headwaters Land Trust | D3: ngo-nongame
A4: Colorado | C4: River Otter Alliance | D4: ngo-nongame
A5: Colorado | C5: Roaring Fork Conservancy | D5: ngo-nongame
A6: Colorado | C6: Rocky Mountain Bighorn Society | D6: ngo-nongame
A7: Colorado | C7: Rocky Mountain Bird Observatory | D7: ngo-nongame
A8: Colorado | C8: Rocky Mountain Climate Organization | D8: ngo-nongame
A9: Colorado | C9: Rocky Mountain Elk Foundation | D9: ngo-consumptive
A10: Colorado | C10: Rocky Mountain Recreation Initiative | D10: ngo-consumptive
A11: Colorado | C11: Rocky Mountain Wild | D11: ngo-nongame
A12: Colorado | C12: Roe Ecological Services | D12: business
A13: Colorado | C13: San Isabel Land Protection Trust | D13: ngo-nongame
... A155: Colorado | C155: Quiet Use Coalition | D155: ngo-nongame
F159: Total Number of Agencies | G159: =counta(F3:F156) -> 154

Sheet Connecticut
A1: state | B1: name | C1: agency | D1: type | F1: Names/Number of People not given
A2: Connecticut | C2: Connecticut National Guard Armory | D2: state
A3: Connecticut | C3: US Army Aviation Support, Bradley International Airport | D3: federal
A4: Connecticut | C4: US Coast Guard | D4: federal
A5: Connecticut | C5: US Naval Submarine Base | D5: federal
A6: Connecticut | C6: Connecticut Animal Control Division | D6: state
A7: Connecticut | C7: Connecticut Shellfish and Aquaculture Program | D7: state
A8: Connecticut | C8: Connecticut Conservation Advisory Council | D8: state
A9: Connecticut | C9: Connecticut Fisheries Advisory Council | D9: state
A10: Connecticut | C10: Connecticut Soil and Water Conservation Districts | D10: state
A11: Connecticut | C11: The Connecticut Open Space Initiative | D11: state
A12: Connecticut | C12: Mashantucket Pequot Tribal Nation | D12: indigenous
A13: Connecticut | C13: Mohegan Tribal Nation | D13: indigenous
... A29: Connecticut | C29: Green Valley Institute (UConn and UMass partnership) | D29: school
A30: Connecticut | C30: Hartford Sportsmen Club
A31: Connecticut | C31: Maritime Aquarium at Norwalk | D31: ngo-nongame
A32: Connecticut | C32: Mystic Aquarium | D32: ngo-nongame
A33: Connecticut | C33: National Wildlife Federation | D33: ngo-nongame
A34: Connecticut | C34: Rivers Alliance Connecticut | D34: ngo-consumptive
A35: Connecticut | C35: The Jonah Center for Earth and Art | D35: ngo-nongame
A36: Connecticut | C36: The Last Green Valley | D36: ngo-nongame
A37: Connecticut | C37: The Metropolitan District | D37: ngo-nongame
A38: Connecticut | C38: The Nature Conservancy | D38: ngo-nongame
A39: Connecticut | C39: The Ruffed Grouse Society | D39: ngo-nongame
A40: Connecticut | C40: The Trust for Public Land | D40: ngo-nongame
A41: Connecticut | C41: Trout Unlimited | D41: ngo-consumptive
A42: Connecticut | C42: United Illuminating | D42: business
... A73: Connecticut | C73: Hartford Armory | D73: state
F77: Total Number of Agencies | G77: =counta(F3:F74) -> 72

Sheet Delaware
A1: state | B1: name | C1: agency | D1: type
A2: Delaware | B2: Karen Terwilliger | C2: Terwilliger Consulting | D2: business
A3: Delaware | B3: Matthew Sarver | C3: Sarver Ecological | D3: business
A4: Delaware | B4: Shannon Alexander | C4: Alexander Environmental Consulting | D4: business
A5: Delaware | B5: Karen Bennett | C5: Delaware Department of Natural Resources and Environmental Control | D5: state
A6: Delaware | B6: John Clark | C6: Delaware Department of Natural Resources and Environmental Control | D6: state
A7: Delaware | B7: Shelley DiBona | C7: Delaware Department of Natural Resources and Environmental Control | D7: state
A8: Delaware | B8: Robert Hossler | C8: Delaware Department of Natural Resources and Environmental Control | D8: state
A9: Delaware | B9: William Meredith | C9: Delaware Department of Natural Resources and Environmental Control | D9: state
A10: Delaware | B10: Stewart Michels | C10: Delaware Department of Natural Resources and Environmental Control | D10: state
A11: Delaware | B11: Thomas Moran | C11: Delaware Department of Natural Resources and Environmental Control | D11: state
A12: Delaware | B12: Craig Rhoads | C12: Delaware Department of Natural Resources and Environmental Control | D12: state
... A16: Delaware | B16: Kevin Kalasz | C16: Delaware Department of Natural Resources and Environmental Control | D16: state
A17: Delaware | B17: Shannon Alexander | C17: Terwilliger Consulting | D17: business | F17: Total Number of Agencies | G17: =counta(F3:F14) -> 12
A18: Delaware | B18: Matt Bailey | C18: Delaware Department of Natural Resources and Environmental Control | D18: state
A19: Delaware | B19: Chris Bennett | C19: Delaware Department of Natural Resources and Environmental Control | D19: state
A20: Delaware | B20: Greg Breese | C20: US Fish and Wildlife Service USFWS | D20: federal
A21: Delaware | B21: Matthew DiBona | C21: Delaware Department of Natural Resources and Environmental Control | D21: state
A22: Delaware | B22: Anthony Gonzon | C22: Delaware Department of Natural Resources and Environmental Control | D22: state
A23: Delaware | B23: Kitt Keckscher | C23: Delaware State University | D23: school
A24: Delaware | B24: Rick McCorkle | C24: US Fish and Wildlife Service USFWS | D24: federal
A25: Delaware | B25: Greg Shriver | C25: University of Delaware | D25: school
A26: Delaware | B26: Jim White | C26: Delaware Nature Society | D26: ngo-nongame
A27: Delaware | B27: Jean Woods | C27: Delaware Museum of Natural History | D27: ngo-nongame
A28: Delaware | B28: Lee Anderson | C28: University of Delaware | D28: school
A29: Delaware | B29: Johnny Moore | C29: Delaware Department of Natural Resources and Environmental Control | D29: state
... A50: Delaware | B50: Chief Coker | C50: Lenape Tribe | D50: indigenous

Sheet Florida
A1: state | B1: name | C1: agency | D1: type
A2: Florida | B2: Dave Almquist | C2: Florida Natural Areas Inventory | D2: school
A3: Florida | B3: Corey Anderson | C3: Florida Fish and Wildlife Conservation Commission | D3: state
A4: Florida | B4: John Ascher | C4: American Museum of Natural History | D4: ngo-nongame
A5: Florida | B5: Mark Asleson | C5: Florida Fish and Wildlife Conservation Commission | D5: state
A6: Florida | B6: Ray Ball | C6: ZooTampa | D6: ngo-nongame
A7: Florida | B7: Brian Barnett | C7: Florida Fish and Wildlife Conservation Commission | D7: state
A8: Florida | B8: Laura Barrett | C8: Florida Department of Environmental Protection | D8: state
A9: Florida | B9: Brian Beneke | C9: Florida Fish and Wildlife Conservation Commission | D9: state
A10: Florida | B10: Jennifer Bernatis | C10: Florida Fish and Wildlife Conservation Commission | D10: state
A11: Florida | B11: Travis Blunden | C11: Florida Fish and Wildlife Conservation Commission | D11: state
A12: Florida | B12: Chris Boland | C12: Florida Fish and Wildlife Conservation Commission | D12: state
... A19: Florida | B19: Amy Clifton | C19: Florida Fish and Wildlife Conservation Commission | D19: state
A20: Florida | B20: Jimmy Connor | C20: Florida Fish and Wildlife Conservation Commission | D20: state | F20: Total Number of Agencies (excluding independent) | G20: =counta(F3:F12, F14:F17) -> 14
A21: Florida | B21: David Cook | C21: Florida Fish and Wildlife Conservation Commission | D21: state
A22: Florida | B22: Scott Cooney | C22: Florida Fish and Wildlife Conservation Commission | D22: state
A23: Florida | B23: Andrew Cox | C23: Florida Fish and Wildlife Conservation Commission | D23: state
A24: Florida | B24: Josh Cucinella | C24: Florida Fish and Wildlife Conservation Commission | D24: state
A25: Florida | B25: Justin Davis | C25: Florida Fish and Wildlife Conservation Commission | D25: state
A26: Florida | B26: Anna Deyle | C26: Florida Fish and Wildlife Conservation Commission | D26: state
A27: Florida | B27: Peter Diamond | C27: Florida Fish and Wildlife Conservation Commission | D27: state
A28: Florida | B28: Andrea Dominguez | C28: Florida Fish and Wildlife Conservation Commission | D28: state
A29: Florida | B29: Terry Doonan | C29: Florida Fish and Wildlife Conservation Commission | D29: state
A30: Florida | B30: Sam Droege | C30: US Geological Survey USGS | D30: federal
A31: Florida | B31: Thomas Eason | C31: Florida Fish and Wildlife Conservation Commission | D31: state
A32: Florida | B32: Kristen Eaton | C32: Florida Power and Light Company | D32: utility
... A130: Florida | B130: Lily Swanbrow Becker | C130: Florida Wildlife Legacy Initiative | D130: state

Sheet Georgia
A1: state | B1: name | C1: agency | D1: type
A2: Georgia | B2: Todd Schneider | C2: Georgia Department of Natural Resources GADNR | D2: state
A3: Georgia | B3: Tim Keyes | C3: Georgia Department of Natural Resources GADNR | D3: state
A4: Georgia | B4: Jim Bates | C4: US Fish and Wildlife Service USFWS | D4: federal
A5: Georgia | B5: Rebecca Byrd | C5: Georgia Department of Transportation | D5: state
A6: Georgia | B6: Larry Carlile | C6: US Department of Defense DOD | D6: federal
A7: Georgia | B7: Scott Coleman | C7: Little St Simons Island | D7: local
A8: Georgia | B8: Chris Coppola | C8: US Fish and Wildlife Service USFWS | D8: federal
A9: Georgia | B9: Jenifer Hilburn | C9: St Catherines Island Foundation, Altamaha Riverkeeper | D9: ngo-nongame
A10: Georgia | B10: Malcolm Hodges | C10: The Nature Conservancy | D10: ngo-nongame
A11: Georgia | B11: Elizabeth Hunter | C11: University of Georgia | D11: school
A12: Georgia | B12: Nathan Klaus | C12: Georgia Department of Natural Resources GADNR | D12: state
... A102: Georgia | B102: John Damer | C102: Georgia Department of Natural Resources GADNR | D102: state
A103: Georgia | B103: Jonathan Davis | C103: Young Harris College | D103: school | F103: Total Number of Agencies | G103: =counta(F3:F100) -> 98
A104: Georgia | B104: Jerry Dinkins | C104: Dinkins Biological Consulting | D104: business
A105: Georgia | B105: Will Duncan | C105: US Fish and Wildlife Service USFWS | D105: federal
A106: Georgia | B106: Sara Duquette | C106: Georgia Power Company | D106: utility
A107: Georgia | B107: Bill Ensign | C107: Kennesaw State University | D107: school
A108: Georgia | B108: Jimmy Evans | C108: Georgia Department of Natural Resources GADNR | D108: state
A109: Georgia | B109: Chester Figiel | C109: Warm Springs Regional Fisheries Center | D109: federal
A110: Georgia | B110: Byron Freeman | C110: Georgia Museum of Natural History | D110: school
A111: Georgia | B111: Mary Freeman | C111: US Geological Survey USGS | D111: federal
A112: Georgia | B112: Mike Gangloff | C112: Appalachian State University | D112: school
A113: Georgia | B113: Robin Goodloe | C113: US Fish and Wildlife Service USFWS | D113: federal
A114: Georgia | B114: Megan Hagler | C114: University of Georgia | D114: school
A115: Georgia | B115: Don Harrison | C115: Georgia Department of Natural Resources GADNR | D115: state
... A315: Georgia | B315: Seth Wenger | C315: University of Georgia | D315: school

Sheet Hawaii
A1: state | B1: name | C1: agency | D1: type
A2: Hawaii | B2: Paul Conry | C2: Hawaii Department of Land and Natural Resources | D2: state
A3: Hawaii | B3: Gregory Spencer | C3: Hawaii Department of Land and Natural Resources | D3: state
A4: Hawaii | B4: Shahin Ansari | C4: Hawaii Department of Land and Natural Resources | D4: state
A5: Hawaii | B5: David Ainley | C5: Hawaii Department of Land and Natural Resources | D5: state
A6: Hawaii | B6: Christine Hamilton | C6: Hawaii Department of Land and Natural Resources | D6: state
A7: Hawaii | B7: Karl Magnacca | C7: Hawaii Department of Land and Natural Resources | D7: state | F7: Names/Number of People Not Given:
A8: Hawaii | B8: John Vetter | C8: Hawaii Department of Land and Natural Resources | D8: state
A9: Hawaii | B9: Michael Fujimoto | C9: Hawaii Department of Land and Natural Resources | D9: state
A10: Hawaii | B10: James Cogswell | C10: unknown | D10: unknown
A11: Hawaii | B11: Alton Miyasaka | C11: unknown | D11: unknown
A12: Hawaii | B12: David Sakoda | C12: unknown | D12: unknown
A13: Hawaii | B13: Maria Carnevale | C13: unknown | D13: unknown
A14: Hawaii | B14: Edward Kekoa | C14: unknown | D14: unknown
A15: Hawaii | B15: Cynthia King | C15: unknown | D15: unknown
A16: Hawaii | B16: David Sischo | C16: unknown | D16: unknown
A17: Hawaii | B17: Elia Hermann | C17: unknown | D17: unknown
A18: Hawaii | B18: lisa Hadway | C18: unknown | D18: unknown
A19: Hawaii | B19: Michelle Jones | C19: unknown | D19: unknown
... A22: Hawaii | B22: David Smith | C22: unknown | D22: unknown
A23: Hawaii | B23: Jason Misaki | C23: unknown | D23: unknown | F23: Total Number of Agencies (excluding unknown) | G23: =counta(F3, F9:F20) -> 13
A24: Hawaii | B24: Steven Bergfeld | C24: unknown | D24: unknown
A25: Hawaii | B25: Joey Mello | C25: unknown | D25: unknown
A26: Hawaii | B26: Kanalu Sproat | C26: unknown | D26: unknown
A27: Hawaii | B27: Scott Fretz | C27: unknown | D27: unknown
A28: Hawaii | B28: John Medeiros | C28: unknown | D28: unknown
A29: Hawaii | B29: Galen Kawakami | C29: unknown | D29: unknown
A30: Hawaii | B30: Thomas Kaiakapu | C30: unknown | D30: unknown
A31: Hawaii | B31: William Walsh | C31: unknown | D31: unknown
A32: Hawaii | B32: Mark Fox | C32: unknown | D32: unknown
A33: Hawaii | B33: Jason Sumiye | C33: unknown | D33: unknown
A34: Hawaii | B34: Jeff Burgett | C34: unknown | D34: unknown
A35: Hawaii | B35: James Jacobi | C35: unknown | D35: unknown
... A48: state | B48: name | C48: agency | D48: type
A49: Hawaii | C49: HT Harvey and Associates | D49: business
A50: Hawaii | C50: Bishop Museum | D50: ngo-nongame
A51: Hawaii | C51: The Nature Conservancy | D51: ngo-nongame
A52: Hawaii | C52: Hawaii Invasive Species Council | D52: state
A53: Hawaii | C53: Hawaii Watershed Partnerships | D53: partnership
A54: Hawaii | C54: University of Hawaii | D54: school
A55: Hawaii | C55: Hawaii Institute of Marine Biology | D55: school
A56: Hawaii | C56: US Fish and Wildlife Service USFWS | D56: federal
A57: Hawaii | C57: US National Oceanic and Atmospheric Administration NOAA | D57: federal
A58: Hawaii | C58: US Geological Survey USGS | D58: federal
A59: Hawaii | C59: National Park Service | D59: federal
A60: Hawaii | C60: Pacific Islands Climate Change Cooperative | D60: partnership

Sheet Idaho
A1: state | B1: name | C1: agency | D1: type
A2: Idaho | B2: Becky Abel | C2: Idaho Department of Fish and Game | D2: state
A3: Idaho | B3: Regan Berkley | C3: Idaho Department of Fish and Game | D3: state
A4: Idaho | B4: William Bosworth | C4: Idaho Department of Fish and Game | D4: state
A5: Idaho | B5: Jody Brostrom | C5: US Fish and Wildlife Service USFWS | D5: federal
A6: Idaho | B6: Bart Butterfield | C6: Idaho Department of Fish and Game | D6: state
A7: Idaho | B7: Jay Carlisle | C7: Boise State University, Intermountain Bird Observatory | D7: school
A8: Idaho | B8: Rob Cavallaro | C8: Idaho Department of Fish and Game | D8: state
A9: Idaho | B9: Rita Dixon | C9: Idaho Department of Fish and Game | D9: state
A10: Idaho | B10: Shannon Ehlers | C10: Idaho Department of Fish and Game | D10: state
A11: Idaho | B11: Diane Evans Mack | C11: Idaho Department of Fish and Game | D11: state
A12: Idaho | B12: Cristy Garris | C12: Foundations of Success | D12: ngo-nongame
... A42: Idaho | B42: Nikki Wade | C42: Idaho Department of Fish and Game | D42: state
A43: Idaho | B43: Beth Waterbury | C43: Idaho Department of Fish and Game | D43: state | F43: Total Number of Agencies | G43: =IFERROR(__xludf.DUMMYFUNCTION("countunique(C2:C187)"),38.0) -> 38
A44: Idaho | B44: Tim Weekley | C44: Idaho Department of Fish and Game | D44: state
A45: Idaho | B45: Joshua White | C45: Idaho Department of Fish and Game | D45: state
A46: Idaho | B46: Ross Winton | C46: Idaho Department of Fish and Game | D46: state
A47: Idaho | B47: Dale Allen | C47: Idaho Department of Fish and Game | D47: state
A48: Idaho | B48: Lydia R Allen | C48: US Forest Service USFS | D48: federal
A49: Idaho | B49: Mark Arana | C49: US Bureau of Reclamation | D49: federal
A50: Idaho | B50: Juliet Barenti | C50: US Fish and Wildlife Service USFWS | D50: federal
A51: Idaho | B51: Kerey K Barnowe-Meyer | C51: Nez Perce Tribe | D51: indigenous
A52: Idaho | B52: Tom Bassista | C52: Idaho Department of Fish and Game | D52: state
A53: Idaho | B53: Jon Beals | C53: Idaho Governor's Office of Species Conservaiton | D53: state
A54: Idaho | B54: Steve Becker | C54: Nez Perce Soil and Water Conservation District | D54: local
A55: Idaho | B55: Laura Berglund | C55: US Fish and Wildlife Service USFWS | D55: federal
... A187: Idaho | B187: Bart Zwetzig | C187: US Bureau of Land Management | D187: federal

Sheet Illinois
A1: state | B1: name | C1: agency | D1: type
A2: Illinois | B2: Steve Chard | C2: Illinois Department of Agriculture | D2: state
A3: Illinois | B3: Terri Savko | C3: Illinois Department of Agriculture | D3: state
A4: Illinois | B4: Scott Schirmer | C4: Illinois Department of Agriculture | D4: state
A5: Illinois | B5: Tim Cashatt | C5: Illinois Department of Natural Resources | D5: state
A6: Illinois | B6: Chris Rollins | C6: Illinois Department of Natural Resources | D6: state
A7: Illinois | B7: Dave Suthard | C7: Illinois Department of Natural Resources | D7: state
A8: Illinois | B8: Saki Villalobos | C8: Illinois Department of Natural Resources | D8: state
A9: Illinois | B9: Barry Walker | C9: Illinois Department of Natural Resources | D9: state
A10: Illinois | B10: Nathan Grider | C10: Illinois Department of Natural Resources | D10: state
A11: Illinois | B11: Barry Hart | C11: Illinois Department of Natural Resources | D11: state
A12: Illinois | B12: Pat Malone | C12: Illinois Department of Natural Resources | D12: state
... A73: Illinois | B73: Chuck Theiling | C73: US Army Corps of Engineers | D73: federal
A74: Illinois | B74: Brad Thomas | C74: US Army Corps of Engineers | D74: federal | F74: Total Number of Agencies | G74: =counta(F3:F71) -> 69
A75: Illinois | B75: Ben Vandermyde | C75: US Army Corps of Engineers | D75: federal
A76: Illinois | B76: Scott Blackwood | C76: US Department of Agriculture | D76: federal
A77: Illinois | B77: Timothy White | C77: US Department of Agriculture | D77: federal
A78: Illinois | B78: Jamie Diebal | C78: US Department of Agriculture | D78: federal
A79: Illinois | B79: Donald King | C79: US Department of Agriculture | D79: federal
A80: Illinois | B80: Gene Barickman | C80: Natural Resources Conservation Service NRCS | D80: federal
A81: Illinois | B81: Wade Conn | C81: Natural Resources Conservation Service NRCS | D81: federal
A82: Illinois | B82: Kerry Goodrich | C82: Natural Resources Conservation Service NRCS | D82: federal
A83: Illinois | B83: Donovan Henry | C83: US Fish and Wildlife Service USFWS | D83: federal
A84: Illinois | B84: Gwen Kolb | C84: US Fish and Wildlife Service USFWS | D84: federal
A85: Illinois | B85: Kris Lah | C85: US Fish and Wildlife Service USFWS | D85: federal
A86: Illinois | B86: Jacob Randa | C86: US Fish and Wildlife Service USFWS | D86: federal
... A224: Illinois | B224: Jeff Hastings | C224: Trout Unlimited | D224: ngo-consumptive

Sheet Indiana
A1: state | B1: name | C1: agency | D1: type
A2: Indiana | B2: Michelle Cain | C2: Indiana Department of Natural Resources | D2: state
A3: Indiana | B3: Sandy Clark-Kolaks | C3: Indiana Department of Natural Resources | D3: state
A4: Indiana | B4: Steve Donabauer | C4: Indiana Department of Natural Resources | D4: state
A5: Indiana | B5: Brant Fisher | C5: Indiana Department of Natural Resources | D5: state
A6: Indiana | B6: Kent Hanauer | C6: Indiana Department of Natural Resources | D6: state
A7: Indiana | B7: Julie Kempf | C7: Indiana Department of Natural Resources | D7: state
A8: Indiana | B8: Nate Levitte | C8: Indiana Department of Natural Resources | D8: state
A9: Indiana | B9: Adam Phelps | C9: Indiana Department of Natural Resources | D9: state
A10: Indiana | B10: Sam Whiteleather | C10: Indiana Department of Natural Resources | D10: state
A11: Indiana | B11: Shannon Winks | C11: Indiana Department of Natural Resources | D11: state
A12: Indiana | B12: Amanda Wuestefeld | C12: Indiana Department of Natural Resources | D12: state
... A22: Indiana | B22: Laura Hilden | C22: Indiana Department of Transportation | D22: state
A23: Indiana | B23: Liz Jackson | C23: Indiana Forest and Woodland Owners Association | D23: ngo-nongame | F23: Total Number of Agencies | G23: =counta(F3:F20) -> 18
A24: Indiana | B24: Jeff Kiefer | C24: US Fish and Wildlife Service USFWS | D24: federal
A25: Indiana | B25: Raoul Moore | C25: Indiana Forest and Woodland Owners Association | D25: ngo-nongame
A26: Indiana | B26: Mike Mycroft | C26: Indiana Department of Natural Resources | D26: state
A27: Indiana | B27: Brian Nentrup | C27: Pheasants Forever | D27: ngo-consumptive
A28: Indiana | B28: Mark Reiter | C28: Indiana Department of Natural Resources | D28: state
A29: Indiana | B29: Joe Robb | C29: US Fish and Wildlife Service USFWS | D29: federal
A30: Indiana | B30: Justin Schneider | C30: Indiana Farm Bureau | D30: ngo-consumptive
A31: Indiana | B31: Mike Sertle | C31: Ducks Unlimited | D31: ngo-consumptive
A32: Indiana | B32: John Shuey | C32: The Nature Conservancy | D32: ngo-nongame
A33: Indiana | B33: Barb Simpson | C33: Indiana Wildlife Federation | D33: ngo-nongame
A34: Indiana | B34: Stacy Sobat | C34: Indiana Department of Environmental Management | D34: state
A35: Indiana | B35: Dave Stratman | C35: Natural Resources Conservation Service NRCS | D35: federal
... A48: Indiana | B48: Lori Ludwig | C48: TrendyMinds | D48: business

Sheet Iowa
A1: state | B1: name | C1: agency | D1: type
A2: Iowa | B2: James Zohrer | C2: E Resources Group | D2: business
A3: Iowa | B3: Katy Reeder | C3: Iowa Department of Natural Resources | D3: state
A4: Iowa | B4: Julia Clymer | C4: Iowa Department of Natural Resources | D4: state
A5: Iowa | B5: Dale Garner | C5: Iowa Department of Natural Resources | D5: state
A6: Iowa | B6: Todd Bishop | C6: Iowa Department of Natural Resources | D6: state
A7: Iowa | B7: Steve Dinsmore | C7: Iowa State University | D7: school
A8: Iowa | B8: Bruce Ehresman | C8: Iowa Department of Natural Resources | D8: state
A9: Iowa | B9: Marlene Ehresman | C9: Iowa Wildlife Center | D9: ngo-nongame
A10: Iowa | B10: Chris Ensminger | C10: Iowa Department of Natural Resources | D10: state
A11: Iowa | B11: Scott Gritters | C11: Iowa Department of Natural Resources | D11: state
A12: Iowa | B12: Mark Gulick | C12: Iowa Department of Natural Resources | D12: state
... A60: Iowa | B60: Jay Gilliam | C60: Iowa Ornithologist Union | D60: ngo-nongame
A61: Iowa | B61: Todd Gosselink | C61: Iowa Department of Natural Resources | D61: state | F61: Total Number of Agencies (excluding independent) | G61: =counta(F3:F13,F15:F58) -> 55
A62: Iowa | B62: Mike Griffin | C62: Iowa Department of Natural Resources | D62: state
A63: Iowa | B63: Scott Gritters | C63: American Fisheries Society | D63: ngo-nongame
A64: Iowa | B64: Jeff Hall | C64: Representative Boswell Staff | D64: state
A65: Iowa | B65: Steve Hansen | C65: Iowa Woodland Owners Association | D65: ngo-nongame
A66: Iowa | B66: Doug Harr | C66: Iowa Department of Natural Resources | D66: state
A67: Iowa | B67: Greg Harson | C67: Iowa Department of Natural Resources | D67: state
A68: Iowa | B68: Neil Heiser | C68: Iowa Department of Natural Resources | D68: state
A69: Iowa | B69: Ace Hendricks | C69: Woodland Growers | D69: business
A70: Iowa | B70: Jane Hey | C70: Morningside College | D70: school
A71: Iowa | B71: Spencer Hill | C71: Iowa Trappers Association | D71: ngo-consumptive
A72: Iowa | B72: Steve Holland | C72: Iowa Department of Transportation | D72: state
A73: Iowa | B73: Daryl Howell | C73: Iowa Department of Natural Resources | D73: state
... A123: Iowa | B123: Kathleen Ziemer | C123: Butterfliz of Iowa | D123: ngo-nongame

Sheet Kansas
A1: state | B1: name | C1: agency | D1: type
A2: Kansas | B2: Chris Berens | C2: Kansas Department of Wildlife and Parks | D2: state
A3: Kansas | B3: Bill Busby | C3: Kansas Biological Survey | D3: school
A4: Kansas | B4: Jeff Conley | C4: Kansas Department of Wildlife and Parks | D4: state
A5: Kansas | B5: Zackary Cordes | C5: Kansas Department of Wildlife and Parks | D5: state
A6: Kansas | B6: Jennifer Delisle | C6: Kansas Biological Survey | D6: school
A7: Kansas | B7: Jordan Hofmeier | C7: Kansas Department of Wildlife and Parks | D7: state
A8: Kansas | B8: Ed Miller | C8: Kansas Department of Wildlife and Parks | D8: state
A9: Kansas | B9: Darn Riedle | C9: Kansas Department of Wildlife and Parks | D9: state
A10: Kansas | B10: Megan Rohweder | C10: Kansas Department of Wildlife and Parks | D10: state
A11: Kansas | B11: Mark VanScoyoc | C11: Kansas Department of Wildlife and Parks | D11: state
A12: Kansas | B12: Ryan Waters | C12: Kansas Department of Wildlife and Parks | D12: state
... A42: Kansas | B42: Jim Hays | C42: The Nature Conservancy | D42: ngo-nongame
A43: Kansas | B43: Eva Horne | C43: Konza Prairie Biological Station | D43: ngo-nongame | F43: Total Number of Agencies | G43: =counta(F3:F40) -> 38
A44: Kansas | B44: Mike Houck | C44: Environmental Division Fort Riley | D44: federal
A45: Kansas | B45: Matthew Hough | C45: Ducks Unlimited | D45: ngo-consumptive
A46: Kansas | B46: Lori Hutfles | C46: Sierra Club | D46: ngo-nongame
A47: Kansas | B47: Pete Janzen | C47: Wichita Audubon Society | D47: ngo-nongame
A48: Kansas | B48: Bill Jensen | C48: Central Plains Society of Mammalogists | D48: ngo-nongame
A49: Kansas | B49: Eric Johnson | C49: Westar Energy Company | D49: utility
A50: Kansas | B50: Doug Kaufman | C50: Kansas State University | D50: school
A51: Kansas | B51: Kelly Kindscher | C51: Kansas Biological Survey | D51: school
A52: Kansas | B52: Murray Laubhan | C52: US Fish and Wildlife Service USFWS | D52: federal
A53: Kansas | B53: Jason Luginbill | C53: US Fish and Wildlife Service USFWS | D53: federal
A54: Kansas | B54: Logan Martin | C54: Kansas Department of Wildlife and Parks | D54: state
A55: Kansas | B55: Laura Mendenhall | C55: US Fish and Wildlife Service USFWS | D55: federal
... A85: Kansas | B85: Rod Winkler | C85: US Department of Agriculture | D85: federal

Sheet Kentucky
A1: state | B1: name | C1: agency | D1: type
A2: Kentucky | B2: Zack Couch | C2: Kentucky Department of Fish and Wildlife Resources | D2: state
A3: Kentucky | B3: Laura Burford | C3: Kentucky Department of Fish and Wildlife Resources | D3: state
A4: Kentucky | B4: Dan Figert | C4: Kentucky Department of Fish and Wildlife Resources | D4: state
A5: Kentucky | B5: Mike Hardin | C5: Kentucky Department of Fish and Wildlife Resources | D5: state
A6: Kentucky | B6: Trey Prather | C6: Kentucky Department of Fish and Wildlife Resources | D6: state
A7: Kentucky | B7: Sunni Carr | C7: Kentucky Nature Preserves | D7: state
A8: Kentucky | B8: Zeb Weese | C8: Kentucky Nature Preserves | D8: state
A9: Kentucky | B9: John MacGregor | C9: Kentucky Department of Fish and Wildlife Resources | D9: state
A10: Kentucky | B10: Steve Bonney | C10: Kentucky Department of Fish and Wildlife Resources | D10: state
A11: Kentucky | B11: Brian Gray | C11: Kentucky Department of Fish and Wildlife Resources | D11: state
A12: Kentucky | B12: James Kiser | C12: Stantec | D12: business
... A38: Kentucky | B38: Mike Compton | C38: Kentucky Nature Preserves | D38: state
A39: Kentucky | B39: David Cravens | C39: Kentucky Division of Water | D39: state | F39: Total Number of Agencies (excluding independent) | G39: =counta(F3:F14,F16:F36) -> 33
A40: Kentucky | B40: Jacob Culp | C40: Kentucky Division of Water | D40: state
A41: Kentucky | B41: David Eisenhour | C41: Morehead State University | D41: school
A42: Kentucky | B42: Michael Floyd | C42: US Fish and Wildlife Service USFWS | D42: federal
A43: Kentucky | B43: Rebecca Blanton Johansen | C43: Austin Peay State University | D43: school
A44: Kentucky | B44: Monte McGregor | C44: Kentucky Department of Fish and Wildlife Resources | D44: state
A45: Kentucky | B45: Julieann Jacobs | C45: Kentucky Department of Fish and Wildlife Resources | D45: state
A46: Kentucky | B46: Wendell Haag | C46: US Forest Service USFS | D46: federal
A47: Kentucky | B47: David Hayes | C47: Eastern Kentucky University | D47: school
A48: Kentucky | B48: Michaela Rogers | C48: Kentucky Department of Fish and Wildlife Resources | D48: state
A49: Kentucky | B49: Shelby Fulton | C49: Kentucky Nature Preserves | D49: state
A50: Kentucky | B50: Ed DeWalt | C50: Illinois Natural History Survey | D50: state
A51: Kentucky | B51: Scott Grubbs | C51: Western Kentucky University | D51: school
... A111: Kentucky | B111: Cody Rhoden | C111: Kentucky Department of Fish and Wildlife Resources | D111: state

Sheet Louisiana
A1: state | B1: name | C1: agency | D1: type
A2: Louisiana | B2: Samuel Holcomb | C2: Louisiana Department of Wildlife and Fisheries | D2: state
A3: Louisiana | B3: Amity Bass | C3: Louisiana Department of Wildlife and Fisheries | D3: state
A4: Louisiana | B4: Christopher Reid | C4: Louisiana Department of Wildlife and Fisheries | D4: state
A5: Louisiana | B5: Michael Seymour | C5: Louisiana Department of Wildlife and Fisheries | D5: state
A6: Louisiana | B6: Nicole Lorenz | C6: Louisiana Department of Wildlife and Fisheries | D6: state
A7: Louisiana | B7: Beau Gregory | C7: Louisiana Department of Wildlife and Fisheries | D7: state
A8: Louisiana | B8: Sairah Javed | C8: Louisiana Department of Wildlife and Fisheries | D8: state
A9: Louisiana | B9: Kyle Balkum | C9: Louisiana Department of Wildlife and Fisheries | D9: state
A10: Louisiana | B10: J Brian Alford | C10: Louisiana Department of Wildlife and Fisheries | D10: state
A11: Louisiana | B11: Steven Beck | C11: Louisiana Department of Wildlife and Fisheries | D11: state
A12: Louisiana | B12: Rob Bourgeois | C12: Louisiana Department of Wildlife and Fisheries | D12: state
... A42: Louisiana | B42: Mandy Tumlin | C42: Louisiana Department of Wildlife and Fisheries | D42: state
A43: Louisiana | B43: Scott Durham | C43: Louisiana Department of Wildlife and Fisheries | D43: state | F43: Total Number of Agencies (excluding independent) | G43: =counta(F3:F9, F11:F40) -> 37
A44: Louisiana | B44: Bill Hano | C44: Louisiana Department of Wildlife and Fisheries | D44: state
A45: Louisiana | B45: Jason Adriance | C45: Louisiana Department of Wildlife and Fisheries | D45: state
A46: Louisiana | B46: Sean Jackson | C46: Louisiana Department of Wildlife and Fisheries | D46: state
A47: Louisiana | B47: Doug Albert | C47: Louisiana Department of Wildlife and Fisheries | D47: state
A48: Louisiana | B48: Jimmy Anthony | C48: Louisiana Department of Wildlife and Fisheries | D48: state
A49: Louisiana | B49: Marianne Burke | C49: Louisiana Department of Wildlife and Fisheries | D49: state
A50: Louisiana | B50: Mike Carloss | C50: Louisiana Department of Wildlife and Fisheries | D50: state
A51: Louisiana | B51: Patti Faulkner | C51: Louisiana Department of Wildlife and Fisheries | D51: state
A52: Louisiana | B52: Jim Hanifen | C52: Louisiana Department of Wildlife and Fisheries | D52: state
A53: Louisiana | B53: Nancy Higginbotham | C53: Louisiana Department of Wildlife and Fisheries | D53: state
A54: Louisiana | B54: Tim Morrison | C54: Louisiana Department of Wildlife and Fisheries | D54: state
A55: Louisiana | B55: Mike Olinde | C55: Louisiana Department of Wildlife and Fisheries | D55: state
... A172: Louisiana | B172: Wesley Daniel | C172: Louisiana State University | D172: school

Sheet Maine
A1: state | B1: name | C1: agency | D1: type
A2: Maine | B2: Barry Burgason | C2: Maine Forest Products Council | D2: ngo-consumptive
A3: Maine | B3: Tom Doak | C3: Small Woodland Owners Association of Maine | D3: ngo-consumptive
A4: Maine | B4: Claire Enterline | C4: Maine Department of Marine Resources | D4: state
A5: Maine | B5: Tim Glidden | C5: Maine Coast Heritage Trust | D5: ngo-nongame
A6: Maine | B6: Mitch Hartley | C6: US Fish and Wildlife Service USFWS | D6: federal
A7: Maine | B7: Emily Norton | C7: Maine Coastal Program | D7: state
A8: Maine | B8: Jeff Norment | C8: Natural Resources Conservation Service NRCS | D8: federal
A9: Maine | B9: Sally Stockwell | C9: Maine Audubon Society | D9: ngo-nongame
A10: Maine | B10: Angela Twitchell | C10: Brunswick-Topsham Land Trust | D10: ngo-nongame
A11: Maine | B11: Jed Wright | C11: US Fish and Wildlife Service USFWS | D11: federal
A12: Maine | B12: Barbara Vickery | C12: The Nature Conservancy | D12: ngo-nongame
... A20: Maine | B20: Slade Moore | C20: Maine Coastal Program | D20: state
A21: Maine | B21: Ray Owen | C21: University of Maine | D21: school | F21: Number of People Not Given:
A22: Maine | B22: Brad Allen | C22: Maine Department of Inland Fisheries and Wildlife | D22: state
A23: Maine | B23: Lindsay Tudor | C23: Maine Department of Inland Fisheries and Wildlife | D23: state
A24: Maine | B24: Tom Hodgman | C24: Maine Department of Inland Fisheries and Wildlife | D24: state
A25: Maine | B25: Danielle D'Auria | C25: Maine Department of Inland Fisheries and Wildlife | D25: state
A26: Maine | B26: Erynn Call | C26: Maine Department of Inland Fisheries and Wildlife | D26: state
A27: Maine | B27: Kelsey Sullivan | C27: Maine Department of Inland Fisheries and Wildlife | D27: state
A28: Maine | B28: Beth Swartz | C28: Maine Department of Inland Fisheries and Wildlife | D28: state
A29: Maine | B29: Kerek Yorks | C29: Maine Department of Inland Fisheries and Wildlife | D29: state
A30: Maine | B30: Wally Jakubas | C30: Maine Department of Inland Fisheries and Wildlife | D30: state
A31: Maine | B31: Jen Vashon | C31: Maine Department of Inland Fisheries and Wildlife | D31: state
A32: Maine | B32: Cory Mosby | C32: Maine Department of Inland Fisheries and Wildlife | D32: state
A33: Maine | B33: Merry Gallagher | C33: Maine Department of Inland Fisheries and Wildlife | D33: state
... A52: state | B52: name | C52: agency | D52: type
A53: Maine | C53: Acadia National Park | D53: federal
A54: Maine | C54: Maine Army National Guard | D54: state
A55: Maine | C55: National Oceanic and Atmospheric Administration NOAA | D55: federal
A56: Maine | C56: Baxter State Park | D56: state
A57: Maine | C57: Maine Department of Agriculture, Conservation and Forestry | D57: state
A58: Maine | C58: Maine Department of Environmental Protection | D58: state
A59: Maine | C59: Maine Department of Transportation | D59: state
A60: Maine | C60: Aroostook Band of MicMac Indians | D60: indigenous
A61: Maine | C61: Houlton Band of Maliseet Indians | D61: indigenous
A62: Maine | C62: Passamaquoddy Tribe Indian Township Reservation | D62: indigenous
A63: Maine | C63: Passamaquoddy Tribe Pleasant Point Reservation | D63: indigenous
A64: Maine | C64: Penobscot Nation | D64: indigenous
... A91: Maine | C91: Maine Cooperative Fish and Wildlife Research Unit | D91: partnership
A92: Maine | C92: Main Discovery Museum | D92: ngo-nongame | F92: Total Number of Agencies (excluding independent) | G92: =counta(F3, F5:F18, F23:F89) -> 82
A93: Maine | C93: Maine Farm Bureau | D93: ngo-consumptive
A94: Maine | C94: Maine Farmland Trust | D94: ngo-consumptive
A95: Maine | C95: Maine Lakes Society | D95: ngo-nongame
A96: Maine | C96: Maine Maritime Academy | D96: school
A97: Maine | C97: Maine Professional Guides Association | D97: ngo-consumptive
A98: Maine | C98: Maine Rivers | D98: ngo-nongame
A99: Maine | C99: Maine SeaGrant | D99: school
A100: Maine | C100: Maine Tourism Association | D100: state
A101: Maine | C101: Maine Trappers Association | D101: ngo-consumptive
A102: Maine | C102: Maine's Teaming with Wildlife | D102: committee-nongame
A103: Maine | C103: Manomet Center for Conservation Science | D103: ngo-nongame
A104: Maine | C104: Mount Agamenticus to the Sea Conservation Initiative | D104: ngo-nongame
... A119: Maine | C119: Wildlife Alliance of Maine | D119: ngo-nongame

Sheet Maryland
A1: state | B1: name | C1: agency | D1: type
A2: Maryland | B2: Ingrid Brofman Sylvester | C2: Maryland Department of Natural Resources | D2: state
A3: Maryland | B3: Annalise Kenney | C3: Maryland Department of Natural Resources | D3: state
A4: Maryland | B4: Gwen Brewer | C4: Maryland Department of Natural Resources | D4: state
A5: Maryland | B5: Lynn Davidson | C5: Maryland Department of Natural Resources | D5: state
A6: Maryland | B6: Jennifer Selfridge | C6: Maryland Department of Natural Resources | D6: state | F6: Names/Number of People Not Given:
A7: Maryland | B7: Jason Harrison | C7: Maryland Department of Natural Resources | D7: state
A8: Maryland | B8: Jay Kilian | C8: Maryland Department of Natural Resources | D8: state
A9: Maryland | B9: Dana Limpert | C9: Maryland Department of Natural Resources | D9: state
A10: Maryland | B10: James McCann | C10: Maryland Department of Natural Resources | D10: state
A11: Maryland | B11: Jonathan McKnight | C11: Maryland Department of Natural Resources | D11: state
A12: state | B12: name | C12: agency | D12: type
A13: Maryland | C13: Frostburg State University | D13: school
A14: Maryland | C14: Salisbury University | D14: school
A15: Maryland | C15: University of Maryland | D15: school
A16: Maryland | C16: National Oceanic and Atmospheric Administration NOAA | D16: federal
A17: Maryland | C17: US Fish and Wildlife Service USFWS | D17: federal
A18: Maryland | C18: National Aquarium in Baltimore | D18: federal
A19: Maryland | C19: Susquehannock Wildlife Society | D19: ngo-nongame
A20: Maryland | C20: Bowie State University | D20: school
A21: Maryland | C21: Cornell University, eBird | D21: school
A22: Maryland | C22: Garrett College | D22: school
A23: Maryland | C23: Washington College | D23: school
A24: Maryland | C24: Ann Arundel County Department of Recreation and Parks | D24: local
... A48: Maryland | C48: US Department of Agriculture | D48: federal
A49: Maryland | C49: Maryland Entomological Society | D49: ngo-nongame | F49: Total Number of Agencies | G49: =counta(F3, F8:F46) -> 40
A50: Maryland | C50: Mid-Atlantic Invertebrate Field Studies | D50: ngo-nongame
A51: Maryland | C51: Interstate Commission on the Potomac River Basin | D51: partnership

Sheet Massachusetts
A1: state | B1: name | C1: agency | D1: type
A2: Massachusetts | B2: Tara Boswell | C2: Massachusetts Division of Fisheries and Wildlife | D2: state
A3: Massachusetts | B3: Jonathan Brooks | C3: Massachusetts Division of Fisheries and Wildlife | D3: state
A4: Massachusetts | B4: Jack Buckley | C4: Massachusetts Division of Fisheries and Wildlife | D4: state
A5: Massachusetts | B5: Chris Buelow | C5: Massachusetts Division of Fisheries and Wildlife | D5: state
A6: Massachusetts | B6: Bill Byrne | C6: Massachusetts Division of Fisheries and Wildlife | D6: state | F6: Names/Number of People Not Given:
A7: Massachusetts | B7: Laura Conlee | C7: Massachusetts Division of Fisheries and Wildlife | D7: state
A8: Massachusetts | B8: Nicole DeAngelis | C8: Massachusetts Division of Fisheries and Wildlife | D8: state
A9: Massachusetts | B9: Rebecca DiGirolomo | C9: Massachusetts Division of Fisheries and Wildlife | D9: state
A10: Massachusetts | B10: Tom French | C10: Massachusetts Division of Fisheries and Wildlife | D10: state
A11: Massachusetts | B11: Karro Frost | C11: Massachusetts Division of Fisheries and Wildlife | D11: state
A12: Massachusetts | B12: Leanda Fontaine Gagnon | C12: Massachusetts Division of Fisheries and Wildlife | D12: state
A13: Massachusetts | B13: Sarah Haggerty | C13: Massachusetts Division of Fisheries and Wildlife | D13: state
A14: Massachusetts | B14: Lynn Harper | C14: Massachusetts Division of Fisheries and Wildlife | D14: state
A15: Massachusetts | B15: Brian Hawthorne | C15: Massachusetts Division of Fisheries and Wildlife | D15: state
A16: Massachusetts | B16: Peter Hazelton | C16: Massachusetts Division of Fisheries and Wildlife | D16: state
A17: Massachusetts | B17: H Heusmann | C17: Massachusetts Division of Fisheries and Wildlife | D17: state
A18: Massachusetts | B18: Michael Huguenin | C18: Massachusetts Division of Fisheries and Wildlife | D18: state
... A24: Massachusetts | B24: Wayne MacCallum | C24: Massachusetts Division of Fisheries and Wildlife | D24: state
A25: Massachusetts | B25: Lisa Plagge MacGillivray | C25: Massachusetts Division of Fisheries and Wildlife | D25: state | F25: Total Number of Agencies (excluding 5 Unnamed listings) | G25: =counta(F3,F8:F16, F22) -> 11
A26: Massachusetts | B26: Sarah Maier | C26: Massachusetts Division of Fisheries and Wildlife | D26: state
A27: Massachusetts | B27: Misty-Anne Marold | C27: Massachusetts Division of Fisheries and Wildlife | D27: state
A28: Massachusetts | B28: Ben Mazzei | C28: Massachusetts Division of Fisheries and Wildlife | D28: state
A29: Massachusetts | B29: Bridgett McAlice | C29: Massachusetts Division of Fisheries and Wildlife | D29: state
A30: Massachusetts | B30: Carlolyn Mostello | C30: Massachusetts Division of Fisheries and Wildlife | D30: state
A31: Massachusetts | B31: Michael W Nelson | C31: Massachusetts Division of Fisheries and Wildlife | D31: state
A32: Massachusetts | B32: John O'Leary | C32: Massachusetts Division of Fisheries and Wildlife | D32: state
A33: Massachusetts | B33: David Paulson | C33: Massachusetts Division of Fisheries and Wildlife | D33: state
A34: Massachusetts | B34: Marianne Piche | C34: Massachusetts Division of Fisheries and Wildlife | D34: state
A35: Massachusetts | B35: Jonathan Regosin | C35: Massachusetts Division of Fisheries and Wildlife | D35: state
A36: Massachusetts | B36: Todd Richards | C36: Massachusetts Division of Fisheries and Wildlife | D36: state
A37: Massachusetts | B37: Susan Benoit Sacco | C37: Massachusetts Division of Fisheries and Wildlife | D37: state
... A51: state | B51: name | C51: agency | D51: type
A52: Massachusetts | C52: Massachusetts Rivers Alliance | D52: ngo-nongame
A53: Massachusetts | C53: Massachusetts Audubon | D53: ngo-nongame
A54: Massachusetts | C54: Massachusetts Water Resources Authority | D54: state
A55: Massachusetts | C55: Environmental League of Massachusetts | D55: ngo-nongame
A56: Massachusetts | C56: Cape Cod Cranberry Growers Association | D56: ngo-consumptive
A57: Massachusetts | C57: Massachusetts Water Works Association | D57: utility
A58: Massachusetts | C58: Conservation Law Foundation | D58: ngo-nongame
A59: Massachusetts | C59: The Nature Conservancy | D59: ngo-nongame
A60: Massachusetts | C60: Charles River Watershed Association | D60: ngo-nongame
A61: Massachusetts | C61: US Geological Survey USGS | D61: federal
A62: Massachusetts | C62: Unnamed private engineering firms | D62: business
A63: Massachusetts | C63: Unnamed environmental law expert | D63: independent
... A66: Massachusetts | C66: Unnamed municipal public works managers | D66: local

Sheet Michigan
A1: state | B1: name | C1: agency | D1: type
A2: Michigan | B2: Dan Kennedy | C2: Michigan Department of Natural Resources | D2: state
A3: Michigan | B3: Christine Hanaburgh | C3: Michigan Department of Natural Resources | D3: state
A4: Michigan | B4: Mike Donovan | C4: Michigan Department of Natural Resources | D4: state
A5: Michigan | B5: Ray Fahlsing | C5: Michigan Department of Natural Resources | D5: state
A6: Michigan | B6: Bill Sterrett | C6: Michigan Department of Natural Resources | D6: state | F6: Names/Number of People Not Given:
A7: Michigan | B7: Mary Rabe | C7: Michigan Department of Natural Resources | D7: state
A8: Michigan | B8: Karen Cleveland | C8: Michigan Department of Natural Resources | D8: state
A9: Michigan | B9: Joanne Foreman | C9: Michigan Department of Natural Resources | D9: state
A10: Michigan | B10: Caitlin Boon | C10: Michigan Department of Natural Resources | D10: state
A11: Michigan | B11: Arthur Cooper | C11: Michigan Department of Natural Resources | D11: state
A12: Michigan | B12: Danielle Forsyth Kilijanczyk | C12: Michigan Department of Natural Resources | D12: state
A13: Michigan | B13: Ken Yeh | C13: Michigan Department of Natural Resources | D13: state
A14: Michigan | B14: Bill Moritz | C14: Michigan Department of Natural Resources | D14: state
A15: Michigan | B15: Vincent Mata | C15: Michigan Department of Natural Resources | D15: state
A16: Michigan | B16: Jim Dexter | C16: Michigan Department of Natural Resources | D16: state
A17: Michigan | B17: Autumn Spitzley | C17: Michigan Department of Natural Resources | D17: state
A18: Michigan | B18: Shennelle Anthony | C18: Michigan Department of Natural Resources | D18: state
A19: state | B19: name | C19: agency | D19: type
A20: Michigan | C20: Adrian College | D20: school
A21: Michigan | C21: Alma College | D21: school
A22: Michigan | C22: Central Michigan University | D22: school
A23: Michigan | C23: Clinton River Watershed Council | D23: ngo-nongame
A24: Michigan | C24: Detroit Zoo | D24: ngo-nongame
A25: Michigan | C25: Ducks Unlimited | D25: ngo-consumptive
A26: Michigan | C26: Eastern Michigan University | D26: school
A27: Michigan | C27: Fisheries and Oceans Canada | D27: ngo-consumptive
A28: Michigan | C28: Friends of the Rouge | D28: ngo-nongame
A29: Michigan | C29: Golden-winged Warbler Conservation Initiative | D29: ngo-nongame
A30: Michigan | C30: Grand Traverse Band of Ottawa and Chippewa Indians | D30: indigenous
A31: Michigan | C31: Grand Traverse Regional Land Conservancy | D31: ngo-nongame
... A58: Michigan | C58: University of Michigan | D58: school
A59: Michigan | C59: US Fish and Wildlife Service USFWS | D59: federal | F59: Total Number of Agencies | G59: =counta(F3,F8:F55) -> 49
A60: Michigan | C60: US Forest Service USFS | D60: federal
A61: Michigan | C61: US Geological Survey USGS | D61: federal
A62: Michigan | C62: Wildlife Habitat Council | D62: ngo-nongame
A63: Michigan | C63: Wisconsin Entomological Society | D63: ngo-nongame
A64: Michigan | C64: World Chelonian Trust | D64: ngo-nongame
A65: Michigan | C65: Kalamazoo Nature Center | D65: ngo-nongame
A66: Michigan | C66: Herpetological Resource and Management | D66: ngo-nongame
A67: Michigan | C67: Organization for Bat Conservation | D67: ngo-nongame

Sheet Minnesota
A1: state | B1: name | C1: agency | D1: type
A2: Minnesota | B2: Faith Balch | C2: Minnesota Department of Natural Resources | D2: state
A3: Minnesota | B3: Bill Bleckwenn | C3: Minnesota Department of Natural Resources | D3: state
A4: Minnesota | B4: Darn Carlson | C4: Minnesota Department of Natural Resources | D4: state
A5: Minnesota | B5: Bob Dunlap | C5: Minnesota Department of Natural Resources | D5: state
A6: Minnesota | B6: Carrol Henderson | C6: Minnesota Department of Natural Resources | D6: state
A7: Minnesota | B7: Krista Larson | C7: Minnesota Department of Natural Resources | D7: state
A8: Minnesota | B8: Jane Norris | C8: Minnesota Department of Natural Resources | D8: state
A9: Minnesota | B9: Nancy Spooner-Mueller | C9: Minnesota Department of Natural Resources | D9: state
A10: Minnesota | B10: Jacquelyn Bacigalupi | C10: Minnesota Department of Natural Resources | D10: state
A11: Minnesota | B11: Rich Baker | C11: Minnesota Department of Natural Resources | D11: state
A12: Minnesota | B12: Peter Buesseler | C12: Minnesota Department of Natural Resources | D12: state
... A20: Minnesota | B20: Mark Martell | C20: Audubon Minnesota | D20: ngo-nongame
A21: Minnesota | B21: Keith Mykleseth | C21: Minnesota Department of Natural Resources | D21: state | F21: Total Number of Agencies | G21: =counta(F3:F18) -> 16
A22: Minnesota | B22: Laura Preus | C22: Minnesota Department of Natural Resources | D22: state
A23: Minnesota | B23: Jim Sehl | C23: Minnesota Department of Natural Resources | D23: state
A24: Minnesota | B24: Bob Welsh | C24: Minnesota Department of Natural Resources | D24: state
A25: Minnesota | B25: Keith Wendt | C25: Minnesota Department of Natural Resources | D25: state
A26: Minnesota | B26: Gaea Crozier | C26: Minnesota Department of Natural Resources | D26: state
A27: Minnesota | B27: Jamie Edwards | C27: Minnesota Department of Natural Resources | D27: state
A28: Minnesota | B28: Lisa Gelvin-Innvaer | C28: Minnesota Department of Natural Resources | D28: state
A29: Minnesota | B29: Christine Herwig | C29: Minnesota Department of Natural Resources | D29: state
A30: Minnesota | B30: Gerda Nordquist | C30: Minnesota Department of Natural Resources | D30: state
A31: Minnesota | B31: John Erb | C31: Minnesota Department of Natural Resources | D31: state
A32: Minnesota | B32: Ron Moen | C32: University of Minnesota | D32: school
A33: Minnesota | B33: Dick Oehlenschlager | C33: Science Museum of Minnesota | D33: ngo-nongame
... A128: Minnesota | B128: Jeff Zajac | C128: Minnesota Department of Natural Resources | D128: state

Sheet Mississippi
A1: state | B1: name | C1: agency | D1: type
A2: Mississippi | B2: Kathy Shelton | C2: Mississippi Department of Wildlife, Fisheries and Parks | D2: state
A3: Mississippi | B3: Ryan Theel | C3: US Fish and Wildlife Service USFWS | D3: federal
A4: Mississippi | B4: Joelle Carney | C4: Mississippi Department of Wildlife, Fisheries and Parks | D4: state
A5: Mississippi | B5: Chad Dacus | C5: Mississippi Department of Wildlife, Fisheries and Parks | D5: state
A6: Mississippi | B6: Sheena Feist | C6: Mississippi Department of Wildlife, Fisheries and Parks | D6: state
A7: Mississippi | B7: John Gruchy | C7: Mississippi Department of Wildlife, Fisheries and Parks | D7: state | F7: Names/Number of People Not Given:
A8: Mississippi | B8: Rick Hamrick | C8: Mississippi Department of Wildlife, Fisheries and Parks | D8: state
A9: Mississippi | B9: Bob Jones | C9: Mississippi Department of Wildlife, Fisheries and Parks | D9: state
A10: Mississippi | B10: Tom Mann | C10: Mississippi Department of Wildlife, Fisheries and Parks | D10: state
A11: Mississippi | B11: Verity Mathis | C11: Mississippi Department of Wildlife, Fisheries and Parks | D11: state
A12: Mississippi | B12: Scott Peyton | C12: Mississippi Department of Wildlife, Fisheries and Parks | D12: state
A13: Mississippi | B13: Larry Pugh | C13: Mississippi Department of Wildlife, Fisheries and Parks | D13: state
A14: Mississippi | B14: Dennis Riecke | C14: Mississippi Department of Wildlife, Fisheries and Parks | D14: state
A15: Mississippi | B15: Matt Roberts | C15: Mississippi Department of Wildlife, Fisheries and Parks | D15: state
A16: Mississippi | B16: Andy Sanderson | C16: Mississippi Department of Wildlife, Fisheries and Parks | D16: state
A17: Mississippi | B17: Heather Sullivan | C17: Mississippi Department of Wildlife, Fisheries and Parks | D17: state
A18: Mississippi | B18: Sherry Surrette | C18: Mississippi Department of Wildlife, Fisheries and Parks | D18: state
A19: Mississippi | B19: Lisa Yager | C19: Mississippi Department of Wildlife, Fisheries and Parks | D19: state
... A22: state | B22: name | C22: agency | D22: type
A23: Mississippi | C23: 25x25 Alliance | D23: ngo-consumptive
A24: Mississippi | C24: Audubon Mississippi | D24: ngo-nongame
A25: Mississippi | C25: US Bureau of Land Management | D25: federal
A26: Mississippi | C26: Delta Wildlife | D26: ngo-nongame
A27: Mississippi | C27: Ducks Unlimited | D27: ngo-consumptive
A28: Mississippi | C28: Grand Bay National Estuarine Research Reserve | D28: federal
A29: Mississippi | C29: Gulf Coast Joint Venture | D29: partnership
A30: Mississippi | C30: Gulf Coastal Plains and Ozarks Landscape Conservation Cooperative | D30: partnership
A31: Mississippi | C31: Gulf Restoration Network | D31: ngo-nongame
A32: Mississippi | C32: Land Trust for the Mississippi Coastal Plain | D32: ngo-nongame
A33: Mississippi | C33: Louisiana Department of Wildlife and Fisheries | D33: state
A34: Mississippi | C34: Lower Mississippi Valley Joint Venture | D34: partnership
... A57: Mississippi | C57: The Trust for Public Land | D57: ngo-nongame
A58: Mississippi | C58: University of Mississippi | D58: school | F58: Total Number of Agencies | G58: =counta(F3:F4,F9:F55) -> 49
A59: Mississippi | C59: University of Southern Mississippi | D59: school
A60: Mississippi | C60: US Army Corps of Engineers | D60: federal
A61: Mississippi | C61: US Forest Service USFS | D61: federal
A62: Mississippi | C62: US Department of Agriculture | D62: federal
A63: Mississippi | C63: Natural Resources Conservation Service NRCS | D63: federal
A64: Mississippi | C64: US Geological Survey USGS | D64: federal
A65: Mississippi | C65: Western Carolina University | D65: school
A66: Mississippi | C66: Weyerhaeuser | D66: business
A67: Mississippi | C67: Wild South | D67: ngo-nongame
A68: Mississippi | C68: Wildlife Mississippi | D68: ngo-nongame

Sheet Missouri
A1: state | B1: name | C1: agency | D1: type
A2: Missouri | B2: Dennis Figg | C2: Missouri Department of Conservation | D2: state
A3: Missouri | B3: Phillip Hanberry | C3: University of Missouri | D3: school
A4: Missouri | B4: Kelly Rezac | C4: Missouri Department of Conservation | D4: state
A5: Missouri | B5: Nathan Muenks | C5: Missouri Department of Conservation | D5: state
A6: Missouri | B6: Robbie Doerhoff | C6: Missouri Department of Conservation | D6: state
A7: Missouri | B7: Taliaa Pendergrass | C7: Missouri Department of Conservation | D7: state | F7: Names/Number of People Not Given:
A8: Missouri | B8: Joshua Ernst | C8: Missouri Department of Conservation | D8: state
A9: Missouri | B9: Courtney Duchardt | C9: Missouri Department of Conservation | D9: state
A10: Missouri | B10: Lin Kuhn | C10: Missouri Department of Conservation | D10: state
A11: Missouri | B11: Donnamarie Duffin | C11: Missouri Department of Conservation | D11: state
A12: Missouri | B12: Ange Corson | C12: Missouri Department of Conservation | D12: state
A13: Missouri | B13: Steve Westin | C13: Missouri Department of Conservation | D13: state
A14: Missouri | B14: Kevin Borisenko | C14: Missouri Department of Conservation | D14: state
A15: Missouri | B15: Norman Murray | C15: Missouri Department of Conservation | D15: state
A16: Missouri | B16: Jennifer Battson Warren | C16: Missouri Department of Conservation | D16: state
A17: Missouri | B17: Lisa Allen | C17: Missouri Department of Conservation | D17: state
A18: Missouri | B18: Brian Canaday | C18: Missouri Department of Conservation | D18: state
A19: Missouri | B19: Bill White | C19: Missouri Department of Conservation | D19: state
... A59: Missouri | B59: Chris McLeland | C59: Missouri Department of Conservation | D59: state
A60: Missouri | B60: Rod Doolen | C60: Missouri Department of Conservation | D60: state | F60: Total Number of Agencies | G60: =counta(F3:F4, F9:F57) -> 51
A61: Missouri | B61: John Murphy | C61: Missouri Department of Conservation | D61: state
A62: Missouri | B62: Randy Haas | C62: Missouri Department of Conservation | D62: state
A63: Missouri | B63: Eric Rahm | C63: Missouri Department of Conservation | D63: state
A64: Missouri | B64: Matt Matheney | C64: Missouri Department of Conservation | D64: state
A65: Missouri | B65: Phil Pitts | C65: Missouri Department of Conservation | D65: state
A66: Missouri | B66: Joe McMullen | C66: Missouri Department of Conservation | D66: state
A67: Missouri | B67: Sherry Fisher | C67: Missouri Department of Conservation | D67: state
A68: Missouri | B68: Paul Blanchard | C68: Missouri Department of Conservation | D68: state
A69: Missouri | B69: Jason Crites | C69: Missouri Department of Conservation | D69: state
A70: Missouri | B70: Rich Horton | C70: Missouri Department of Conservation | D70: state
A71: Missouri | B71: Blake Stephens | C71: Missouri Department of Conservation | D71: state
A72: Missouri | B72: Rob Pulliam | C72: Missouri Department of Conservation | D72: state
... A100: state | B100: name | C100: agency | D100: type
A101: Missouri | C101: American Bird Conservancy | D101: ngo-nongame
A102: Missouri | C102: American Fisheries Society | D102: ngo-consumptive
A103: Missouri | C103: Animal and Plant Health Inspection Service | D103: federal
A104: Missouri | C104: Audubon Society of Missouri | D104: ngo-nongame
A105: Missouri | C105: Central Hardwoods Joint Venture | D105: partnership
A106: Missouri | C106: Conservation Federation of Missouri | D106: ngo-nongame
A107: Missouri | C107: Ducks Unlimited | D107: ngo-consumptive
A108: Missouri | C108: Forest and Woodland Association of Missouri | D108: ngo-consumptive
A109: Missouri | C109: Gulf Coastal Plains and Ozarks Landscape Conservation Cooperative | D109: partnership
A110: Missouri | C110: L-A-D Foundation | D110: ngo-consumptive
A111: Missouri | C111: Mark Twain National Forest | D111: federal
A112: Missouri | C112: Missouri Association of Soil and Water Conservation Districts | D112: ngo-consumptive
... A149: Missouri | C149: National Park Service | D149: federal

Sheet Montana
A1: state | B1: name | C1: agency | D1: type
A2: Montana | B2: Jeff Hagener | C2: Montana Fish, Wildlife and Parks | D2: state
A3: Montana | B3: Ron Aasheim | C3: Montana Fish, Wildlife and Parks | D3: state
A4: Montana | B4: Ken McDonald | C4: Montana Fish, Wildlife and Parks | D4: state
A5: Montana | B5: Bruce Rich | C5: Montana Fish, Wildlife and Parks | D5: state
A6: Montana | B6: Pat Flowers | C6: Montana Fish, Wildlife and Parks | D6: state
A7: Montana | B7: Tom Flowers | C7: Montana Fish, Wildlife and Parks | D7: state
A8: Montana | B8: Leo Rosenthal | C8: Montana Fish, Wildlife and Parks | D8: state
A9: Montana | B9: Ladd Knotek | C9: Montana Fish, Wildlife and Parks | D9: state
A10: Montana | B10: Ron Spoon | C10: Montana Fish, Wildlife and Parks | D10: state
A11: Montana | B11: Grant Grisak | C11: Montana Fish, Wildlife and Parks | D11: state
A12: Montana | B12: Mike Ruggles | C12: Montana Fish, Wildlife and Parks | D12: state
... A20: Montana | B20: Ashley Beyer | C20: Montana Fish, Wildlife and Parks | D20: state
A21: Montana | B21: Mark Sullivan | C21: Montana Fish, Wildlife and Parks | D21: state | F21: Total number of Agencies | G21: =counta(F3:F18) -> 16
A22: Montana | B22: John Ensign | C22: Montana Fish, Wildlife and Parks | D22: state
A23: Montana | B23: Lauri Hanauska-Brown | C23: Montana Fish, Wildlife and Parks | D23: state
A24: Montana | B24: Kristina Smucker | C24: Montana Fish, Wildlife and Parks | D24: state
A25: Montana | B25: Jeff Chaffin | C25: US Bureau of Land Management | D25: federal
A26: Montana | B26: Gary Tabor | C26: Center for Large Landscape Conservation | D26: ngo-nongame
A27: Montana | B27: Bryce Maxell | C27: Montana Natural Heritage Program | D27: state
A28: Montana | B28: Pete Husby | C28: Natural Resources Conservation Service NRCS | D28: federal
A29: Montana | B29: Brian Martin | C29: The Nature Conservancy | D29: ngo-nongame
A30: Montana | B30: Yvette Converse | C30: US Fish and Wildlife Service USFWS | D30: federal
A31: Montana | B31: Alan Dohmen | C31: US Forest Service USFS | D31: federal
A32: Montana | C32: Montana Natural Heritage Program | D32: state
A33: Montana | C33: Montana Natural Heritage Program | D33: state
A34: Montana | C34: National Park Service | D34: federal
A35: Montana | C35: US Fish and Wildlife Service USFWS | D35: federal
A36: Montana | C36: US Forest Service USFS | D36: federal
A37: Montana | C37: US Forest Service USFS | D37: federal
A38: Montana | C38: US Forest Service USFS | D38: federal
A39: Montana | C39: US Forest Service USFS | D39: federal
A40: Montana | C40: American Wildlands | D40: ngo-nongame
A41: Montana | C41: American Wildlands | D41: ngo-nongame
A42: Montana | C42: Center for Large Landscape Conservation | D42: ngo-nongame
A43: Montana | C43: Defenders of Wildlife | D43: ngo-nongame
... A54: Montana | C54: Wildlife Conservation Society | D54: ngo-nongame

Sheet Nebraska
A1: state | B1: name | C1: agency | D1: type
A2: Nebraska | B2: Rick Schneider | C2: Nebraska Game and Parks Commission | D2: state
A3: Nebraska | B3: Gerry Steinauer | C3: Nebraska Game and Parks Commission | D3: state
A4: Nebraska | B4: Melissa Panella | C4: Nebraska Game and Parks Commission | D4: state
A5: Nebraska | B5: Mark Humpert | C5: Nebraska Game and Parks Commission | D5: state
A6: Nebraska | B6: Jeff Abegglen | C6: US Forest Service USFS | D6: federal
A7: Nebraska | B7: Pete Berthelsen | C7: Pheasants Forever | D7: ngo-consumptive
A8: Nebraska | B8: Andy Bishop | C8: Rainwater Basin Joint Venture | D8: ngo-nongame
A9: Nebraska | B9: Kelly Brunkhorst | C9: Nebraska Corn Board | D9: ngo-consumptive
A10: Nebraska | B10: Barb Cooksley | C10: Sandhills Task Force | D10: ngo-nongame
A11: Nebraska | B11: Kenny Dinan | C11: US Fish and Wildlife Service USFWS | D11: federal
A12: Nebraska | B12: Steve Donovan | C12: Ducks Unlimited | D12: ngo-consumptive
... A56: Nebraska | B56: Amanda Filip | C56: Nebraska Prairie Partners | D56: ngo-nongame
A57: Nebraska | B57: Betty Grennon | C57: Fontenelle Nature Association | D57: ngo-nongame | F57: Total Number of Agencies | G57: =counta(F3:F54) -> 52
A58: Nebraska | B58: Marcia Lee | C58: Central Platte Natural Resources District | D58: ngo-consumptive
A59: Nebraska | B59: Keanna Leonard | C59: Rowe Sanctuary | D59: ngo-nongame
A60: Nebraska | B60: Valerie Newman | C60: National Park Service | D60: federal
A61: Nebraska | B61: Amy Sandeen | C61: Prairie Loft Center for Outdoor and Agricultural Learning | D61: ngo-nongame
A62: Nebraska | B62: Rick Schmidt | C62: Fontenelle Nature Association | D62: ngo-nongame
A63: Nebraska | B63: Kirsten Smith | C63: Lincoln Public Schools | D63: school
A64: Nebraska | B64: Dennis Ferraro | C64: University of Nebraska | D64: school
A65: Nebraska | B65: Dan Fogell | C65: Southeast Community College | D65: school
A66: Nebraska | B66: Matt Brust | C66: Chadron State College | D66: school
A67: Nebraska | B67: Wyatt Hoback | C67: University of Nebraska | D67: school
A68: Nebraska | B68: Steve Spomer | C68: University of Nebraska | D68: school
A69: Nebraska | B69: Patricia Freeman | C69: University of Nebraska | D69: school
... A152: Nebraska | B152: Paul Johnsgard | C152: University of Nebraska | D152: school

Sheet Nevada
A1: state | B1: name | C1: agency | D1: type
A2: Nevada | B2: Joe Barnes | C2: Nevada Department of Wildlife | D2: state
A3: Nevada | B3: Lee Davis | C3: Nevada Department of Wildlife | D3: state
A4: Nevada | B4: Jasmine Kleiber | C4: Nevada Department of Wildlife | D4: state
A5: Nevada | B5: Jennifer Newmark | C5: Nevada Department of Wildlife | D5: state
A6: Nevada | B6: Brandon Senger | C6: Nevada Department of Wildlife | D6: state
A7: Nevada | B7: Christy Klinger | C7: Nevada Department of Wildlife | D7: state
A8: Nevada | B8: David Catalano | C8: Nevada Department of Wildlife | D8: state
A9: Nevada | B9: Julie Bless | C9: Nevada Department of Wildlife | D9: state
A10: Nevada | B10: Liz Mack | C10: Kearns and West | D10: business
A11: Nevada | B11: Angela Hessenius | C11: Kearns and West | D11: business
A12: Nevada | B12: Kristin Szabo | C12: Nevada Division of Natural Heritage | D12: state
... A20: Nevada | B20: Chris Crookshanks | C20: Nevada Department of Wildlife | D20: state
A21: Nevada | B21: Chris Vasey | C21: Nevada Department of Wildlife | D21: state | F21: Total Number of Agencies | G21: =counta(F3:F18) -> 16
A22: Nevada | B22: Cody McKee | C22: Nevada Department of Wildlife | D22: state
A23: Nevada | B23: Cody Schroeder | C23: Nevada Department of Wildlife | D23: state
A24: Nevada | B24: Ial Holl | C24: Nevada Department of Wildlife | D24: state
A25: Nevada | B25: Jane VanGunst | C25: Nevada Department of Wildlife | D25: state
A26: Nevada | B26: Jason Jones | C26: Nevada Department of Wildlife | D26: state
A27: Nevada | B27: Jason Williams | C27: Nevada Department of Wildlife | D27: state
A28: Nevada | B28: Jenni Jeffers | C28: Nevada Department of Wildlife | D28: state
A29: Nevada | B29: Jinna Larkin | C29: Nevada Department of Wildlife | D29: state
A30: Nevada | B30: Justin Small | C30: Nevada Department of Wildlife | D30: state
A31: Nevada | B31: Katie Andrle | C31: Nevada Department of Wildlife | D31: state
A32: Nevada | B32: Kevin Netcher | C32: Nevada Department of Wildlife | D32: state
A33: Nevada | B33: Kim Tisdale | C33: Nevada Department of Wildlife | D33: state
... A85: Nevada | B85: Alexa McKerrow | C85: US Geological Survey USGS | D85: federal

Sheet New Hampshire
A1: state | B1: name | C1: agency | D1: type
A2: New Hampshire | B2: Glenn Normandeau | C2: New Hampshire Fish and Game | D2: state
A3: New Hampshire | B3: Mark Ellingwood | C3: New Hampshire Fish and Game | D3: state
A4: New Hampshire | B4: John Kanter | C4: New Hampshire Fish and Game | D4: state
A5: New Hampshire | B5: Emily Preston | C5: New Hampshire Fish and Game | D5: state
A6: New Hampshire | B6: Michael Marchand | C6: New Hampshire Fish and Game | D6: state
A7: New Hampshire | B7: Loren Valliere | C7: New Hampshire Fish and Game | D7: state
A8: New Hampshire | B8: Pamela Hunt | C8: New Hampshire Audubon | D8: ngo-nongame
A9: New Hampshire | B9: Peter Bowman | C9: New Hampshire Natural Heritage | D9: state
A10: New Hampshire | B10: Peter Steckler | C10: The Nature Conservancy | D10: ngo-nongame
A11: New Hampshire | B11: Matthew Carpenter | C11: New Hampshire Fish and Game | D11: state
A12: New Hampshire | B12: Heidi Holman | C12: New Hampshire Fish and Game | D12: state
... A37: New Hampshire | B37: Liz Willey | C37: Antioch University New England | D37: school
A38: New Hampshire | B38: David Publicover | C38: Appalachian Mountain Club | D38: ngo-nongame | F38: Total Number of Agencies | G38: =counta(F3:F35) -> 33
A39: New Hampshire | B39: Dianna Schulte | C39: Blue Ocean Society | D39: ngo-nongame
A40: New Hampshire | B40: Jennifer Kennedy | C40: Blue Ocean Society | D40: ngo-nongame
A41: New Hampshire | B41: Shannon Kearney | C41: Connecticut Department of Energy and Environmental Protection | D41: state
A42: New Hampshire | B42: Ethan Nedeau | C42: Consultant | D42: independent
A43: New Hampshire | B43: Craig Rennie | C43: New Hampshire Department of Environmental Services | D43: state
A44: New Hampshire | B44: Mary Ann Tilton | C44: New Hampshire Department of Environmental Services | D44: state
A45: New Hampshire | B45: Sandy Crystall | C45: New Hampshire Department of Environmental Services | D45: state
A46: New Hampshire | B46: Ken Desmarais | C46: New Hampshire Department of Resources and Economic Development | D46: state
A47: New Hampshire | B47: Kyle Lombard | C47: New Hampshire Department of Resources and Economic Development | D47: state
A48: New Hampshire | B48: Susan Francher | C48: New Hampshire Department of Resources and Economic Development | D48: state
A49: New Hampshire | B49: William Nichols | C49: New Hampshire Department of Resources and Economic Development | D49: state
A50: New Hampshire | B50: Rick Van de Poll | C50: Ecosystem Management Consultants | D50: business
... A105: New Hampshire | B105: Tin Smith | C105: Wells National Estuarine Research Reserve | D105: federal

Sheet New Jersey
A1: state | B1: name | C1: agency | D1: type
A2: New Jersey | B2: David Jenkins | C2: New Jersey Department of Environmental Protection | D2: state
A3: New Jersey | B3: Kris Schantz | C3: New Jersey Department of Environmental Protection | D3: state
A4: New Jersey | B4: Kathy Clark | C4: New Jersey Department of Environmental Protection | D4: state
A5: New Jersey | B5: John Heilferty | C5: New Jersey Department of Environmental Protection | D5: state
A6: New Jersey | B6: Jeanette Bowers-Altman | C6: New Jersey Department of Environmental Protection | D6: state
A7: New Jersey | B7: Christina Davis | C7: New Jersey Department of Environmental Protection | D7: state
A8: New Jersey | B8: Amanda Dey | C8: New Jersey Department of Environmental Protection | D8: state
A9: New Jersey | B9: Gretchen Fowles | C9: New Jersey Department of Environmental Protection | D9: state
A10: New Jersey | B10: MacKenzie Hall | C10: New Jersey Department of Environmental Protection | D10: state | F10: Names/Number of People Not Given
A11: New Jersey | B11: Brian Melendez | C11: New Jersey Department of Environmental Protection | D11: state
A12: New Jersey | B12: Shawn Crouse | C12: New Jersey Department of Environmental Protection | D12: state
A13: New Jersey | B13: Greg Hinks | C13: New Jersey Department of Environmental Protection | D13: state
A14: New Jersey | B14: Larry Herrighty | C14: New Jersey Department of Environmental Protection | D14: state
A15: New Jersey | B15: David Chanda | C15: New Jersey Department of Environmental Protection | D15: state
A16: New Jersey | B16: Dave Golden | C16: New Jersey Department of Environmental Protection | D16: state
A17: New Jersey | B17: Rich Boornazian | C17: New Jersey Department of Environmental Protection | D17: state
A18: New Jersey | B18: Kathleen Walz | C18: New Jersey Department of Environmental Protection | D18: state
A19: New Jersey | B19: Rick Lathrop | C19: New Jersey Endangered and Nongame Species Advisory Committee | D19: state
A20: New Jersey | B20: James Applegate | C20: New Jersey Endangered and Nongame Species Advisory Committee | D20: state
A21: New Jersey | B21: Barbara Brummer | C21: New Jersey Endangered and Nongame Species Advisory Committee | D21: state
A22: New Jersey | B22: Joanna Burger | C22: New Jersey Endangered and Nongame Species Advisory Committee | D22: state
... A47: state | B47: name | C47: agency | D47: type
A48: New Jersey | C48: New Jersey Audubon Society | D48: ngo-nongame
A49: New Jersey | C49: New Jersey Conservation Foundation | D49: ngo-nongame
A50: New Jersey | C50: The Nature Conservancy | D50: ngo-nongame
A51: New Jersey | C51: New Jersey Pinelands Commission | D51: state | F51: Total Number of Agencies (excluding Unaffiliated and Independent) | G51: =counta(F3,F5:F7,F12:F43,F45:F48) -> 40
A52: New Jersey | C52: D&R Greenway Land Trust | D52: ngo-nongame
A53: New Jersey | C53: US Fish and Wildlife Service USFWS | D53: federal
A54: New Jersey | C54: Edwin B Forsythe National Wildlife Refuge | D54: federal
A55: New Jersey | C55: Cape May National Wildlife Refuge | D55: federal
A56: New Jersey | C56: Supawna Meadows National Wildlife Refuge | D56: federal
A57: New Jersey | C57: Great Swamp National Wildlife Refuge | D57: federal
A58: New Jersey | C58: Wallkill River National Wildlife Refuge | D58: federal
A59: New Jersey | C59: National Park Service | D59: federal
A60: New Jersey | C60: US Department of Defense DOD | D60: federal
A61: New Jersey | C61: Natural Resources Conservation Service NRCS | D61: federal
A62: New Jersey | C62: New Jersey State Forestry Service | D62: state
A63: New Jersey | C63: Atlantic City Electric | D63: utility
... A84: New Jersey | C84: Monmouth University | D84: school

Sheet New Mexico
A1: state | B1: name | C1: agency | D1: type
A2: New Mexico | B2: V Ryan | C2: US Bureau of Reclamation | D2: federal
A3: New Mexico | B3: L Walton | C3: US Bureau of Reclamation | D3: federal
A4: New Mexico | B4: M Porter | C4: US Army Corps of Engineers | D4: federal
A5: New Mexico | B5: S Ryan | C5: US Army Corps of Engineers | D5: federal
A6: New Mexico | B6: M Ramsey | C6: US Bureau of Land Management | D6: federal
A7: New Mexico | B7: J Sherman | C7: US Bureau of Land Management | D7: federal
A8: New Mexico | B8: B Dykstra | C8: US Forest Service USFS | D8: federal
A9: New Mexico | B9: S Sartorius | C9: US Forest Service USFS | D9: federal
A10: New Mexico | B10: K Granillo | C10: US Fish and Wildlife Service USFWS | D10: federal
A11: New Mexico | B11: L Bonner | C11: US Fish and Wildlife Service USFWS | D11: federal
A12: New Mexico | B12: M Wrigley | C12: National Park Service | D12: federal
... A35: New Mexico | B35: N Ashcroft | C35: New Mexico State University | D35: school
A36: New Mexico | B36: D Cram | C36: New Mexico State University | D36: school | F36: Total Number of Agencies | G36: =counta(F3:F33) -> 31
A37: New Mexico | B37: K Boykin | C37: New Mexico State University | D37: school
A38: New Mexico | B38: B Dunn | C38: Big Picture Conservation | D38: ngo-nongame
A39: New Mexico | B39: R Jennings | C39: Western New Mexico University | D39: school
A40: New Mexico | B40: B Christman | C40: Consultant | D40: independent
A41: New Mexico | B41: J Jacobi | C41: Consultant | D41: independent
A42: New Mexico | B42: A Burdett | C42: New Mexico Museum of Natural History and Science | D42: ngo-nongame
A43: New Mexico | B43: M Darr | C43: New Mexico Department of Game and Fish | D43: state
A44: New Mexico | B44: K Madden | C44: New Mexico Department of Game and Fish | D44: state
A45: New Mexico | B45: S Cary | C45: New Mexico Audubon | D45: ngo-nongame
A46: New Mexico | B46: J McIntyre | C46: US Fish and Wildlife Service USFWS | D46: federal
A47: New Mexico | B47: E Metzler | C47: Consultant | D47: independent
A48: New Mexico | B48: J Stuart | C48: New Mexico Department of Game and Fish | D48: state
... A100: New Mexico | B100: H Reiser | C100: Consultant | D100: independent

Sheet New York

Sheet North Carolina
A1: state | B1: name | C1: agency | D1: type
A2: North Carolina | B2: Cindy Carr | C2: North Carolina Wildlife Resources Commission | D2: state
A3: North Carolina | B3: Allen Boynton | C3: North Carolina Wildlife Resources Commission | D3: state
A4: North Carolina | B4: Ken Bridle | C4: Piedmont Land Conservancy | D4: ngo-nongame
A5: North Carolina | B5: Shannon Deaton | C5: North Carolina Wildlife Resources Commission | D5: state
A6: North Carolina | B6: Todd Ewing | C6: North Carolina Wildlife Resources Commission | D6: state
A7: North Carolina | B7: Chris McGrath | C7: North Carolina Wildlife Resources Commission | D7: state
A8: North Carolina | B8: David Sawyer | C8: North Carolina Wildlife Resources Commission | D8: state
A9: North Carolina | B9: Perry Sumner | C9: North Carolina Wildlife Resources Commission | D9: state
A10: North Carolina | B10: Dave Allen | C10: North Carolina Wildlife Resources Commission | D10: state
A11: North Carolina | B11: Scott Anderson | C11: North Carolina Wildlife Resources Commission | D11: state
A12: North Carolina | B12: Steve Fraley | C12: North Carolina Wildlife Resources Commission | D12: state
... A26: North Carolina | B26: Ed Corey | C26: North Carolina Division of Parks and Recreation | D26: state
A27: North Carolina | B27: Sara Finn | C27: North Carolina Wildlife Resources Commission | D27: state | F27: Names/Number of People Not Given
A28: North Carolina | B28: Gabrielle Graeter | C28: North Carolina Wildlife Resources Commission | D28: state
A29: North Carolina | B29: Jeff Humphries | C29: North Carolina Wildlife Resources Commission | D29: state
A30: North Carolina | B30: Lori Williams | C30: North Carolina Wildlife Resources Commission | D30: state
A31: North Carolina | B31: Joe Carpenter | C31: North Carolina Wildlife Resources Commission | D31: state
A32: North Carolina | B32: Walker Golder | C32: Audubon North Carolina | D32: ngo-nongame
A33: North Carolina | B33: Mark Jones | C33: North Carolina Wildlife Resources Commission | D33: state
A34: North Carolina | B34: Christine Kelly | C34: North Carolina Wildlife Resources Commission | D34: state
A35: North Carolina | B35: Harry LeGrand | C35: North Carolina Natural Heritage Program | D35: ngo-nongame
A36: North Carolina | B36: Curtis Smalling | C36: Audubon North Carolina | D36: ngo-nongame
A37: North Carolina | B37: John Stanton | C37: US Fish and Wildlife Service USFWS | D37: federal
A38: North Carolina | B38: Craig Watson | C38: US Fish and Wildlife Service USFWS | D38: federal
A39: North Carolina | B39: Tyler Black | C39: North Carolina Wildlife Resources Commission | D39: state
... A61: North Carolina | B61: Nancy Adamson | C61: Natural Resources Conservation Service NRCS | D61: federal
A62: North Carolina | B62: John Amoroso | C62: North Carolina Department of Parks and Recreation | D62: state | F62: Total Number of Agencies | G62: =counta(F3:F24,F29:F59) -> 53
A63: North Carolina | B63: Susan Cameron | C63: US Fish and Wildlife Service USFWS | D63: federal
A64: North Carolina | B64: Steve Hall | C64: North Carolina Natural Heritage Program | D64: ngo-nongame
A65: North Carolina | B65: Kathleen Kidd | C65: North Carolina Department of Agriculture and Consumer Services | D65: state
A66: North Carolina | B66: Andrea Leslie | C66: North Carolina Wildlife Resources Commission | D66: state
A67: North Carolina | B67: Dave Lenat | C67: North Carolina Division of Water Quality | D67: state
A68: North Carolina | B68: Dave Penrose | C68: North Carolina Division of Water Quality | D68: state
A69: North Carolina | B69: David Stephan | C69: North Carolina State University | D69: school
A70: North Carolina | B70: David Tarpy | C70: North Carolina State University | D70: school
A71: North Carolina | B71: Rob Trickel | C71: North Carolina Forest Service | D71: state
A72: state | B72: name | C72: agency | D72: type
A73: North Carolina | C73: National Park Service | D73: federal
A74: North Carolina | C74: US Forest Service USFS | D74: federal
A75: North Carolina | C75: US Geological Survey USGS | D75: federal
A76: North Carolina | C76: Clean Water Management Trust Fund | D76: state
A77: North Carolina | C77: Georgia Museum of Natural History | D77: school
A78: North Carolina | C78: North Carolina Department of Environment and Natural Resources | D78: state
A79: North Carolina | C79: North Carolina Department of Transportation | D79: state
A80: North Carolina | C80: Ohio Department of Natural Resources | D80: state
A81: North Carolina | C81: Virginia Department of Game and Inland Fisheries | D81: state
A82: North Carolina | C82: Duke (Progress) Energy | D82: utility
A83: North Carolina | C83: Unique Places Land Conservation, Restoration and Management | D83: ngo-nongame
A84: North Carolina | C84: Weyerhaeuser | D84: business
... A103: North Carolina | C103: The Xerces Society | D103: ngo-nongame

Sheet North Dakota
A1: state | B1: name | C1: agency | D1: type | F1: Plan references consulting with multiple people, but does not list
A2: North Dakota | B2: Steve Dyke | C2: North Dakota Game and Fish Department | D2: state
A3: North Dakota | B3: Sandra Johnson | C3: North Dakota Game and Fish Department | D3: state
A4: North Dakota | B4: Patrick Isakson | C4: North Dakota Game and Fish Department | D4: state
A5: North Dakota | B5: Terry Steinwand | C5: North Dakota Game and Fish Department | D5: state
A6: North Dakota | B6: Greg Link | C6: North Dakota Game and Fish Department | D6: state | F6: Total Number of Agencies | G6: =counta(F3) -> 1

Sheet Ohio

Sheet Oklahoma
A1: state | B1: name | C1: agency | D1: type
A2: Oklahoma | B2: Jena Donnell | C2: Oklahoma Department of Wildlife Conservation | D2: state
A3: Oklahoma | B3: Rich Fuller | C3: Oklahoma Department of Wildlife Conservation | D3: state
A4: Oklahoma | B4: Matt Fullerton | C4: Oklahoma Department of Wildlife Conservation | D4: state
A5: Oklahoma | B5: Melynda Hickman | C5: Oklahoma Department of Wildlife Conservation | D5: state
A6: Oklahoma | B6: Russ Horton | C6: Oklahoma Department of Wildlife Conservation | D6: state
A7: Oklahoma | B7: Mirk Howery | C7: Oklahoma Department of Wildlife Conservation | D7: state
A8: Oklahoma | B8: Kurt Kuklinski | C8: Oklahoma Department of Wildlife Conservation | D8: state
A9: Oklahoma | B9: Doug Schoeling | C9: Oklahoma Department of Wildlife Conservation | D9: state
A10: Oklahoma | B10: Curtis Tackett | C10: Oklahoma Department of Wildlife Conservation | D10: state
A11: Oklahoma | B11: David Arbour | C11: Oklahoma Ornithological Society | D11: ngo-nongame
A12: Oklahoma | B12: Anita Barstow | C12: US Fish and Wildlife Service USFWS | D12: federal
... A42: Oklahoma | B42: Daniel Fenner | C42: US Fish and Wildlife Service USFWS | D42: federal
A43: Oklahoma | B43: Jane Fitzgerald | C43: Central Hardwoods Joint Venture | D43: partnership | F43: Total Number of Agencies (excluding independent) | G43: =counta(F3:F9,F11:F40) -> 37
A44: Oklahoma | B44: Stanley Fox | C44: Oklahoma State University | D44: school
A45: Oklahoma | B45: Jim Giocomo | C45: Oaks and Prairies Joint Venture | D45: partnership
A46: Oklahoma | B46: Claudia Glass | C46: Rogers State University | D46: school
A47: Oklahoma | B47: Don Glass | C47: Rogers State University | D47: school
A48: Oklahoma | B48: Joe Grzybowski | C48: University of Central Oklahoma | D48: school
A49: Oklahoma | B49: Jeff Haase | C49: US Fish and Wildlife Service USFWS | D49: federal
A50: Oklahoma | B50: Bob Hamilton | C50: The Nature Conservancy | D50: ngo-nongame
A51: Oklahoma | B51: Richard Hatcher | C51: Oklahoma Department of Wildlife Conservation | D51: state
A52: Oklahoma | B52: John Hendrix | C52: US Fish and Wildlife Service USFWS | D52: federal
A53: Oklahoma | B53: Steve Hensley | C53: US Fish and Wildlife Service USFWS | D53: federal
A54: Oklahoma | B54: Karen Hickman | C54: Oklahoma State University | D54: school
A55: Oklahoma | B55: Chris Hise | C55: The Nature Conservancy | D55: ngo-nongame
... A147: Oklahoma | B147: Melinda West | C147: Oklahoma Master Naturalists Program | D147: school

Sheet Oregon
A1: state | B1: name | C1: agency | D1: type
A2: Oregon | B2: Mark Nystrom | C2: Association of Oregon Counties | D2: ngo-nongame
A3: Oregon | B3: Bob Bovett | C3: Association of Oregon Counties | D3: ngo-nongame
A4: Oregon | B4: Bob Sallinger | C4: Audubon Society of Portland | D4: ngo-nongame
A5: Oregon | B5: Kelley Beamer | C5: Coalition of Oregon Land Trusts | D5: ngo-nongame
A6: Oregon | B6: Elizabeth Ruther | C6: Defenders of Wildlife | D6: ngo-nongame
A7: Oregon | B7: Sara Vickerman | C7: Institute for Natural Resources | D7: school
A8: Oregon | B8: Cathy MacDonald | C8: The Nature Conservancy | D8: ngo-nongame
A9: Oregon | B9: Ryan Gordon | C9: Network of Oregon Watershed Councils | D9: ngo-nongame
A10: Oregon | B10: Mark Saelens | C10: Oregon Association of Conservation Districts | D10: ngo-nongame
A11: Oregon | B11: Jerry Nicolescu | C11: Oregon Association of Conservation Districts | D11: ngo-nongame
A12: Oregon | B12: Jerome Rosa | C12: Oregon Cattlemens Association | D12: ngo-consumptive
... A76: Oregon | B76: Dana Ross | C76: Consultant | D76: independent
A77: Oregon | B77: Al Smith | C77: Consultant | D77: independent | F77: Names/Number of People Not Given
A78: Oregon | B78: Rebecca Currin | C78: Institute for Applied Ecology | D78: ngo-nongame
A79: Oregon | B79: Jimmy Kagan | C79: Oregon State University | D79: school
A80: Oregon | B80: Theresa Burscu | C80: Portland State University | D80: school
A81: Oregon | B81: Michael Wetter | C81: Intertwine Alliance | D81: ngo-nongame
A82: Oregon | B82: David Cohen | C82: Intertwine Alliance | D82: ngo-nongame
A83: Oregon | B83: John Alexander | C83: Klamath Bird Observatory | D83: ngo-nongame
A84: Oregon | B84: Kate Halstead | C84: Klamath Bird Observatory | D84: ngo-nongame
A85: Oregon | B85: Tracy Rutten | C85: League of Oregon Cities | D85: ngo-nongame
A86: Oregon | B86: Erin Doyle | C86: League of Oregon Cities | D86: ngo-nongame | F86: Total Number of Agencies | G86: =counta(F3:F74,F79:F83) -> 77
A87: Oregon | B87: Carol Macbeth | C87: Lewis and Clark College | D87: school
A88: Oregon | B88: Steve Buttrick | C88: The Nature Conservancy | D88: ngo-nongame
A89: Oregon | B89: Dan Bell | C89: The Nature Conservancy | D89: ngo-nongame
A90: Oregon | B90: Debbie Pickering | C90: The Nature Conservancy | D90: ngo-nongame
A91: Oregon | B91: Gway Kirchner | C91: The Nature Conservancy | D91: ngo-nongame
A92: Oregon | B92: Leslie Bach | C92: The Nature Conservancy | D92: ngo-nongame
A93: Oregon | B93: Mark Stern | C93: The Nature Conservancy | D93: ngo-nongame
A94: Oregon | B94: Michael Schindel | C94: The Nature Conservancy | D94: ngo-nongame
A95: Oregon | B95: Ken Popper | C95: The Nature Conservancy | D95: ngo-nongame
A96: Oregon | B96: Eleanor Gaines | C96: Oregon Biodiversity Information Center | D96: school
A97: Oregon | B97: Kelly Amsberry | C97: Oregon Department of Agriculture | D97: state
A98: Oregon | B98: Jordan Brown | C98: Oregon Department of Agriculture | D98: state
... A266: state | B266: name | C266: agency | D266: type
A267: Oregon | C267: Confederated Tribes of Coos, Lower Umpqua, and Suislaw Indians | D267: indigenous
A268: Oregon | C268: Confederated Tribes of the Grand Ronde | D268: indigenous
A269: Oregon | C269: Confederated Tribes of Siletz Indians of Oregon | D269: indigenous
A270: Oregon | C270: Confederated Tribes of the Umatilla Indian Reservation | D270: indigenous
A271: Oregon | C271: Confederated Tribes of Warm Springs | D271: indigenous

Sheet Pennsylvania
A1: state | B1: name | C1: agency | D1: type
A2: Pennsylvania | B2: Jennifer DeCecco | C2: Pennsylvania Game Commission | D2: state
A3: Pennsylvania | B3: Catherine Haffner | C3: Pennsylvania Game Commission | D3: state
A4: Pennsylvania | B4: Diana Day | C4: Pennsylvania Fish and Boat Commission | D4: state
A5: Pennsylvania | B5: Scott Weidensaul | C5: Project Owlnet | D5: ngo-nongame
A6: Pennsylvania | B6: Joseph Tavano | C6: Pennsylvania Game Commission | D6: state
A7: Pennsylvania | B7: Elizabeth Crisfield | C7: Pennsylvania Game Commission | D7: state
A8: Pennsylvania | B8: Joseph Kosack | C8: Pennsylvania Game Commission | D8: state
A9: Pennsylvania | B9: Daniel Brauning | C9: Pennsylvania Game Commission | D9: state
A10: Pennsylvania | B10: Christopher Urban | C10: Pennsylvania Fish and Boat Commission | D10: state
A11: Pennsylvania | B11: Nate Zalik | C11: Pennsylvania Game Commission | D11: state
A12: Pennsylvania | B12: R Matthew Hough | C12: Pennsylvania Game Commission | D12: state
... A81: Pennsylvania | B81: Justin Vreeland | C81: Pennsylvania Game Commission | D81: state
A82: Pennsylvania | B82: Jeffrey Wagner | C82: Western Pennsylvania Conservancy | D82: ngo-nongame | F82: Total Number of Agencies | G82: =counta(F3:F79) -> 77
A83: Pennsylvania | B83: Nathan Welker | C83: US Forest Service USFS | D83: federal
A84: Pennsylvania | B84: Ephraim Zimmerman | C84: Western Pennsylvania Conservancy | D84: ngo-nongame
A85: Pennsylvania | B85: Matthew Lovallo | C85: Pennsylvania Game Commission | D85: state
A86: Pennsylvania | B86: Tyler Wagner | C86: US Geological Survey USGS | D86: federal
A87: Pennsylvania | B87: David Yeany | C87: Western Pennsylvania Conservancy | D87: ngo-nongame
A88: Pennsylvania | B88: Laurel Anders | C88: Pennsylvania Fish and Boat Commission | D88: state
A89: Pennsylvania | B89: Eric Levis | C89: Pennsylvania Fish and Boat Commission | D89: state
A90: Pennsylvania | B90: Brittany Howell | C90: Pennsylvania Game Commission | D90: state
A91: Pennsylvania | B91: Timothy Klinger | C91: Pennsylvania Fish and Boat Commission | D91: state
A92: Pennsylvania | B92: Travis Lau | C92: Pennsylvania Game Commission | D92: state
A93: Pennsylvania | B93: Lori Neely | C93: Pennsylvania Game Commission | D93: state
A94: Pennsylvania | B94: Joe Neville | C94: Pennsylvania Game Commission | D94: state
... A247: Pennsylvania | B247: Chen Young | C247: Carnegie Museum of Natural History | D247: ngo-nongame

Sheet Rhode Island
A1: state | B1: name | C1: agency | D1: type
A2: Rhode Island | B2: Scott Comings | C2: The Nature Conservancy | D2: ngo-nongame
A3: Rhode Island | B3: John O'Brien | C3: The Nature Conservancy | D3: ngo-nongame
A4: Rhode Island | B4: Jay Osenkowski | C4: Rhode Island Department of Environmental Management | D4: state
A5: Rhode Island | B5: Chris Raithel | C5: Rhode Island Department of Environmental Management | D5: state
A6: Rhode Island | B6: Sue Kiernan | C6: Rhode Island Department of Environmental Management | D6: state
A7: Rhode Island | B7: Catherine Sparks | C7: Rhode Island Department of Environmental Management | D7: state
A8: Rhode Island | B8: Peter Paton | C8: University of Rhode Island | D8: school
A9: Rhode Island | B9: Karen Terwilliger | C9: Terwilliger Consulting | D9: business
A10: Rhode Island | B10: Amanda Freitas | C10: Rhode Island Natural History Survey | D10: ngo-nongame
A11: Rhode Island | B11: Tom Epstein | C11: Rhode Island Department of Environmental Management | D11: state
A12: Rhode Island | B12: Gail Mastrati | C12: Rhode Island Department of Environmental Management | D12: state
... A63: Rhode Island | B63: Rick McKinney | C63: Environmental Protection Agency | D63: federal
A64: Rhode Island | B64: Leland Mello | C64: Natural Resources Conservation Service NRCS | D64: federal | F64: Total Number of Agencies | G64: =counta(F3:F61) -> 59
A65: Rhode Island | B65: Lou Perotti | C65: Roger Williams Park Zoo | D65: ngo-nongame
A66: Rhode Island | B66: Susan Adamowicz | C66: US Fish and Wildlife Service USFWS | D66: federal
A67: Rhode Island | B67: Sheldon Pratt | C67: University of Rhode Island | D67: school
A68: Rhode Island | B68: Evan Preisser | C68: University of Rhode Island | D68: school
A69: Rhode Island | B69: Dave Reis | C69: Coastal Resources Management Council | D69: state
A70: Rhode Island | B70: Malia Schwartz | C70: University of Rhode Island | D70: school
A71: Rhode Island | B71: Shawna Smith | C71: Rhode Island Department of Environmental Management | D71: state
A72: Rhode Island | B72: Charlotte Sornberger | C72: Audubon Society of Rhode Island | D72: ngo-nongame
A73: Rhode Island | B73: Caleb Speigel | C73: US Fish and Wildlife Service USFWS | D73: federal
A74: Rhode Island | B74: Linda Steere | C74: Applied Bio-Systems | D74: business
A75: Rhode Island | B75: Terry Sullivan | C75: The Nature Conservancy | D75: ngo-nongame
A76: Rhode Island | B76: Jim Tappero | C76: Rhode Island Ducks Unlimited | D76: ngo-consumptive
... A148: Rhode Island | B148: Cheryl Wiitala | C148: The Nature Conservancy | D148: ngo-nongame

Sheet South Carolina
A1: state | B1: name | C1: agency | D1: type
A2: South Carolina | B2: Craig Allen | C2: South Carolina Cooperative Fish and Wildlife Research Unit | D2: partnership
A3: South Carolina | B3: Buddy Baker | C3: South Carolina Department of Natural Resources | D3: state
A4: South Carolina | B4: Judy Barnes | C4: South Carolina Department of Natural Resources | D4: state
A5: South Carolina | B5: Mary Bunch | C5: South Carolina Department of Natural Resources | D5: state
A6: South Carolina | B6: Jay Butfiloski | C6: South Carolina Department of Natural Resources | D6: state
A7: South Carolina | B7: Julia Byrd | C7: South Carolina Department of Natural Resources | D7: state
A8: South Carolina | B8: John Cely | C8: South Carolina Department of Natural Resources | D8: state
A9: South Carolina | B9: Mary Clark | C9: North Carolina Museum of Natural Sciences | D9: ngo-nongame
A10: South Carolina | B10: David Cupka | C10: South Carolina Department of Natural Resources | D10: state
A11: South Carolina | B11: Rickie Davis | C11: Clemson University | D11: school
A12: South Carolina | B12: Steve Fields | C12: Culture and Heritage Museums | D12: ngo-nongame
... A66: South Carolina | B66: Jeff Beane | C66: North Carolina Museum of Natural History | D66: ngo-nongame
A67: South Carolina | B67: Steve Bennett | C67: South Carolina Department of Natural Resources | D67: state | F67: Total Number of Agencies | G67: =counta(F3:F64) -> 62
A68: South Carolina | B68: Eric Billings | C68: Charleston Turtle and Tortoise Society | D68: ngo-nongame
A69: South Carolina | B69: Denise Billings | C69: Charleston Turtle and Tortoise Society | D69: ngo-nongame
A70: South Carolina | B70: Rick Blob | C70: Clemson University | D70: school
A71: South Carolina | B71: Alvin Braswell | C71: North Carolina Museum of Natural History | D71: ngo-nongame
A72: South Carolina | B72: Kurt Buhlmann | C72: Savannah River Ecology Laboratory | D72: school
A73: South Carolina | B73: Carlos Camp | C73: Piedmont College | D73: school
A74: South Carolina | B74: Jeffrey Camper | C74: Francis Marion University | D74: school
A75: South Carolina | B75: Joshua Castleberry | C75: University of South Carolina | D75: school
A76: South Carolina | B76: Heyward Clamp | C76: Edisto Island Serpentarium | D76: business
A77: South Carolina | B77: Mark Danaher | C77: US Forest Service USFS | D77: federal
A78: South Carolina | B78: Mike Dorcas | C78: Davidson College | D78: school
A79: South Carolina | B79: Mary Lang Edwards | C79: Erskine College | D79: school
... A220: South Carolina | B220: Herrick Brown | C220: South Carolina Department of Natural Resources | D220: state

Sheet South Dakota
A1: state | B1: name | C1: agency | D1: type
A2: South Dakota | B2: Eileen Dowd Stukel | C2: South Dakota Game, Fish and Parks | D2: state
A3: South Dakota | B3: Jon Haufler | C3: Ecosystem Management Research Institute | D3: ngo-nongame
A4: South Dakota | B4: Casey Heimerl | C4: South Dakota Game, Fish and Parks | D4: state
A5: South Dakota | B5: Silka Kempema | C5: South Dakota Game, Fish and Parks | D5: state
A6: South Dakota | B6: John Lott | C6: South Dakota Game, Fish and Parks | D6: state
A7: South Dakota | B7: Carolyn Mehl | C7: Ecosystem Management Research Institute | D7: ngo-nongame
A8: South Dakota | B8: Dave Ode | C8: South Dakota Game, Fish and Parks | D8: state
A9: South Dakota | B9: Chelsey Pasbrig | C9: South Dakota Game, Fish and Parks | D9: state
A10: South Dakota | B10: Chad Switzer | C10: South Dakota Game, Fish and Parks | D10: state | F10: Names/Number of People Not Given
A11: South Dakota | B11: Nathan Baker | C11: South Dakota Game, Fish and Parks | D11: state
A12: South Dakota | B12: Andrew Burgess | C12: South Dakota Game, Fish and Parks | D12: state
A13: South Dakota | B13: Ruth Howell | C13: South Dakota Game, Fish and Parks | D13: state
A14: South Dakota | B14: Larry Gigliotti | C14: South Dakota Game, Fish and Parks | D14: state
A15: South Dakota | B15: Cynthia Longmire | C15: South Dakota Game, Fish and Parks | D15: state
A16: South Dakota | B16: Christopher Marsh | C16: South Dakota Game, Fish and Parks | D16: state
A17: South Dakota | B17: Chelsea Krause | C17: South Dakota Game, Fish and Parks | D17: state
A18: South Dakota | B18: Heather Berg | C18: South Dakota Game, Fish and Parks | D18: state
A19: South Dakota | B19: David Freidel | C19: South Dakota Game, Fish and Parks | D19: state
A20: South Dakota | B20: Anna Schmidt | C20: US Fish and Wildlife Service USFWS | D20: federal
A21: South Dakota | B21: Michael Cotter | C21: US Fish and Wildlife Service USFWS | D21: federal
A22: South Dakota | B22: Rick Schneider | C22: Nebraska Game and Parks Commission | D22: state
... A25: state | B25: name | C25: agency | D25: type
A26: South Dakota | C26: US Bureau of Land Management | D26: federal
A27: South Dakota | C27: US Bureau of Reclamation | D27: federal
A28: South Dakota | C28: Bureau of Indian Affairs | D28: indigenous
A29: South Dakota | C29: US Forest Service USFS | D29: federal
A30: South Dakota | C30: Badlands National Park | D30: federal
A31: South Dakota | C31: Wind Cave National Park | D31: federal
A32: South Dakota | C32: Jewel Cave National Park | D32: federal
A33: South Dakota | C33: Cheyenne River Sioux Tribe | D33: indigenous
A34: South Dakota | C34: Oglala Sioux Tribe | D34: indigenous
A35: South Dakota | C35: Oglala Sioux Parks and Recreation Authority | D35: indigenous
A36: South Dakota | C36: Standing Rock Sioux Tribe | D36: indigenous
A37: South Dakota | C37: Crow Creek Sioux Tribe | D37: indigenous
... A45: South Dakota | C45: Prairie Pothole Joint Venture | D45: partnership
A46: South Dakota | C46: Northern Great Plains Joint Venture | D46: partnership | F46: Total Number of Agencies | G46: =counta(F3:F7,F12:F43) -> 37
A47: South Dakota | C47: South Dakota Department of Environment and Natural Resources | D47: state
A48: South Dakota | C48: South Dakota Department of Agriculture | D48: state
A49: South Dakota | C49: South Dakota Department of Transportation | D49: state
A50: South Dakota | C50: South Dakota Department of Tribal Relations | D50: state
A51: South Dakota | C51: University of South Dakota | D51: school
A52: South Dakota | C52: Black Hills State University | D52: school
A53: South Dakota | C53: Northern State University | D53: school
A54: South Dakota | C54: South Dakota Office of School and Public Lands | D54: state
A55: South Dakota | C55: US Army Corps of Engineers | D55: federal
A56: South Dakota | C56: South Dakota Governors Office | D56: state
A57: South Dakota | C57: Northern Prairies Land Trust | D57: ngo-nongame

Sheet Tennessee
A1: state | B1: name | C1: agency | D1: type
A2: Tennessee | B2: Bill Reeves | C2: Tennessee Wildlife Resources Agency | D2: state
A3: Tennessee | B3: Sally Palmer | C3: The Nature Conservancy | D3: ngo-nongame
A4: Tennessee | B4: Gregg Elliott | C4: K Gregg Consulting | D4: business
A5: Tennessee | B5: Joseph Wisby | C5: The Nature Conservancy | D5: ngo-nongame
A6: Tennessee | B6: Rob Colvin | C6: Tennessee Wildlife Resources Agency | D6: state
A7: Tennessee | B7: Jeremy Dennison | C7: Tennessee Wildlife Resources Agency | D7: state
A8: Tennessee | B8: Josh Campbell | C8: Tennessee Wildlife Resources Agency | D8: state
A9: Tennessee | B9: Dustin Thames | C9: Tennessee Wildlife Resources Agency | D9: state
A10: Tennessee | B10: Terry Hopkins | C10: Tennessee Wildlife Resources Agency | D10: state
A11: Tennessee | B11: Chris Simpson | C11: Tennessee Wildlife Resources Agency | D11: state
A12: Tennessee | B12: Daniel Istvanko | C12: Tennessee Wildlife Resources Agency | D12: state
... A52: Tennessee | B52: Carl Williams | C52: Tennessee Wildlife Resources Agency | D52: state
A53: Tennessee | B53: Steve Ahlstedt | C53: US Geological Survey USGS | D53: federal | F53: Total Number of Agencies | G53: =counta(F3:F50) -> 48
A54: Tennessee | B54: Fred Alsop | C54: East Tennessee State University | D54: school
A55: Tennessee | B55: Katie Benson | C55: Lincoln Memorial University | D55: school
A56: Tennessee | B56: Tom Blanchard | C56: University of Tennessee | D56: school
A57: Tennessee | B57: Chris Brown | C57: Tennessee Technological University | D57: school
A58: Tennessee | B58: Brian Butterfield | C58: Freed Hardeman University | D58: school
A59: Tennessee | B59: Danny Bryan | C59: Cumberland University | D59: school
A60: Tennessee | B60: Ron Caldwell | C60: Lincoln Memorial University | D60: school
A61: Tennessee | B61: Brian Carver | C61: Tennessee Technological University | D61: school
A62: Tennessee | B62: Todd Crabtree | C62: Tennessee Department of Environment and Conservation | D62: state
A63: Tennessee | B63: Kristen Cecala | C63: University of the South | D63: school
A64: Tennessee | B64: Vince Cobb | C64: Middle Tennessee State University | D64: school
A65: Tennessee | B65: Dan Combs | C65: Tennessee Technological University | D65: school
... A141: Tennessee | B141: Ryan Hall | C141: Wolf River Conservancy | D141: ngo-nongame

Sheet Texas
A1: state | B1: name | C1: agency | D1: type
A2: Texas | B2: Julie Wicker | C2: Unknown | D2: unknown
A3: Texas | B3: Richard Heilbrun | C3: Unknown | D3: unknown
A4: Texas | B4: Tim Birdsong | C4: Texas Parks and Wildlife Department | D4: state
A5: Texas | B5: Dakus Geeslin | C5: Unknown | D5: unknown
A6: Texas | B6: John Davis | C6: Unknown | D6: unknown
A7: Texas | B7: Ross Winton | C7: Unknown | D7: unknown
A8: Texas | B8: Chelsea Acres | C8: Unknown | D8: unknown | F8: Total Number of Agencies (excluding unknown) | G8: =counta(F3:F4) -> 2
A9: Texas | B9: Trey Barron | C9: Unknown | D9: unknown
A10: Texas | B10: Hanna Bauer | C10: Unknown | D10: unknown
A11: Texas | B11: Megan Bean | C11: Texas Parks and Wildlife Department | D11: state
A12: Texas | B12: Lindsay Campbell | C12: Unknown | D12: unknown
A13: Texas | B13: Paul Crump | C13: Unknown | D13: unknown
A14: Texas | B14: Stephen Curtis | C14: Texas Parks and Wildlife Department | D14: state
A15: Texas | B15: Krysta Demere | C15: Unknown | D15: unknown
A16: Texas | B16: Jonah Evans | C16: Unknown | D16: unknown
A17: Texas | B17: Nathan Fuller | C17: Unknown | D17: unknown
A18: Texas | B18: Bob Gottfried | C18: Unknown | D18: unknown
A19: Texas | B19: Tania Homayoun | C19: Unknown | D19: unknown
A20: Texas | B20: Dana Karelus | C20: Unknown | D20: unknown
... A59: Texas | B59: Nathan Smith | C59: Texas Parks and Wildlife Department | D59: state

Sheet Utah
A1: state | B1: name | C1: agency | D1: type
A2: Utah | B2: Brian Allen | C2: US Fish and Wildlife Service USFWS | D2: federal
A3: Utah | B3: Lorien Belton | C3: Utah State University | D3: school
A4: Utah | B4: Paul Birdsey | C4: Utah Division of Wildlife Resources | D4: state
A5: Utah | B5: Casey Burns | C5: Natural Resources Conservation Service NRCS | D5: federal
A6: Utah | B6: Chris Crockett | C6: Utah Division of Wildlife Resources | D6: state
A7: Utah | B7: Jimi Gragg | C7: Utah Division of Wildlife Resources | D7: state
A8: Utah | B8: Betsey Herrmann | C8: US Fish and Wildlife Service USFWS | D8: federal
A9: Utah | B9: Kim Hersey | C9: Utah Division of Wildlife Resources | D9: state
A10: Utah | B10: Justin Jimenez | C10: US Bureau of Land Management | D10: federal
A11: Utah | B11: Allison Jones | C11: Wild Utah Project | D11: ngo-nongame
A12: Utah | B12: Chris Keleher | C12: Utah Department of Natural Resources | D12: state
... A20: Utah | B20: Mary Pendergast | C20: Wild Utah Project | D20: ngo-nongame
A21: Utah | B21: Mark Petersen | C21: Utah Farm Bureau Federation | D21: ngo-consumptive | F21: Total Number of Agencies | G21: =counta(F3:F18) -> 16
A22: Utah | B22: Jason Robinson | C22: Utah Division of Wildlife Resources | D22: state
A23: Utah | B23: Steve Slater | C23: Hawkwatch International | D23: ngo-nongame
A24: Utah | B24: Ben Sutter | C24: Utah Division of Wildlife Resources | D24: state
A25: Utah | B25: Tyler Thompson | C25: Utah Division of Wildlife Resources | D25: state
A26: Utah | B26: Joel Tuhy | C26: The Nature Conservancy | D26: ngo-nongame
A27: Utah | B27: Anis Aoude | C27: Utah Division of Wildlife Resources | D27: state
A28: Utah | B28: Carmen Bailey | C28: Utah Division of Wildlife Resources | D28: state
A29: Utah | B29: Phaedra Budy | C29: Utah State University | D29: school
A30: Utah | B30: Kevin Bunnell | C30: Utah Division of Wildlife Resources | D30: state
A31: Utah | B31: Tiffany Cummins | C31: US Fish and Wildlife Service USFWS | D31: federal
